Workbook

Sheet INDEX overview
A1: Model at a glance
A2: Item | B2: Summary
A3: Purpose of Index | B3: Compares jurisdiction readiness for credible coal-to-clean transition credit activity
A4: Country universe | B4: Jurisdictions with operating coal capacity recorded by GEM (eligibility gate) > with material transition opportunity (screening)
A5: Output | B5: Overall implementation readiness score, pillar scores and country ranking
A6: Scoring | B6: Indicators normalised to 0–100, weighted within pillars, then combined
A7: Data basis | B7: 2024 is the principal base year, with disclosed exceptions for dynamic trackers, multi-year windows and less frequently updated datasets
A8: Overlay | B8: Market-confidence evidence adjusts indicator weights, not country data
A9: Missing data | B9: Missing observations are estimated separately and clearly flagged
A12: Screening
A13: Stage | B13: Variable | C13: Rule or treatment | D13: Selected central threshold | E13: Current result | F13: Notes
A14: Eligibility gate | B14: Operating coal capacity | C14: Pass when operating coal capacity is greater than zero | D14: Greater than 0 MW | E14: 73 eligible jurisdictions | F14: No GEM country record is treated as zero recorded operating capacity
A15: Material-opportunity screen | B15: Operating coal capacity | C15: One of three opportunity conditions | D15: 1,907 MW | F15: Median threshold among eligible jurisdictions
A16: Material-opportunity screen | B16: Coal generation share | C16: One of three opportunity conditions | D16: 20.260% | F16: Threshold derived from reported Ember data; documented estimates may be used to screen a country
A17: Material-opportunity screen | B17: Estimated lifetime CO₂ | C17: One of three opportunity conditions | D17: 70.511 Mt | F17: Country-level source calculation from WIP.xlsx
A18: Material-opportunity screen | B18: Minimum conditions | C18: Meet at least two of the three opportunity conditions | D18: 2 of 3 | E18: 36 pass; 37 fail | F18: Central scenario selected for the base index
A20: Pillar overview
A21: Pillar | B21: Overall weight | C21: Key treatment
A22: Pillar 1: Energy system conditions | B22: 0.2 | C22: Operating coal capacity and coal share are screening variables. They remain visible for audit but have zero Pillar 1 weight
A23: Pillar 2: Policy and transition commitment | B23: 0.2 | C23: Combines policy infrastructure, transition direction and documented coal-phaseout implementation. Expansion and construction inputs are already ratios
A24: Pillar 3: Governance and institutional capacity | B24: 0.15 | C24: World Bank governance indicators are already converted to comparable 0–100 scores
A25: Pillar 4: Carbon market maturity | B25: 0.2 | C25: VCM indicators use logarithmic scaling. Article 6 indicators use institutional milestones and implementation-stage scores
A26: Pillar 5: Macro-financial conditions | B26: 0.15 | C26: Higher financial depth is favourable. High inflation, debt pressure and exchange-rate instability reduce readiness
A27: Pillar 6: Just transition and social credibility | B27: 0.1 | C27: The resilience indicator combines social-protection coverage and HDI. Unemployment represents labour-market absorption risk
A30: Indicator reference
A31: Pillar | B31: Indicator | C31: Weight | D31: Data year | E31: Metric and source | F31: Scoring
A32: Screening | B32: Operating coal capacity | C32: 0 | D32: January 2026 | E32: Operating coal capacity, MW – GEM Global Coal Plant Tracker | F32: Eligibility requires capacity above 0 MW. Central opportunity condition requires at least 1,907 MW.
A33: Screening | B33: Coal share of electricity generation | C33: 0 | D33: 2024 | E33: Coal generation share, % – Ember | F33: Central opportunity condition requires at least 20.260%. Not included in Pillar 1 scoring.
A34: Screening | B34: Estimated remaining lifetime CO₂ | C34: 0 | D34: January 2026 | E34: Estimated remaining lifetime emissions, MtCO₂ – calculated from GEM unit-level plant data | F34: Central opportunity condition requires at least 70.511 MtCO₂.
A35: 1. Energy system conditions | B35: Renewable electricity share | C35: 0.35 | D35: 2024 | E35: Renewable share of electricity generation, % – Ember | F35: Higher is better – min–max normalisation.
A36: 1. Energy system conditions | B36: Wind and solar share | C36: 0.3 | D36: 2024 | E36: Wind and solar share of electricity generation, % – Ember | F36: Higher is better – min–max normalisation.
A37: 1. Energy system conditions | B37: Grid emissions intensity | C37: 0.35 | D37: 2024 | E37: Grid emissions intensity, gCO₂e/kWh – Ember | F37: Lower is better – reverse P5/P95 winsorised score.
A38: 2. Policy and transition commitment | B38: Renewable energy policy and regulatory readiness | C38: 0.12 | D38: 2023 | E38: Renewable Energy score, 0–100 – World Bank RISE | F38: Direct 0–100 score.
A39: 2. Policy and transition commitment | B39: Coal expansion pressure | C39: 0.16 | D39: January 2026 | E39: Announced, pre-permit and permitted coal capacity divided by operating coal capacity – GEM | F39: Lower is better – reverse score using a P95 cap.
A40: 2. Policy and transition commitment | B40: Coal construction pressure | C40: 0.12 | D40: January 2026 | E40: Coal capacity under construction divided by operating coal capacity – GEM | F40: Lower is better – reverse score using a P95 cap.
A41: 2. Policy and transition commitment | B41: Coal share five-year trend | C41: 0.12 | D41: 2019–2024 | E41: Linear trend in coal generation share, percentage points per year – Ember | F41: Lower is better – reverse P5/P95 winsorised score.
A42: 2. Policy and transition commitment | B42: Renewables share five-year trend | C42: 0.12 | D42: 2019–2024 | E42: Linear trend in renewable generation share, percentage points per year – Ember | F42: Higher is better – P5/P95 winsorised score.
A43: 2. Policy and transition commitment | B43: Grid emissions intensity five-year trend | C43: 0.08 | D43: 2019–2024 | E43: Linear trend in grid emissions intensity, gCO₂/kWh per year – Ember | F43: Lower is better – reverse P5/P95 winsorised score.
... A63: 6. Just transition and social credibility | B63: Coal transition social exposure proxy | C63: 0 | D63: January 2026 capacity; 2024 population | E63: Operating coal MW per million people – GEM and World Bank population | F63: Lower is better – reverse log1p scaling
A66: Dropped indicators
A67: Indicator | B67: Current treatment | C67: Reason
A68: Operating coal capacity | B68: Eligibility gate | C68: Measures opportunity scale rather than implementation readiness
A69: Coal generation share | B69: Material-opportunity screen | C69: High coal dependence is an opportunity condition, not evidence of readiness
A70: PPI electricity project count and value | B70: Removed | C70: Strongly affected by jurisdiction size and may include unrelated or fossil infrastructure
A71: Standalone social-protection coverage | B71: Removed | C71: Now forms part of the combined resilience indicator
A72: Standalone HDI | B72: Removed | C72: Now forms part of the combined resilience indicator
A73: Coal capacity per million people | B73: Removed | C73: Weak proxy for affected workers and overlaps with material-opportunity screening
A74: Two basic Article 6 fields | B74: Removed | C74: Replaced by more comparable institutional-readiness and operational-maturity scores when datasets became available in June 2026
A77: Estimated values for missing data
A78: AI was used to estimate missing values across indicators, in this order of preference:
A79: 1. Latest available value carried forward
A80: 2. Parent-country proxy for territories
A81: 3. Regional peer median
A82: 4. A more conservative regional proxy where a median appeared unrealistic
A84: All estimated values are highlighted in grey in the Pillar tabs
A85: Corresponding indicator scores and pillar scores are highlighted in blue
A87: Each estimate is placed in its corresponding indicator column
A88: Brief method and source note stated for each estimate
A90: Exception: Taiwan’s missing 2024 population denominator used to calculate coal capacity per million people was added in 'Pillar-6'!$H$99
A92: Countries with the most estimated values
A94: Country [old] | B94: Estimated weighted inputsm[old]
A95: Ukraine | B95: 8
A96: New Caledonia | B96: 7
A97: North Korea | B97: 7
A98: Taiwan, China | B98: 5
A99: Kosovo | B99: 4
A100: Tajikistan | B100: 3
A101: Pakistan | B101: 2
A102: Brunei | B102: 2
A103: Hong Kong | B103: 2
A104: Slovenia | B104: 2
A105: Myanmar | B105: 2
A106: Zimbabwe | B106: 2
A108: Country [old] | B108: Estimated weighted inputs [old]
A109: Taiwan | B109: 8
A110: North Korea | B110: 7
A111: Hong Kong | B111: 4
A112: Pakistan | B112: 2
A113: Sri Lanka | B113: 2
A114: Canada | B114: 1
A115: Germany | B115: 1
A116: Laos | B116: 1
A117: Mongolia | B117: 1
A118: Russia | B118: 1
A119: Vietnam | B119: 1
A121: All countries are retained because the eligibility rule was operating coal capacity, not data completeness
A122: Dropping any of these countries would:
A123: • exclude several substantively important coal jurisdictions
A124: • favour jurisdictions with stronger statistical systems;
A125: • change your coal-dependent country universe;
A126: • reduce global comparability
A128: Instead, these countries are flagged in Index as more estimate-dependent
A130: Estimated weighted inputs | B130: Classification | C130: Number of countries
A131: 0–1 | B131: Higher data confidence | C131: =COUNTIF(INDEX!$M$4:$M$39,"Higher") -> 31
A132: 2–3 | B132: Moderate data confidence | C132: =COUNTIF(INDEX!$M$4:$M$39,"Moderate") -> 2
A133: 4 or more | B133: Lower data confidence | C133: =COUNTIF(INDEX!$M$4:$M$39,"Lower") -> 3

Sheet INDEX
A1: JURISDICTIONAL READINESS INDEX FOR COAL-TO -CLEAN TRANSITION OPPORTUNITIES | C1: Pillar weights
C2: 0.2 | D2: 0.2 | E2: 0.15 | F2: 0.2 | G2: 0.15 | H2: 0.1 | I2: =SUM(C2:H2) -> 1
A3: Country | B3: ISO3 | C3: PILLAR 1 SCORE Energy system conditions | D3: PILLAR 2 SCORE Policy and transition commitment | E3: PILLAR 3 SCORE Governance and institutional capacity | F3: PILLAR 4 SCORE Carbon market maturity | G3: PILLAR 5 SCORE Macro-financial conditions | H3: PILLAR 6 SCORE Just transition and social credibility | I3: Overall index score | J3: Rank | L3: Number of estimated indicator inputs | M3: Data-confidence level | O3: Provisional overlay-adjusted score | P3: Provisional overlay-adjusted rank
A4: {=_xlfn._xlws.FILTER(Screening!$A$2:$B$216,Screening!$L$2:$L$216="Yes","")} -> Australia | B4: AUS | C4: =IF($B4="","",_xlfn.XLOOKUP($B4,'Pillar-1'!$B$5:$B$216,'Pillar-1'!$M$5:$M$216,"",0)) -> 46.551741 | D4: =IF($B4="","",_xlfn.XLOOKUP($B4,'Pillar-2'!$B$5:$B$216,'Pillar-2'!$S$5:$S$216,"",0)) -> 69.782657 | E4: =IF($B4="","",_xlfn.XLOOKUP($B4,'Pillar-3'!$B$5:$B$217,'Pillar-3'!$M$5:$M$217,"",0)) -> 83.6035 | F4: =IF($B4="","",_xlfn.XLOOKUP($B4,'Pillar-4'!$B$5:$B$217,'Pillar-4'!$R$5:$R$217,"",0)) -> 38.13411 | G4: =IF($B4="","",_xlfn.XLOOKUP($B4,'Pillar-5'!$B$5:$B$216,'Pillar-5'!$O$5:$O$216,"",0)) -> 74.902856 | H4: =IF($B4="","",_xlfn.XLOOKUP($B4,'Pillar-6'!$B$5:$B$216,'Pillar-6'!$O$5:$O$216,"",0)) -> 83.5835 | I4: =IF(COUNT(C4:H4)=6,SUMPRODUCT(C4:H4,$C$2:$H$2),"") -> 63.028005 | J4: =IF(ISNUMBER(I4),1+COUNTIF($I$4:$I$39,">"&I4),"") -> 6 | L4: =IF($B4="","",SUM(_xlfn.XLOOKUP($B4,'Pillar-1'!$B$57:$B$92,'Pillar-1'!$F$57:$F$92,0,0),_xlfn.XLOOKUP($B4,'Pillar-2'!$B$65:$B$100,'Pillar-2'!$K$65:$K$100,0,0),_xlfn.XLOOKUP($B4,'Pillar-3'!$B$54:$B$89,'Pillar-3'!$H$54:$H$89,0,0),_xlfn.XLOOKUP($B4,'Pillar-4'!$B$65:$B$100,'Pillar-4'!$H$65:$H$100,0,0),_xlfn.XLOOKUP($B4,'Pillar-5'!$B$80:$B$115,'Pillar-5'!$G$80:$G$115,0,0),_xlfn.XLOOKUP($B4,'Pillar-6'!$B$74:$B$109,'Pillar-6'!$F$74:$F$109,0,0))) -> 0 | M4: =IF($B4="","",IF(L4<=1,"Higher",IF(L4<=3,"Moderate","Lower"))) -> Higher | O4: =IF(COUNT(C4:H4)=6,C4*#REF!+D4*#REF!+E4*#REF!+F4*#REF!+G4*#REF!+H4*#REF!,"") -> #REF! | P4: =IF(ISNUMBER(O4),1+COUNTIF($O$4:$O$39,">"&O4),"")
A5: Bangladesh | B5: BGD | C5: =IF($B5="","",_xlfn.XLOOKUP($B5,'Pillar-1'!$B$5:$B$216,'Pillar-1'!$M$5:$M$216,"",0)) -> 3.9510783 | D5: =IF($B5="","",_xlfn.XLOOKUP($B5,'Pillar-2'!$B$5:$B$216,'Pillar-2'!$S$5:$S$216,"",0)) -> 12.97493 | E5: =IF($B5="","",_xlfn.XLOOKUP($B5,'Pillar-3'!$B$5:$B$217,'Pillar-3'!$M$5:$M$217,"",0)) -> 37.0855 | F5: =IF($B5="","",_xlfn.XLOOKUP($B5,'Pillar-4'!$B$5:$B$217,'Pillar-4'!$R$5:$R$217,"",0)) -> 77.299124 | G5: =IF($B5="","",_xlfn.XLOOKUP($B5,'Pillar-5'!$B$5:$B$216,'Pillar-5'!$O$5:$O$216,"",0)) -> 46.704982 | H5: =IF($B5="","",_xlfn.XLOOKUP($B5,'Pillar-6'!$B$5:$B$216,'Pillar-6'!$O$5:$O$216,"",0)) -> 44.22375 | I5: =IF(COUNT(C5:H5)=6,SUMPRODUCT(C5:H5,$C$2:$H$2),"") -> 35.835974 | J5: =IF(ISNUMBER(I5),1+COUNTIF($I$4:$I$179,">"&I5),"") -> 36 | L5: =IF($B5="","",SUM(_xlfn.XLOOKUP($B5,'Pillar-1'!$B$57:$B$92,'Pillar-1'!$F$57:$F$92,0,0),_xlfn.XLOOKUP($B5,'Pillar-2'!$B$65:$B$100,'Pillar-2'!$K$65:$K$100,0,0),_xlfn.XLOOKUP($B5,'Pillar-3'!$B$54:$B$89,'Pillar-3'!$H$54:$H$89,0,0),_xlfn.XLOOKUP($B5,'Pillar-4'!$B$65:$B$100,'Pillar-4'!$H$65:$H$100,0,0),_xlfn.XLOOKUP($B5,'Pillar-5'!$B$80:$B$115,'Pillar-5'!$G$80:$G$115,0,0),_xlfn.XLOOKUP($B5,'Pillar-6'!$B$74:$B$109,'Pillar-6'!$F$74:$F$109,0,0))) -> 0 | M5: =IF($B5="","",IF(L5<=1,"Higher",IF(L5<=3,"Moderate","Lower"))) -> Higher | O5: =IF(COUNT(C5:H5)=6,C5*#REF!+D5*#REF!+E5*#REF!+F5*#REF!+G5*#REF!+H5*#REF!,"") -> #REF! | P5: =IF(ISNUMBER(O5),1+COUNTIF($O$4:$O$39,">"&O5),"")
A6: Bosnia and Herzegovina | B6: BIH | C6: =IF($B6="","",_xlfn.XLOOKUP($B6,'Pillar-1'!$B$5:$B$216,'Pillar-1'!$M$5:$M$216,"",0)) -> 28.514445 | D6: =IF($B6="","",_xlfn.XLOOKUP($B6,'Pillar-2'!$B$5:$B$216,'Pillar-2'!$S$5:$S$216,"",0)) -> 38.326415 | E6: =IF($B6="","",_xlfn.XLOOKUP($B6,'Pillar-3'!$B$5:$B$217,'Pillar-3'!$M$5:$M$217,"",0)) -> 45.607 | F6: =IF($B6="","",_xlfn.XLOOKUP($B6,'Pillar-4'!$B$5:$B$217,'Pillar-4'!$R$5:$R$217,"",0)) -> 0 | G6: =IF($B6="","",_xlfn.XLOOKUP($B6,'Pillar-5'!$B$5:$B$216,'Pillar-5'!$O$5:$O$216,"",0)) -> 66.484901 | H6: =IF($B6="","",_xlfn.XLOOKUP($B6,'Pillar-6'!$B$5:$B$216,'Pillar-6'!$O$5:$O$216,"",0)) -> 59.60425 | I6: =IF(COUNT(C6:H6)=6,SUMPRODUCT(C6:H6,$C$2:$H$2),"") -> 36.142382 | J6: =IF(ISNUMBER(I6),1+COUNTIF($I$4:$I$179,">"&I6),"") -> 35 | L6: =IF($B6="","",SUM(_xlfn.XLOOKUP($B6,'Pillar-1'!$B$57:$B$92,'Pillar-1'!$F$57:$F$92,0,0),_xlfn.XLOOKUP($B6,'Pillar-2'!$B$65:$B$100,'Pillar-2'!$K$65:$K$100,0,0),_xlfn.XLOOKUP($B6,'Pillar-3'!$B$54:$B$89,'Pillar-3'!$H$54:$H$89,0,0),_xlfn.XLOOKUP($B6,'Pillar-4'!$B$65:$B$100,'Pillar-4'!$H$65:$H$100,0,0),_xlfn.XLOOKUP($B6,'Pillar-5'!$B$80:$B$115,'Pillar-5'!$G$80:$G$115,0,0),_xlfn.XLOOKUP($B6,'Pillar-6'!$B$74:$B$109,'Pillar-6'!$F$74:$F$109,0,0))) -> 0 | M6: =IF($B6="","",IF(L6<=1,"Higher",IF(L6<=3,"Moderate","Lower"))) -> Higher | O6: =IF(COUNT(C6:H6)=6,C6*#REF!+D6*#REF!+E6*#REF!+F6*#REF!+G6*#REF!+H6*#REF!,"") -> #REF! | P6: =IF(ISNUMBER(O6),1+COUNTIF($O$4:$O$39,">"&O6),"")
A7: Brazil | B7: BRA | C7: =IF($B7="","",_xlfn.XLOOKUP($B7,'Pillar-1'!$B$5:$B$216,'Pillar-1'!$M$5:$M$216,"",0)) -> 86.575121 | D7: =IF($B7="","",_xlfn.XLOOKUP($B7,'Pillar-2'!$B$5:$B$216,'Pillar-2'!$S$5:$S$216,"",0)) -> 56.001412 | E7: =IF($B7="","",_xlfn.XLOOKUP($B7,'Pillar-3'!$B$5:$B$217,'Pillar-3'!$M$5:$M$217,"",0)) -> 47.772 | F7: =IF($B7="","",_xlfn.XLOOKUP($B7,'Pillar-4'!$B$5:$B$217,'Pillar-4'!$R$5:$R$217,"",0)) -> 72.481828 | G7: =IF($B7="","",_xlfn.XLOOKUP($B7,'Pillar-5'!$B$5:$B$216,'Pillar-5'!$O$5:$O$216,"",0)) -> 53.849575 | H7: =IF($B7="","",_xlfn.XLOOKUP($B7,'Pillar-6'!$B$5:$B$216,'Pillar-6'!$O$5:$O$216,"",0)) -> 63.9555 | I7: =IF(COUNT(C7:H7)=6,SUMPRODUCT(C7:H7,$C$2:$H$2),"") -> 64.650458 | J7: =IF(ISNUMBER(I7),1+COUNTIF($I$4:$I$179,">"&I7),"") -> 5 | L7: =IF($B7="","",SUM(_xlfn.XLOOKUP($B7,'Pillar-1'!$B$57:$B$92,'Pillar-1'!$F$57:$F$92,0,0),_xlfn.XLOOKUP($B7,'Pillar-2'!$B$65:$B$100,'Pillar-2'!$K$65:$K$100,0,0),_xlfn.XLOOKUP($B7,'Pillar-3'!$B$54:$B$89,'Pillar-3'!$H$54:$H$89,0,0),_xlfn.XLOOKUP($B7,'Pillar-4'!$B$65:$B$100,'Pillar-4'!$H$65:$H$100,0,0),_xlfn.XLOOKUP($B7,'Pillar-5'!$B$80:$B$115,'Pillar-5'!$G$80:$G$115,0,0),_xlfn.XLOOKUP($B7,'Pillar-6'!$B$74:$B$109,'Pillar-6'!$F$74:$F$109,0,0))) -> 0 | M7: =IF($B7="","",IF(L7<=1,"Higher",IF(L7<=3,"Moderate","Lower"))) -> Higher | O7: =IF(COUNT(C7:H7)=6,C7*#REF!+D7*#REF!+E7*#REF!+F7*#REF!+G7*#REF!+H7*#REF!,"") -> #REF! | P7: =IF(ISNUMBER(O7),1+COUNTIF($O$4:$O$39,">"&O7),"")
A8: Bulgaria | B8: BGR | C8: =IF($B8="","",_xlfn.XLOOKUP($B8,'Pillar-1'!$B$5:$B$216,'Pillar-1'!$M$5:$M$216,"",0)) -> 55.203175 | D8: =IF($B8="","",_xlfn.XLOOKUP($B8,'Pillar-2'!$B$5:$B$216,'Pillar-2'!$S$5:$S$216,"",0)) -> 69.049865 | E8: =IF($B8="","",_xlfn.XLOOKUP($B8,'Pillar-3'!$B$5:$B$217,'Pillar-3'!$M$5:$M$217,"",0)) -> 54.431 | F8: =IF($B8="","",_xlfn.XLOOKUP($B8,'Pillar-4'!$B$5:$B$217,'Pillar-4'!$R$5:$R$217,"",0)) -> 31.90232 | G8: =IF($B8="","",_xlfn.XLOOKUP($B8,'Pillar-5'!$B$5:$B$216,'Pillar-5'!$O$5:$O$216,"",0)) -> 67.029884 | H8: =IF($B8="","",_xlfn.XLOOKUP($B8,'Pillar-6'!$B$5:$B$216,'Pillar-6'!$O$5:$O$216,"",0)) -> 78.52775 | I8: =IF(COUNT(C8:H8)=6,SUMPRODUCT(C8:H8,$C$2:$H$2),"") -> 57.30298 | J8: =IF(ISNUMBER(I8),1+COUNTIF($I$4:$I$179,">"&I8),"") -> 11 | L8: =IF($B8="","",SUM(_xlfn.XLOOKUP($B8,'Pillar-1'!$B$57:$B$92,'Pillar-1'!$F$57:$F$92,0,0),_xlfn.XLOOKUP($B8,'Pillar-2'!$B$65:$B$100,'Pillar-2'!$K$65:$K$100,0,0),_xlfn.XLOOKUP($B8,'Pillar-3'!$B$54:$B$89,'Pillar-3'!$H$54:$H$89,0,0),_xlfn.XLOOKUP($B8,'Pillar-4'!$B$65:$B$100,'Pillar-4'!$H$65:$H$100,0,0),_xlfn.XLOOKUP($B8,'Pillar-5'!$B$80:$B$115,'Pillar-5'!$G$80:$G$115,0,0),_xlfn.XLOOKUP($B8,'Pillar-6'!$B$74:$B$109,'Pillar-6'!$F$74:$F$109,0,0))) -> 0 | M8: =IF($B8="","",IF(L8<=1,"Higher",IF(L8<=3,"Moderate","Lower"))) -> Higher | O8: =IF(COUNT(C8:H8)=6,C8*#REF!+D8*#REF!+E8*#REF!+F8*#REF!+G8*#REF!+H8*#REF!,"") -> #REF! | P8: =IF(ISNUMBER(O8),1+COUNTIF($O$4:$O$39,">"&O8),"")
A9: Cambodia | B9: KHM | C9: =IF($B9="","",_xlfn.XLOOKUP($B9,'Pillar-1'!$B$5:$B$216,'Pillar-1'!$M$5:$M$216,"",0)) -> 32.203217 | D9: =IF($B9="","",_xlfn.XLOOKUP($B9,'Pillar-2'!$B$5:$B$216,'Pillar-2'!$S$5:$S$216,"",0)) -> 17.988229 | E9: =IF($B9="","",_xlfn.XLOOKUP($B9,'Pillar-3'!$B$5:$B$217,'Pillar-3'!$M$5:$M$217,"",0)) -> 41.782 | F9: =IF($B9="","",_xlfn.XLOOKUP($B9,'Pillar-4'!$B$5:$B$217,'Pillar-4'!$R$5:$R$217,"",0)) -> 78.86397 | G9: =IF($B9="","",_xlfn.XLOOKUP($B9,'Pillar-5'!$B$5:$B$216,'Pillar-5'!$O$5:$O$216,"",0)) -> 84.482081 | H9: =IF($B9="","",_xlfn.XLOOKUP($B9,'Pillar-6'!$B$5:$B$216,'Pillar-6'!$O$5:$O$216,"",0)) -> 42.6285 | I9: =IF(COUNT(C9:H9)=6,SUMPRODUCT(C9:H9,$C$2:$H$2),"") -> 49.013545 | J9: =IF(ISNUMBER(I9),1+COUNTIF($I$4:$I$179,">"&I9),"") -> 20 | L9: =IF($B9="","",SUM(_xlfn.XLOOKUP($B9,'Pillar-1'!$B$57:$B$92,'Pillar-1'!$F$57:$F$92,0,0),_xlfn.XLOOKUP($B9,'Pillar-2'!$B$65:$B$100,'Pillar-2'!$K$65:$K$100,0,0),_xlfn.XLOOKUP($B9,'Pillar-3'!$B$54:$B$89,'Pillar-3'!$H$54:$H$89,0,0),_xlfn.XLOOKUP($B9,'Pillar-4'!$B$65:$B$100,'Pillar-4'!$H$65:$H$100,0,0),_xlfn.XLOOKUP($B9,'Pillar-5'!$B$80:$B$115,'Pillar-5'!$G$80:$G$115,0,0),_xlfn.XLOOKUP($B9,'Pillar-6'!$B$74:$B$109,'Pillar-6'!$F$74:$F$109,0,0))) -> 0 | M9: =IF($B9="","",IF(L9<=1,"Higher",IF(L9<=3,"Moderate","Lower"))) -> Higher | O9: =IF(COUNT(C9:H9)=6,C9*#REF!+D9*#REF!+E9*#REF!+F9*#REF!+G9*#REF!+H9*#REF!,"") -> #REF! | P9: =IF(ISNUMBER(O9),1+COUNTIF($O$4:$O$39,">"&O9),"")
A10: Canada | B10: CAN | C10: =IF($B10="","",_xlfn.XLOOKUP($B10,'Pillar-1'!$B$5:$B$216,'Pillar-1'!$M$5:$M$216,"",0)) -> 66.642502 | D10: =IF($B10="","",_xlfn.XLOOKUP($B10,'Pillar-2'!$B$5:$B$216,'Pillar-2'!$S$5:$S$216,"",0)) -> 61.782231 | E10: =IF($B10="","",_xlfn.XLOOKUP($B10,'Pillar-3'!$B$5:$B$217,'Pillar-3'!$M$5:$M$217,"",0)) -> 80.6845 | F10: =IF($B10="","",_xlfn.XLOOKUP($B10,'Pillar-4'!$B$5:$B$217,'Pillar-4'!$R$5:$R$217,"",0)) -> 45.087058 | G10: =IF($B10="","",_xlfn.XLOOKUP($B10,'Pillar-5'!$B$5:$B$216,'Pillar-5'!$O$5:$O$216,"",0)) -> 79.666175 | H10: =IF($B10="","",_xlfn.XLOOKUP($B10,'Pillar-6'!$B$5:$B$216,'Pillar-6'!$O$5:$O$216,"",0)) -> 78.75225 | I10: =IF(COUNT(C10:H10)=6,SUMPRODUCT(C10:H10,$C$2:$H$2),"") -> 66.630184 | J10: =IF(ISNUMBER(I10),1+COUNTIF($I$4:$I$179,">"&I10),"") -> 3 | L10: =IF($B10="","",SUM(_xlfn.XLOOKUP($B10,'Pillar-1'!$B$57:$B$92,'Pillar-1'!$F$57:$F$92,0,0),_xlfn.XLOOKUP($B10,'Pillar-2'!$B$65:$B$100,'Pillar-2'!$K$65:$K$100,0,0),_xlfn.XLOOKUP($B10,'Pillar-3'!$B$54:$B$89,'Pillar-3'!$H$54:$H$89,0,0),_xlfn.XLOOKUP($B10,'Pillar-4'!$B$65:$B$100,'Pillar-4'!$H$65:$H$100,0,0),_xlfn.XLOOKUP($B10,'Pillar-5'!$B$80:$B$115,'Pillar-5'!$G$80:$G$115,0,0),_xlfn.XLOOKUP($B10,'Pillar-6'!$B$74:$B$109,'Pillar-6'!$F$74:$F$109,0,0))) -> 1 | M10: =IF($B10="","",IF(L10<=1,"Higher",IF(L10<=3,"Moderate","Lower"))) -> Higher | O10: =IF(COUNT(C10:H10)=6,C10*#REF!+D10*#REF!+E10*#REF!+F10*#REF!+G10*#REF!+H10*#REF!,"") -> #REF! | P10: =IF(ISNUMBER(O10),1+COUNTIF($O$4:$O$39,">"&O10),"")
A11: Chile | B11: CHL | C11: =IF($B11="","",_xlfn.XLOOKUP($B11,'Pillar-1'!$B$5:$B$216,'Pillar-1'!$M$5:$M$216,"",0)) -> 84.124011 | D11: =IF($B11="","",_xlfn.XLOOKUP($B11,'Pillar-2'!$B$5:$B$216,'Pillar-2'!$S$5:$S$216,"",0)) -> 96.046667 | E11: =IF($B11="","",_xlfn.XLOOKUP($B11,'Pillar-3'!$B$5:$B$217,'Pillar-3'!$M$5:$M$217,"",0)) -> 68.9345 | F11: =IF($B11="","",_xlfn.XLOOKUP($B11,'Pillar-4'!$B$5:$B$217,'Pillar-4'!$R$5:$R$217,"",0)) -> 66.186105 | G11: =IF($B11="","",_xlfn.XLOOKUP($B11,'Pillar-5'!$B$5:$B$216,'Pillar-5'!$O$5:$O$216,"",0)) -> 64.399427 | H11: =IF($B11="","",_xlfn.XLOOKUP($B11,'Pillar-6'!$B$5:$B$216,'Pillar-6'!$O$5:$O$216,"",0)) -> 71.85375 | I11: =IF(COUNT(C11:H11)=6,SUMPRODUCT(C11:H11,$C$2:$H$2),"") -> 76.456821 | J11: =IF(ISNUMBER(I11),1+COUNTIF($I$4:$I$179,">"&I11),"") -> 1 | L11: =IF($B11="","",SUM(_xlfn.XLOOKUP($B11,'Pillar-1'!$B$57:$B$92,'Pillar-1'!$F$57:$F$92,0,0),_xlfn.XLOOKUP($B11,'Pillar-2'!$B$65:$B$100,'Pillar-2'!$K$65:$K$100,0,0),_xlfn.XLOOKUP($B11,'Pillar-3'!$B$54:$B$89,'Pillar-3'!$H$54:$H$89,0,0),_xlfn.XLOOKUP($B11,'Pillar-4'!$B$65:$B$100,'Pillar-4'!$H$65:$H$100,0,0),_xlfn.XLOOKUP($B11,'Pillar-5'!$B$80:$B$115,'Pillar-5'!$G$80:$G$115,0,0),_xlfn.XLOOKUP($B11,'Pillar-6'!$B$74:$B$109,'Pillar-6'!$F$74:$F$109,0,0))) -> 0 | M11: =IF($B11="","",IF(L11<=1,"Higher",IF(L11<=3,"Moderate","Lower"))) -> Higher | O11: =IF(COUNT(C11:H11)=6,C11*#REF!+D11*#REF!+E11*#REF!+F11*#REF!+G11*#REF!+H11*#REF!,"") -> #REF! | P11: =IF(ISNUMBER(O11),1+COUNTIF($O$4:$O$39,">"&O11),"")
A12: China | B12: CHN | C12: =IF($B12="","",_xlfn.XLOOKUP($B12,'Pillar-1'!$B$5:$B$216,'Pillar-1'!$M$5:$M$216,"",0)) -> 38.100942 | D12: =IF($B12="","",_xlfn.XLOOKUP($B12,'Pillar-2'!$B$5:$B$216,'Pillar-2'!$S$5:$S$216,"",0)) -> 43.783305 | E12: =IF($B12="","",_xlfn.XLOOKUP($B12,'Pillar-3'!$B$5:$B$217,'Pillar-3'!$M$5:$M$217,"",0)) -> 56.281 | F12: =IF($B12="","",_xlfn.XLOOKUP($B12,'Pillar-4'!$B$5:$B$217,'Pillar-4'!$R$5:$R$217,"",0)) -> 63.496375 | G12: =IF($B12="","",_xlfn.XLOOKUP($B12,'Pillar-5'!$B$5:$B$216,'Pillar-5'!$O$5:$O$216,"",0)) -> 80.979037 | H12: =IF($B12="","",_xlfn.XLOOKUP($B12,'Pillar-6'!$B$5:$B$216,'Pillar-6'!$O$5:$O$216,"",0)) -> 64.15425 | I12: =IF(COUNT(C12:H12)=6,SUMPRODUCT(C12:H12,$C$2:$H$2),"") -> 56.080555 | J12: =IF(ISNUMBER(I12),1+COUNTIF($I$4:$I$179,">"&I12),"") -> 13 | L12: =IF($B12="","",SUM(_xlfn.XLOOKUP($B12,'Pillar-1'!$B$57:$B$92,'Pillar-1'!$F$57:$F$92,0,0),_xlfn.XLOOKUP($B12,'Pillar-2'!$B$65:$B$100,'Pillar-2'!$K$65:$K$100,0,0),_xlfn.XLOOKUP($B12,'Pillar-3'!$B$54:$B$89,'Pillar-3'!$H$54:$H$89,0,0),_xlfn.XLOOKUP($B12,'Pillar-4'!$B$65:$B$100,'Pillar-4'!$H$65:$H$100,0,0),_xlfn.XLOOKUP($B12,'Pillar-5'!$B$80:$B$115,'Pillar-5'!$G$80:$G$115,0,0),_xlfn.XLOOKUP($B12,'Pillar-6'!$B$74:$B$109,'Pillar-6'!$F$74:$F$109,0,0))) -> 0 | M12: =IF($B12="","",IF(L12<=1,"Higher",IF(L12<=3,"Moderate","Lower"))) -> Higher | O12: =IF(COUNT(C12:H12)=6,C12*#REF!+D12*#REF!+E12*#REF!+F12*#REF!+G12*#REF!+H12*#REF!,"") -> #REF! | P12: =IF(ISNUMBER(O12),1+COUNTIF($O$4:$O$39,">"&O12),"")
A13: Czech Republic | B13: CZE | C13: =IF($B13="","",_xlfn.XLOOKUP($B13,'Pillar-1'!$B$5:$B$216,'Pillar-1'!$M$5:$M$216,"",0)) -> 32.268071 | D13: =IF($B13="","",_xlfn.XLOOKUP($B13,'Pillar-2'!$B$5:$B$216,'Pillar-2'!$S$5:$S$216,"",0)) -> 74.69426 | E13: =IF($B13="","",_xlfn.XLOOKUP($B13,'Pillar-3'!$B$5:$B$217,'Pillar-3'!$M$5:$M$217,"",0)) -> 74.202 | F13: =IF($B13="","",_xlfn.XLOOKUP($B13,'Pillar-4'!$B$5:$B$217,'Pillar-4'!$R$5:$R$217,"",0)) -> 4 | G13: =IF($B13="","",_xlfn.XLOOKUP($B13,'Pillar-5'!$B$5:$B$216,'Pillar-5'!$O$5:$O$216,"",0)) -> 62.885372 | H13: =IF($B13="","",_xlfn.XLOOKUP($B13,'Pillar-6'!$B$5:$B$216,'Pillar-6'!$O$5:$O$216,"",0)) -> 85.4895 | I13: =IF(COUNT(C13:H13)=6,SUMPRODUCT(C13:H13,$C$2:$H$2),"") -> 51.304522 | J13: =IF(ISNUMBER(I13),1+COUNTIF($I$4:$I$179,">"&I13),"") -> 19 | L13: =IF($B13="","",SUM(_xlfn.XLOOKUP($B13,'Pillar-1'!$B$57:$B$92,'Pillar-1'!$F$57:$F$92,0,0),_xlfn.XLOOKUP($B13,'Pillar-2'!$B$65:$B$100,'Pillar-2'!$K$65:$K$100,0,0),_xlfn.XLOOKUP($B13,'Pillar-3'!$B$54:$B$89,'Pillar-3'!$H$54:$H$89,0,0),_xlfn.XLOOKUP($B13,'Pillar-4'!$B$65:$B$100,'Pillar-4'!$H$65:$H$100,0,0),_xlfn.XLOOKUP($B13,'Pillar-5'!$B$80:$B$115,'Pillar-5'!$G$80:$G$115,0,0),_xlfn.XLOOKUP($B13,'Pillar-6'!$B$74:$B$109,'Pillar-6'!$F$74:$F$109,0,0))) -> 0 | M13: =IF($B13="","",IF(L13<=1,"Higher",IF(L13<=3,"Moderate","Lower"))) -> Higher | O13: =IF(COUNT(C13:H13)=6,C13*#REF!+D13*#REF!+E13*#REF!+F13*#REF!+G13*#REF!+H13*#REF!,"") -> #REF! | P13: =IF(ISNUMBER(O13),1+COUNTIF($O$4:$O$39,">"&O13),"")
A14: Dominican Republic | B14: DOM | C14: =IF($B14="","",_xlfn.XLOOKUP($B14,'Pillar-1'!$B$5:$B$216,'Pillar-1'!$M$5:$M$216,"",0)) -> 26.862616 | D14: =IF($B14="","",_xlfn.XLOOKUP($B14,'Pillar-2'!$B$5:$B$216,'Pillar-2'!$S$5:$S$216,"",0)) -> 39.015957 | E14: =IF($B14="","",_xlfn.XLOOKUP($B14,'Pillar-3'!$B$5:$B$217,'Pillar-3'!$M$5:$M$217,"",0)) -> 54.588 | F14: =IF($B14="","",_xlfn.XLOOKUP($B14,'Pillar-4'!$B$5:$B$217,'Pillar-4'!$R$5:$R$217,"",0)) -> 30.75 | G14: =IF($B14="","",_xlfn.XLOOKUP($B14,'Pillar-5'!$B$5:$B$216,'Pillar-5'!$O$5:$O$216,"",0)) -> 59.328467 | H14: =IF($B14="","",_xlfn.XLOOKUP($B14,'Pillar-6'!$B$5:$B$216,'Pillar-6'!$O$5:$O$216,"",0)) -> 73.0645 | I14: =IF(COUNT(C14:H14)=6,SUMPRODUCT(C14:H14,$C$2:$H$2),"") -> 43.719635 | J14: =IF(ISNUMBER(I14),1+COUNTIF($I$4:$I$179,">"&I14),"") -> 27 | L14: =IF($B14="","",SUM(_xlfn.XLOOKUP($B14,'Pillar-1'!$B$57:$B$92,'Pillar-1'!$F$57:$F$92,0,0),_xlfn.XLOOKUP($B14,'Pillar-2'!$B$65:$B$100,'Pillar-2'!$K$65:$K$100,0,0),_xlfn.XLOOKUP($B14,'Pillar-3'!$B$54:$B$89,'Pillar-3'!$H$54:$H$89,0,0),_xlfn.XLOOKUP($B14,'Pillar-4'!$B$65:$B$100,'Pillar-4'!$H$65:$H$100,0,0),_xlfn.XLOOKUP($B14,'Pillar-5'!$B$80:$B$115,'Pillar-5'!$G$80:$G$115,0,0),_xlfn.XLOOKUP($B14,'Pillar-6'!$B$74:$B$109,'Pillar-6'!$F$74:$F$109,0,0))) -> 0 | M14: =IF($B14="","",IF(L14<=1,"Higher",IF(L14<=3,"Moderate","Lower"))) -> Higher | O14: =IF(COUNT(C14:H14)=6,C14*#REF!+D14*#REF!+E14*#REF!+F14*#REF!+G14*#REF!+H14*#REF!,"") -> #REF! | P14: =IF(ISNUMBER(O14),1+COUNTIF($O$4:$O$39,">"&O14),"")
A15: Germany | B15: DEU | C15: =IF($B15="","",_xlfn.XLOOKUP($B15,'Pillar-1'!$B$5:$B$216,'Pillar-1'!$M$5:$M$216,"",0)) -> 80.528427 | D15: =IF($B15="","",_xlfn.XLOOKUP($B15,'Pillar-2'!$B$5:$B$216,'Pillar-2'!$S$5:$S$216,"",0)) -> 87.144209 | E15: =IF($B15="","",_xlfn.XLOOKUP($B15,'Pillar-3'!$B$5:$B$217,'Pillar-3'!$M$5:$M$217,"",0)) -> 80.517 | F15: =IF($B15="","",_xlfn.XLOOKUP($B15,'Pillar-4'!$B$5:$B$217,'Pillar-4'!$R$5:$R$217,"",0)) -> 49.027601 | G15: =IF($B15="","",_xlfn.XLOOKUP($B15,'Pillar-5'!$B$5:$B$216,'Pillar-5'!$O$5:$O$216,"",0)) -> 66.520655 | H15: =IF($B15="","",_xlfn.XLOOKUP($B15,'Pillar-6'!$B$5:$B$216,'Pillar-6'!$O$5:$O$216,"",0)) -> 99.35425 | I15: =IF(COUNT(C15:H15)=6,SUMPRODUCT(C15:H15,$C$2:$H$2),"") -> 75.33112 | J15: =IF(ISNUMBER(I15),1+COUNTIF($I$4:$I$179,">"&I15),"") -> 2 | L15: =IF($B15="","",SUM(_xlfn.XLOOKUP($B15,'Pillar-1'!$B$57:$B$92,'Pillar-1'!$F$57:$F$92,0,0),_xlfn.XLOOKUP($B15,'Pillar-2'!$B$65:$B$100,'Pillar-2'!$K$65:$K$100,0,0),_xlfn.XLOOKUP($B15,'Pillar-3'!$B$54:$B$89,'Pillar-3'!$H$54:$H$89,0,0),_xlfn.XLOOKUP($B15,'Pillar-4'!$B$65:$B$100,'Pillar-4'!$H$65:$H$100,0,0),_xlfn.XLOOKUP($B15,'Pillar-5'!$B$80:$B$115,'Pillar-5'!$G$80:$G$115,0,0),_xlfn.XLOOKUP($B15,'Pillar-6'!$B$74:$B$109,'Pillar-6'!$F$74:$F$109,0,0))) -> 1 | M15: =IF($B15="","",IF(L15<=1,"Higher",IF(L15<=3,"Moderate","Lower"))) -> Higher | O15: =IF(COUNT(C15:H15)=6,C15*#REF!+D15*#REF!+E15*#REF!+F15*#REF!+G15*#REF!+H15*#REF!,"") -> #REF! | P15: =IF(ISNUMBER(O15),1+COUNTIF($O$4:$O$39,">"&O15),"")
A16: Hong Kong | B16: HKG | C16: =IF($B16="","",_xlfn.XLOOKUP($B16,'Pillar-1'!$B$5:$B$216,'Pillar-1'!$M$5:$M$216,"",0)) -> 4.5636845 | D16: =IF($B16="","",_xlfn.XLOOKUP($B16,'Pillar-2'!$B$5:$B$216,'Pillar-2'!$S$5:$S$216,"",0)) -> 67.969412 | E16: =IF($B16="","",_xlfn.XLOOKUP($B16,'Pillar-3'!$B$5:$B$217,'Pillar-3'!$M$5:$M$217,"",0)) -> 79.537 | F16: =IF($B16="","",_xlfn.XLOOKUP($B16,'Pillar-4'!$B$5:$B$217,'Pillar-4'!$R$5:$R$217,"",0)) -> 1.8606328 | G16: =IF($B16="","",_xlfn.XLOOKUP($B16,'Pillar-5'!$B$5:$B$216,'Pillar-5'!$O$5:$O$216,"",0)) -> 97.983185 | H16: =IF($B16="","",_xlfn.XLOOKUP($B16,'Pillar-6'!$B$5:$B$216,'Pillar-6'!$O$5:$O$216,"",0)) -> 67.78125 | I16: =IF(COUNT(C16:H16)=6,SUMPRODUCT(C16:H16,$C$2:$H$2),"") -> 48.284899 | J16: =IF(ISNUMBER(I16),1+COUNTIF($I$4:$I$179,">"&I16),"") -> 21 | L16: =IF($B16="","",SUM(_xlfn.XLOOKUP($B16,'Pillar-1'!$B$57:$B$92,'Pillar-1'!$F$57:$F$92,0,0),_xlfn.XLOOKUP($B16,'Pillar-2'!$B$65:$B$100,'Pillar-2'!$K$65:$K$100,0,0),_xlfn.XLOOKUP($B16,'Pillar-3'!$B$54:$B$89,'Pillar-3'!$H$54:$H$89,0,0),_xlfn.XLOOKUP($B16,'Pillar-4'!$B$65:$B$100,'Pillar-4'!$H$65:$H$100,0,0),_xlfn.XLOOKUP($B16,'Pillar-5'!$B$80:$B$115,'Pillar-5'!$G$80:$G$115,0,0),_xlfn.XLOOKUP($B16,'Pillar-6'!$B$74:$B$109,'Pillar-6'!$F$74:$F$109,0,0))) -> 4 | M16: =IF($B16="","",IF(L16<=1,"Higher",IF(L16<=3,"Moderate","Lower"))) -> Lower | O16: =IF(COUNT(C16:H16)=6,C16*#REF!+D16*#REF!+E16*#REF!+F16*#REF!+G16*#REF!+H16*#REF!,"") -> #REF! | P16: =IF(ISNUMBER(O16),1+COUNTIF($O$4:$O$39,">"&O16),"")
... A39: Vietnam | B39: VNM | C39: =IF($B39="","",_xlfn.XLOOKUP($B39,'Pillar-1'!$B$5:$B$216,'Pillar-1'!$M$5:$M$216,"",0)) -> 42.588404 | D39: =IF($B39="","",_xlfn.XLOOKUP($B39,'Pillar-2'!$B$5:$B$216,'Pillar-2'!$S$5:$S$216,"",0)) -> 58.075052 | E39: =IF($B39="","",_xlfn.XLOOKUP($B39,'Pillar-3'!$B$5:$B$217,'Pillar-3'!$M$5:$M$217,"",0)) -> 50.513 | F39: =IF($B39="","",_xlfn.XLOOKUP($B39,'Pillar-4'!$B$5:$B$217,'Pillar-4'!$R$5:$R$217,"",0)) -> 70.649827 | G39: =IF($B39="","",_xlfn.XLOOKUP($B39,'Pillar-5'!$B$5:$B$216,'Pillar-5'!$O$5:$O$216,"",0)) -> 76.538933 | H39: =IF($B39="","",_xlfn.XLOOKUP($B39,'Pillar-6'!$B$5:$B$216,'Pillar-6'!$O$5:$O$216,"",0)) -> 57.26725 | I39: =IF(COUNT(C39:H39)=6,SUMPRODUCT(C39:H39,$C$2:$H$2),"") -> 59.047171 | J39: =IF(ISNUMBER(I39),1+COUNTIF($I$4:$I$179,">"&I39),"") -> 8 | L39: =IF($B39="","",SUM(_xlfn.XLOOKUP($B39,'Pillar-1'!$B$57:$B$92,'Pillar-1'!$F$57:$F$92,0,0),_xlfn.XLOOKUP($B39,'Pillar-2'!$B$65:$B$100,'Pillar-2'!$K$65:$K$100,0,0),_xlfn.XLOOKUP($B39,'Pillar-3'!$B$54:$B$89,'Pillar-3'!$H$54:$H$89,0,0),_xlfn.XLOOKUP($B39,'Pillar-4'!$B$65:$B$100,'Pillar-4'!$H$65:$H$100,0,0),_xlfn.XLOOKUP($B39,'Pillar-5'!$B$80:$B$115,'Pillar-5'!$G$80:$G$115,0,0),_xlfn.XLOOKUP($B39,'Pillar-6'!$B$74:$B$109,'Pillar-6'!$F$74:$F$109,0,0))) -> 1 | M39: =IF($B39="","",IF(L39<=1,"Higher",IF(L39<=3,"Moderate","Lower"))) -> Higher | O39: =IF(COUNT(C39:H39)=6,C39*#REF!+D39*#REF!+E39*#REF!+F39*#REF!+G39*#REF!+H39*#REF!,"") -> #REF! | P39: =IF(ISNUMBER(O39),1+COUNTIF($O$4:$O$39,">"&O39),"")
A42: Pillar score includes estimate(s)
A43: Index Score / Rank includes estimate(s)
A44: Overlay Adjusted Score / Rank includes estimate(s)

Sheet INDEX ranked
A1: JURISDICTIONAL READINESS INDEX FOR COAL-TO -CLEAN TRANSITION OPPORTUNITIES
A2: Country | B2: ISO3 | C2: Pillar 1 score Energy system conditions | D2: Pillar 2 score Policy and transition commitment | E2: Pillar 3 score Governance and institutional capacity | F2: Pillar 4 score Carbon market maturity | G2: Pillar 5 score Macro-financial conditions | H2: Pillar 6 score Just transition and social credibility | I2: Overall index score | J2: Rank
A3: {=_xlfn.LET( _xlpm.data,_xlfn._xlws.FILTER(_xlfn.HSTACK(INDEX!A4:J39,IF(INDEX!N4:N39="","",INDEX!N4:N39)),INDEX!A4:A39<>""), _xlpm.r,_xlfn._xlws.FILTER(INDEX!J4:J39,INDEX!A4:A39<>""), _xlfn.SORTBY(_xlpm.data,--(_xlpm.r=""),1,_xlpm.r,1) )} -> Chile | B3: CHL | C3: 84.124011 | D3: 96.046667 | E3: 68.9345 | F3: 66.186105 | G3: 64.399427 | H3: 71.85375 | I3: 76.456821 | J3: 1
A4: Germany | B4: DEU | C4: 80.528427 | D4: 87.144209 | E4: 80.517 | F4: 49.027601 | G4: 66.520655 | H4: 99.35425 | I4: 75.33112 | J4: 2
A5: Canada | B5: CAN | C5: 66.642502 | D5: 61.782231 | E5: 80.6845 | F5: 45.087058 | G5: 79.666175 | H5: 78.75225 | I5: 66.630184 | J5: 3
A6: United States | B6: USA | C6: 45.102471 | D6: 67.22198 | E6: 73.5955 | F6: 61.122227 | G6: 83.697333 | H6: 71.8225 | I6: 65.465511 | J6: 4
A7: Brazil | B7: BRA | C7: 86.575121 | D7: 56.001412 | E7: 47.772 | F7: 72.481828 | G7: 53.849575 | H7: 63.9555 | I7: 64.650458 | J7: 5
A8: Australia | B8: AUS | C8: 46.551741 | D8: 69.782657 | E8: 83.6035 | F8: 38.13411 | G8: 74.902856 | H8: 83.5835 | I8: 63.028005 | J8: 6
A9: South Korea | B9: KOR | C9: 29.213946 | D9: 75.030089 | E9: 73.707 | F9: 61.533748 | G9: 79.944199 | H9: 65.21625 | I9: 62.724861 | J9: 7
A10: Vietnam | B10: VNM | C10: 42.588404 | D10: 58.075052 | E10: 50.513 | F10: 70.649827 | G10: 76.538933 | H10: 57.26725 | I10: 59.047171 | J10: 8
A11: Sri Lanka | B11: LKA | C11: 55.031939 | D11: 79.768239 | E11: 48.546 | F11: 62.709379 | G11: 38.530653 | H11: 58.30225 | I11: 58.393634 | J11: 9
A12: Japan | B12: JPN | C12: 33.370858 | D12: 56.252323 | E12: 82.1295 | F12: 41.320255 | G12: 66.587888 | H12: 90.23925 | I12: 57.520221 | J12: 10
A13: Bulgaria | B13: BGR | C13: 55.203175 | D13: 69.049865 | E13: 54.431 | F13: 31.90232 | G13: 67.029884 | H13: 78.52775 | I13: 57.30298 | J13: 11
A14: Thailand | B14: THA | C14: 20.944702 | D14: 48.962463 | E14: 51.7125 | F14: 86.532861 | G14: 78.799662 | H14: 60.07275 | I14: 56.872104 | J14: 12
A15: China | B15: CHN | C15: 38.100942 | D15: 43.783305 | E15: 56.281 | F15: 63.496375 | G15: 80.979037 | H15: 64.15425 | I15: 56.080555 | J15: 13
... A38: Bangladesh | B38: BGD | C38: 3.9510783 | D38: 12.97493 | E38: 37.0855 | F38: 77.299124 | G38: 46.704982 | H38: 44.22375 | I38: 35.835974 | J38: 36

Sheet OVERLAY
A1: Final Q1 and Q2 market-salience overlay integration
A2: The analysis found more market-relevant factors than the index could directly score. Only constructs with a clear primary link to an existing indicator were applied to weights. Cross-cutting or project-specific factors were retained as contextual evidence to avoid forced mapping and double-counting.
A3: Pillar | D3: Indicator | F3: Primary mapped construct | G3: Base global weight | H3: Q1 multiplier | I3: Q1 adjusted weight | J3: Q2 multiplier | K3: Q2 adjusted weight
A4: PILLAR 1 – Energy system conditions | D4: P1 I1 – Renewable electricity share | F4: C01A | G4: =[2]INDEX!$C$2*'[2]Pillar-1'!$J$2 -> 0.07 | H4: 1 | I4: =G4*H4/SUMPRODUCT($G$4:$G$31,$H$4:$H$31) -> 0.067453626 | J4: 1 | K4: =G4*J4/SUMPRODUCT($G$4:$G$31,$J$4:$J$31) -> 0.068372729
A5: PILLAR 1 – Energy system conditions | D5: P1 I2 – Wind and solar share | F5: C01B | G5: =[2]INDEX!$C$2*'[2]Pillar-1'!$K$2 -> 0.06 | H5: 1 | I5: =G5*H5/SUMPRODUCT($G$4:$G$31,$H$4:$H$31) -> 0.057817393 | J5: 1 | K5: =G5*J5/SUMPRODUCT($G$4:$G$31,$J$4:$J$31) -> 0.058605196
A6: PILLAR 1 – Energy system conditions | D6: P1 I3 – Grid emissions intensity | F6: None | G6: =[2]INDEX!$C$2*'[2]Pillar-1'!$L$2 -> 0.07 | H6: 1 | I6: =G6*H6/SUMPRODUCT($G$4:$G$31,$H$4:$H$31) -> 0.067453626 | J6: 1 | K6: =G6*J6/SUMPRODUCT($G$4:$G$31,$J$4:$J$31) -> 0.068372729
A7: PILLAR 2 – Policy and transition commitment | D7: P2 I1 – Renewable energy policy and regulatory readiness | F7: C06 | G7: =[2]INDEX!$D$2*'[2]Pillar-2'!$K$2 -> 0.024 | H7: 1.1 | I7: =G7*H7/SUMPRODUCT($G$4:$G$31,$H$4:$H$31) -> 0.025439653 | J7: 1 | K7: =G7*J7/SUMPRODUCT($G$4:$G$31,$J$4:$J$31) -> 0.023442079
A8: PILLAR 2 – Policy and transition commitment | D8: P2 I2 – Coal expansion pressure | F8: C04A | G8: =[2]INDEX!$D$2*'[2]Pillar-2'!$L$2 -> 0.032 | H8: 1 | I8: =G8*H8/SUMPRODUCT($G$4:$G$31,$H$4:$H$31) -> 0.030835943 | J8: 1.05 | K8: =G8*J8/SUMPRODUCT($G$4:$G$31,$J$4:$J$31) -> 0.03281891
A9: PILLAR 2 – Policy and transition commitment | D9: P2 I3 – Coal construction pressure | F9: C04B | G9: =[2]INDEX!$D$2*'[2]Pillar-2'!$M$2 -> 0.024 | H9: 1 | I9: =G9*H9/SUMPRODUCT($G$4:$G$31,$H$4:$H$31) -> 0.023126957 | J9: 1.05 | K9: =G9*J9/SUMPRODUCT($G$4:$G$31,$J$4:$J$31) -> 0.024614182
A10: PILLAR 2 – Policy and transition commitment | D10: P2 I4 – Coal share 5yr linear trend slope | F10: C05A | G10: =[2]INDEX!$D$2*'[2]Pillar-2'!$N$2 -> 0.024 | H10: 1 | I10: =G10*H10/SUMPRODUCT($G$4:$G$31,$H$4:$H$31) -> 0.023126957 | J10: 1 | K10: =G10*J10/SUMPRODUCT($G$4:$G$31,$J$4:$J$31) -> 0.023442079
A11: PILLAR 2 – Policy and transition commitment | D11: P2 I5 – Renewables share 5y linear trend slope | F11: C05B | G11: =[2]INDEX!$D$2*'[2]Pillar-2'!$O$2 -> 0.024 | H11: 1 | I11: =G11*H11/SUMPRODUCT($G$4:$G$31,$H$4:$H$31) -> 0.023126957 | J11: 1 | K11: =G11*J11/SUMPRODUCT($G$4:$G$31,$J$4:$J$31) -> 0.023442079
A12: PILLAR 2 – Policy and transition commitment | D12: P2 I6 – Grid emissions intensity 5yr linear trend slope | F12: None | G12: =[2]INDEX!$D$2*'[2]Pillar-2'!$P$2 -> 0.016 | H12: 1 | I12: =G12*H12/SUMPRODUCT($G$4:$G$31,$H$4:$H$31) -> 0.015417972 | J12: 1 | K12: =G12*J12/SUMPRODUCT($G$4:$G$31,$J$4:$J$31) -> 0.015628052
A13: PILLAR 2 – Policy and transition commitment | D13: P2 I7 – Carbon-pricing infrastructure | F13: C07 | G13: =[2]INDEX!$D$2*'[2]Pillar-2'!$Q$2 -> 0.016 | H13: 1.1 | I13: =G13*H13/SUMPRODUCT($G$4:$G$31,$H$4:$H$31) -> 0.016959769 | J13: 1 | K13: =G13*J13/SUMPRODUCT($G$4:$G$31,$J$4:$J$31) -> 0.015628052
A14: PILLAR 2 – Policy and transition commitment | D14: P2 I8 – Coal phaseout commitment and documented implementation alignment | F14: C03 | G14: =[2]INDEX!$D$2*'[2]Pillar-2'!$R$2 -> 0.04 | H14: 1.2 | I14: =G14*H14/SUMPRODUCT($G$4:$G$31,$H$4:$H$31) -> 0.046253915 | J14: 1.2 | K14: =G14*J14/SUMPRODUCT($G$4:$G$31,$J$4:$J$31) -> 0.046884157
A15: PILLAR 3 – Governance and institutional capacity | D15: P3 I1 – Political stability | F15: C10A | G15: =[2]INDEX!$E$2*'[2]Pillar-3'!$H$2 -> 0.015 | H15: 1 | I15: =G15*H15/SUMPRODUCT($G$4:$G$31,$H$4:$H$31) -> 0.014454348 | J15: 1 | K15: =G15*J15/SUMPRODUCT($G$4:$G$31,$J$4:$J$31) -> 0.014651299
A16: PILLAR 3 – Governance and institutional capacity | D16: P3 I2 – Government effectiveness | F16: C08 | G16: =[2]INDEX!$E$2*'[2]Pillar-3'!$I$2 -> 0.0375 | H16: 1.05 | I16: =G16*H16/SUMPRODUCT($G$4:$G$31,$H$4:$H$31) -> 0.037942664 | J16: 1 | K16: =G16*J16/SUMPRODUCT($G$4:$G$31,$J$4:$J$31) -> 0.036628248
A17: PILLAR 3 – Governance and institutional capacity | D17: P3 I3 – Regulatory quality | F17: C09A | G17: =[2]INDEX!$E$2*'[2]Pillar-3'!$J$2 -> 0.0375 | H17: 1.05 | I17: =G17*H17/SUMPRODUCT($G$4:$G$31,$H$4:$H$31) -> 0.037942664 | J17: 1.1 | K17: =G17*J17/SUMPRODUCT($G$4:$G$31,$J$4:$J$31) -> 0.040291072
A18: PILLAR 3 – Governance and institutional capacity | D18: P3 I4 – Rule of law | F18: C09B | G18: =[2]INDEX!$E$2*'[2]Pillar-3'!$K$2 -> 0.03 | H18: 1.05 | I18: =G18*H18/SUMPRODUCT($G$4:$G$31,$H$4:$H$31) -> 0.030354132 | J18: 1.05 | K18: =G18*J18/SUMPRODUCT($G$4:$G$31,$J$4:$J$31) -> 0.030767728
A19: PILLAR 3 – Governance and institutional capacity | D19: P3 I5 – Control of corruption | F19: C10B | G19: =[2]INDEX!$E$2*'[2]Pillar-3'!$L$2 -> 0.03 | H19: 1 | I19: =G19*H19/SUMPRODUCT($G$4:$G$31,$H$4:$H$31) -> 0.028908697 | J19: 1 | K19: =G19*J19/SUMPRODUCT($G$4:$G$31,$J$4:$J$31) -> 0.029302598
A20: PILLAR 4 – Carbon market maturity | D20: P4 I1 – VCM project activity | F20: C12A | G20: =[2]INDEX!$F$2*'[2]Pillar-4'!$K$2 -> 0.04 | H20: 1 | I20: =G20*H20/SUMPRODUCT($G$4:$G$31,$H$4:$H$31) -> 0.038544929 | J20: 1 | K20: =G20*J20/SUMPRODUCT($G$4:$G$31,$J$4:$J$31) -> 0.039070131
A21: PILLAR 4 – Carbon market maturity | D21: P4 I2 – VCM issuance scale | F21: C12B | G21: =[2]INDEX!$F$2*'[2]Pillar-4'!$L$2 -> 0.04 | H21: 1 | I21: =G21*H21/SUMPRODUCT($G$4:$G$31,$H$4:$H$31) -> 0.038544929 | J21: 1 | K21: =G21*J21/SUMPRODUCT($G$4:$G$31,$J$4:$J$31) -> 0.039070131
A22: PILLAR 4 – Carbon market maturity | D22: P4 I3 – VCM retirement activity | F22: C12C | G22: =[2]INDEX!$F$2*'[2]Pillar-4'!$M$2 -> 0.03 | H22: 1 | I22: =G22*H22/SUMPRODUCT($G$4:$G$31,$H$4:$H$31) -> 0.028908697 | J22: 1.05 | K22: =G22*J22/SUMPRODUCT($G$4:$G$31,$J$4:$J$31) -> 0.030767728
A23: PILLAR 4 – Carbon market maturity | D23: P4 I4 – Article 6 institutional readiness score (0–100) | F23: C11A | G23: =[2]INDEX!$F$2*'[2]Pillar-4'!$N$2 -> 0.04 | H23: 1.1 | I23: =G23*H23/SUMPRODUCT($G$4:$G$31,$H$4:$H$31) -> 0.042399422 | J23: 1.1 | K23: =G23*J23/SUMPRODUCT($G$4:$G$31,$J$4:$J$31) -> 0.042977144
A24: PILLAR 4 – Carbon market maturity | D24: P4 I5 – Article 6 operational maturity score (0–100) | F24: C11B | G24: =[2]INDEX!$F$2*'[2]Pillar-4'!$O$2 -> 0.05 | H24: 1.1 | I24: =G24*H24/SUMPRODUCT($G$4:$G$31,$H$4:$H$31) -> 0.052999277 | J24: 1 | K24: =G24*J24/SUMPRODUCT($G$4:$G$31,$J$4:$J$31) -> 0.048837664
A25: PILLAR 5 – Macro-financial conditions | D25: P5 I1 – Domestic financial depth | F25: C16 | G25: =[2]INDEX!$G$2*'[2]Pillar-5'!$I$2 -> 0.045 | H25: 1.1 | I25: =G25*H25/SUMPRODUCT($G$4:$G$31,$H$4:$H$31) -> 0.04769935 | J25: 1 | K25: =G25*J25/SUMPRODUCT($G$4:$G$31,$J$4:$J$31) -> 0.043953897
A26: PILLAR 5 – Macro-financial conditions | D26: P5 I2 – Macroeconomic price stability | F26: C14A | G26: =[2]INDEX!$G$2*'[2]Pillar-5'!$J$2 -> 0.0375 | H26: 1 | I26: =G26*H26/SUMPRODUCT($G$4:$G$31,$H$4:$H$31) -> 0.036135871 | J26: 1 | K26: =G26*J26/SUMPRODUCT($G$4:$G$31,$J$4:$J$31) -> 0.036628248
A27: PILLAR 5 – Macro-financial conditions | D27: P5 I3 – Sovereign debt pressure | F27: C14B | G27: =[2]INDEX!$G$2*'[2]Pillar-5'!$K$2 -> 0.03 | H27: 1.05 | I27: =G27*H27/SUMPRODUCT($G$4:$G$31,$H$4:$H$31) -> 0.030354132 | J27: 1 | K27: =G27*J27/SUMPRODUCT($G$4:$G$31,$J$4:$J$31) -> 0.029302598
A28: PILLAR 5 – Macro-financial conditions | D28: P5 I4 – Exchange-rate instability | F28: C15 | G28: =[2]INDEX!$G$2*'[2]Pillar-5'!$L$2 -> 0.0375 | H28: 1 | I28: =G28*H28/SUMPRODUCT($G$4:$G$31,$H$4:$H$31) -> 0.036135871 | J28: 1 | K28: =G28*J28/SUMPRODUCT($G$4:$G$31,$J$4:$J$31) -> 0.036628248
A29: PILLAR 6 – Just transition and social credibility | D29: P6 I1 – Labour rights and social dialogue environment | F29: C18 | G29: =[2]INDEX!$H$2*'[2]Pillar-6'!$I$2 -> 0.035 | H29: 1 | I29: =G29*H29/SUMPRODUCT($G$4:$G$31,$H$4:$H$31) -> 0.033726813 | J29: 1 | K29: =G29*J29/SUMPRODUCT($G$4:$G$31,$J$4:$J$31) -> 0.034186365
A30: PILLAR 6 – Just transition and social credibility | D30: P6 I2 – Social protection and human-development resilience | F30: C19 | G30: =[2]INDEX!$H$2*'[2]Pillar-6'!$K$2 -> 0.045 | H30: 1.1 | I30: =G30*H30/SUMPRODUCT($G$4:$G$31,$H$4:$H$31) -> 0.04769935 | J30: 1.05 | K30: =G30*J30/SUMPRODUCT($G$4:$G$31,$J$4:$J$31) -> 0.046151592
A31: PILLAR 6 – Just transition and social credibility | D31: P6 I3 – Labour-market absorption risk | F31: C20 | G31: =[2]INDEX!$H$2*'[2]Pillar-6'!$L$2 -> 0.02 | H31: 1.05 | I31: =G31*H31/SUMPRODUCT($G$4:$G$31,$H$4:$H$31) -> 0.020236088 | J31: 1 | K31: =G31*J31/SUMPRODUCT($G$4:$G$31,$J$4:$J$31) -> 0.019535065
E32: Weight totals | G32: =SUM(G4:G31) -> 1 | I32: =SUM(I4:I31) -> 1 | K32: =SUM(K4:K31) -> 1
A35: Country | B35: ISO3 | C35: Base score | D35: Base rank | E35: Q1 overlay score | F35: Q1 rank | G35: Q1 score change | H35: Q1 rank change | I35: Q2 overlay score | J35: Q2 rank | K35: Q2 rank change
A36: Australia | B36: AUS | C36: =_xlfn.XLOOKUP($B36,[3]INDEX!$B$4:$B$39,[3]INDEX!$I$4:$I$39,"") -> 63.028005 | D36: =_xlfn.XLOOKUP($B36,[3]INDEX!$B$4:$B$39,[3]INDEX!$J$4:$J$39,"") -> 6 | E36: =IFERROR(_xlfn.LET(_xlpm.iso,$B36,_xlpm.s,_xlfn.VSTACK(_xlfn.XLOOKUP(_xlpm.iso,'[3]Pillar-1'!$B$5:$B$40,'[3]Pillar-1'!$J$5:$J$40),_xlfn.XLOOKUP(_xlpm.iso,'[3]Pillar-1'!$B$5:$B$40,'[3]Pillar-1'!$K$5:$K$40),_xlfn.XLOOKUP(_xlpm.iso,'[3]Pillar-1'!$B$5:$B$40,'[3]Pillar-1'!$L$5:$L$40),_xlfn.XLOOKUP(_xlpm.iso,'[3]Pillar-2'!$B$5:$B$40,'[3]Pillar-2'!$K$5:$K$40),_xlfn.XLOOKUP(_xlpm.iso,'[3]Pillar-2'!$B$5:$B$40,'[3]Pillar-2'!$L$5:$L$40),_xlfn.XLOOKUP(_xlpm.iso,'[3]Pillar-2'!$B$5:$B$40,'[3]Pillar-2'!$M$5:$M$40),_xlfn.XLOOKUP(_xlpm.iso,'[3]Pillar-2'!$B$5:$B$40,'[3]Pillar-2'!$N$5:$N$40),_xlfn.XLOOKUP(_xlpm.iso,'[3]Pillar-2'!$B$5:$B$40,'[3]Pillar-2'!$O$5:$O$40),_xlfn.XLOOKUP(_xlpm.iso,'[3]Pillar-2'!$B$5:$B$40,'[3]Pillar-2'!$P$5:$P$40),_xlfn.XLOOKUP(_xlpm.iso,'[3]Pillar-2'!$B$5:$B$40,'[3]Pillar-2'!$Q$5:$Q$40),_xlfn.XLOOKUP(_xlpm.iso,'[3]Pillar-2'!$B$5:$B$40,'[3]Pillar-2'!$R$5:$R$40),_xlfn.XLOOKUP(_xlpm.iso,'[3]Pillar-3'!$B$5:$B$40,'[3]Pillar-3'!$H$5:$H$40),_xlfn.XLOOKUP(_xlpm.iso,'[3]Pillar-3'!$B$5:$B$40,'[3]Pillar-3'!$I$5:$I$40),_xlfn.XLOOKUP(_xlpm.iso,'[3]Pillar-3'!$B$5:$B$40,'[3]Pillar-3'!$J$5:$J$40),_xlfn.XLOOKUP(_xlpm.iso,'[3]Pillar-3'!$B$5:$B$40,'[3]Pillar-3'!$K$5:$K$40),_xlfn.XLOOKUP(_xlpm.iso,'[3]Pillar-3'!$B$5:$B$40,'[3]Pillar-3'!$L$5:$L$40),_xlfn.XLOOKUP(_xlpm.iso,'[3]Pillar-4'!$B$5:$B$40,'[3]Pillar-4'!$K$5:$K$40),_xlfn.XLOOKUP(_xlpm.iso,'[3]Pillar-4'!$B$5:$B$40,'[3]Pillar-4'!$L$5:$L$40),_xlfn.XLOOKUP(_xlpm.iso,'[3]Pillar-4'!$B$5:$B$40,'[3]Pillar-4'!$M$5:$M$40),_xlfn.XLOOKUP(_xlpm.iso,'[3]Pillar-4'!$B$5:$B$40,'[3]Pillar-4'!$N$5:$N$40),_xlfn.XLOOKUP(_xlpm.iso,'[3]Pillar-4'!$B$5:$B$40,'[3]Pillar-4'!$O$5:$O$40),_xlfn.XLOOKUP(_xlpm.iso,'[3]Pillar-5'!$B$5:$B$40,'[3]Pillar-5'!$I$5:$I$40),_xlfn.XLOOKUP(_xlpm.iso,'[3]Pillar-5'!$B$5:$B$40,'[3]Pillar-5'!$J$5:$J$40),_xlfn.XLOOKUP(_xlpm.iso,'[3]Pillar-5'!$B$5:$B$40,'[3]Pillar-5'!$K$5:$K$40),_xlfn.XLOOKUP(_xlpm.iso,'[3]Pillar-5'!$B$5:$B$40,'[3]Pillar-5'!$L$5:$L$40),_xlfn.XLOOKUP(_xlpm.iso,'[3]Pillar-6'!$B$5:$B$40,'[3]Pillar-6'!$I$5:$I$40),_xlfn.XLOOKUP(_xlpm.iso,'[3]Pillar-6'!$B$5:$B$40,'[3]Pillar-6'!$K$5:$K$40),_xlfn.XLOOKUP(_xlpm.iso,'[3]Pillar-6'!$B$5:$B$40,'[3]Pillar-6'!$L$5:$L$40)),SUMPRODUCT(_xlpm.s,$I$4:$I$31)),"") -> 62.473414 | F36: =IF(E36="","",_xlfn.RANK.EQ(E36,$E$36:$E$71,0)) -> 7 | G36: =IF(E36="","",E36-C36) -> -0.55459152 | H36: =IF(F36="","",D36-F36) -> -1 | I36: =IFERROR(_xlfn.LET(_xlpm.iso,$B36,_xlpm.s,_xlfn.VSTACK(_xlfn.XLOOKUP(_xlpm.iso,'[3]Pillar-1'!$B$5:$B$40,'[3]Pillar-1'!$J$5:$J$40),_xlfn.XLOOKUP(_xlpm.iso,'[3]Pillar-1'!$B$5:$B$40,'[3]Pillar-1'!$K$5:$K$40),_xlfn.XLOOKUP(_xlpm.iso,'[3]Pillar-1'!$B$5:$B$40,'[3]Pillar-1'!$L$5:$L$40),_xlfn.XLOOKUP(_xlpm.iso,'[3]Pillar-2'!$B$5:$B$40,'[3]Pillar-2'!$K$5:$K$40),_xlfn.XLOOKUP(_xlpm.iso,'[3]Pillar-2'!$B$5:$B$40,'[3]Pillar-2'!$L$5:$L$40),_xlfn.XLOOKUP(_xlpm.iso,'[3]Pillar-2'!$B$5:$B$40,'[3]Pillar-2'!$M$5:$M$40),_xlfn.XLOOKUP(_xlpm.iso,'[3]Pillar-2'!$B$5:$B$40,'[3]Pillar-2'!$N$5:$N$40),_xlfn.XLOOKUP(_xlpm.iso,'[3]Pillar-2'!$B$5:$B$40,'[3]Pillar-2'!$O$5:$O$40),_xlfn.XLOOKUP(_xlpm.iso,'[3]Pillar-2'!$B$5:$B$40,'[3]Pillar-2'!$P$5:$P$40),_xlfn.XLOOKUP(_xlpm.iso,'[3]Pillar-2'!$B$5:$B$40,'[3]Pillar-2'!$Q$5:$Q$40),_xlfn.XLOOKUP(_xlpm.iso,'[3]Pillar-2'!$B$5:$B$40,'[3]Pillar-2'!$R$5:$R$40),_xlfn.XLOOKUP(_xlpm.iso,'[3]Pillar-3'!$B$5:$B$40,'[3]Pillar-3'!$H$5:$H$40),_xlfn.XLOOKUP(_xlpm.iso,'[3]Pillar-3'!$B$5:$B$40,'[3]Pillar-3'!$I$5:$I$40),_xlfn.XLOOKUP(_xlpm.iso,'[3]Pillar-3'!$B$5:$B$40,'[3]Pillar-3'!$J$5:$J$40),_xlfn.XLOOKUP(_xlpm.iso,'[3]Pillar-3'!$B$5:$B$40,'[3]Pillar-3'!$K$5:$K$40),_xlfn.XLOOKUP(_xlpm.iso,'[3]Pillar-3'!$B$5:$B$40,'[3]Pillar-3'!$L$5:$L$40),_xlfn.XLOOKUP(_xlpm.iso,'[3]Pillar-4'!$B$5:$B$40,'[3]Pillar-4'!$K$5:$K$40),_xlfn.XLOOKUP(_xlpm.iso,'[3]Pillar-4'!$B$5:$B$40,'[3]Pillar-4'!$L$5:$L$40),_xlfn.XLOOKUP(_xlpm.iso,'[3]Pillar-4'!$B$5:$B$40,'[3]Pillar-4'!$M$5:$M$40),_xlfn.XLOOKUP(_xlpm.iso,'[3]Pillar-4'!$B$5:$B$40,'[3]Pillar-4'!$N$5:$N$40),_xlfn.XLOOKUP(_xlpm.iso,'[3]Pillar-4'!$B$5:$B$40,'[3]Pillar-4'!$O$5:$O$40),_xlfn.XLOOKUP(_xlpm.iso,'[3]Pillar-5'!$B$5:$B$40,'[3]Pillar-5'!$I$5:$I$40),_xlfn.XLOOKUP(_xlpm.iso,'[3]Pillar-5'!$B$5:$B$40,'[3]Pillar-5'!$J$5:$J$40),_xlfn.XLOOKUP(_xlpm.iso,'[3]Pillar-5'!$B$5:$B$40,'[3]Pillar-5'!$K$5:$K$40),_xlfn.XLOOKUP(_xlpm.iso,'[3]Pillar-5'!$B$5:$B$40,'[3]Pillar-5'!$L$5:$L$40),_xlfn.XLOOKUP(_xlpm.iso,'[3]Pillar-6'!$B$5:$B$40,'[3]Pillar-6'!$I$5:$I$40),_xlfn.XLOOKUP(_xlpm.iso,'[3]Pillar-6'!$B$5:$B$40,'[3]Pillar-6'!$K$5:$K$40),_xlfn.XLOOKUP(_xlpm.iso,'[3]Pillar-6'!$B$5:$B$40,'[3]Pillar-6'!$L$5:$L$40)),SUMPRODUCT(_xlpm.s,$K$4:$K$31)),"") -> 62.558096 | J36: =IF(I36="","",_xlfn.RANK.EQ(I36,$I$36:$I$71,0)) -> 7 | K36: =IF(J36="","",D36-J36) -> -1
A37: Bangladesh | B37: BGD | C37: =_xlfn.XLOOKUP($B37,[3]INDEX!$B$4:$B$39,[3]INDEX!$I$4:$I$39,"") -> 35.835974 | D37: =_xlfn.XLOOKUP($B37,[3]INDEX!$B$4:$B$39,[3]INDEX!$J$4:$J$39,"") -> 36 | E37: =IFERROR(_xlfn.LET(_xlpm.iso,$B37,_xlpm.s,_xlfn.VSTACK(_xlfn.XLOOKUP(_xlpm.iso,'[3]Pillar-1'!$B$5:$B$40,'[3]Pillar-1'!$J$5:$J$40),_xlfn.XLOOKUP(_xlpm.iso,'[3]Pillar-1'!$B$5:$B$40,'[3]Pillar-1'!$K$5:$K$40),_xlfn.XLOOKUP(_xlpm.iso,'[3]Pillar-1'!$B$5:$B$40,'[3]Pillar-1'!$L$5:$L$40),_xlfn.XLOOKUP(_xlpm.iso,'[3]Pillar-2'!$B$5:$B$40,'[3]Pillar-2'!$K$5:$K$40),_xlfn.XLOOKUP(_xlpm.iso,'[3]Pillar-2'!$B$5:$B$40,'[3]Pillar-2'!$L$5:$L$40),_xlfn.XLOOKUP(_xlpm.iso,'[3]Pillar-2'!$B$5:$B$40,'[3]Pillar-2'!$M$5:$M$40),_xlfn.XLOOKUP(_xlpm.iso,'[3]Pillar-2'!$B$5:$B$40,'[3]Pillar-2'!$N$5:$N$40),_xlfn.XLOOKUP(_xlpm.iso,'[3]Pillar-2'!$B$5:$B$40,'[3]Pillar-2'!$O$5:$O$40),_xlfn.XLOOKUP(_xlpm.iso,'[3]Pillar-2'!$B$5:$B$40,'[3]Pillar-2'!$P$5:$P$40),_xlfn.XLOOKUP(_xlpm.iso,'[3]Pillar-2'!$B$5:$B$40,'[3]Pillar-2'!$Q$5:$Q$40),_xlfn.XLOOKUP(_xlpm.iso,'[3]Pillar-2'!$B$5:$B$40,'[3]Pillar-2'!$R$5:$R$40),_xlfn.XLOOKUP(_xlpm.iso,'[3]Pillar-3'!$B$5:$B$40,'[3]Pillar-3'!$H$5:$H$40),_xlfn.XLOOKUP(_xlpm.iso,'[3]Pillar-3'!$B$5:$B$40,'[3]Pillar-3'!$I$5:$I$40),_xlfn.XLOOKUP(_xlpm.iso,'[3]Pillar-3'!$B$5:$B$40,'[3]Pillar-3'!$J$5:$J$40),_xlfn.XLOOKUP(_xlpm.iso,'[3]Pillar-3'!$B$5:$B$40,'[3]Pillar-3'!$K$5:$K$40),_xlfn.XLOOKUP(_xlpm.iso,'[3]Pillar-3'!$B$5:$B$40,'[3]Pillar-3'!$L$5:$L$40),_xlfn.XLOOKUP(_xlpm.iso,'[3]Pillar-4'!$B$5:$B$40,'[3]Pillar-4'!$K$5:$K$40),_xlfn.XLOOKUP(_xlpm.iso,'[3]Pillar-4'!$B$5:$B$40,'[3]Pillar-4'!$L$5:$L$40),_xlfn.XLOOKUP(_xlpm.iso,'[3]Pillar-4'!$B$5:$B$40,'[3]Pillar-4'!$M$5:$M$40),_xlfn.XLOOKUP(_xlpm.iso,'[3]Pillar-4'!$B$5:$B$40,'[3]Pillar-4'!$N$5:$N$40),_xlfn.XLOOKUP(_xlpm.iso,'[3]Pillar-4'!$B$5:$B$40,'[3]Pillar-4'!$O$5:$O$40),_xlfn.XLOOKUP(_xlpm.iso,'[3]Pillar-5'!$B$5:$B$40,'[3]Pillar-5'!$I$5:$I$40),_xlfn.XLOOKUP(_xlpm.iso,'[3]Pillar-5'!$B$5:$B$40,'[3]Pillar-5'!$J$5:$J$40),_xlfn.XLOOKUP(_xlpm.iso,'[3]Pillar-5'!$B$5:$B$40,'[3]Pillar-5'!$K$5:$K$40),_xlfn.XLOOKUP(_xlpm.iso,'[3]Pillar-5'!$B$5:$B$40,'[3]Pillar-5'!$L$5:$L$40),_xlfn.XLOOKUP(_xlpm.iso,'[3]Pillar-6'!$B$5:$B$40,'[3]Pillar-6'!$I$5:$I$40),_xlfn.XLOOKUP(_xlpm.iso,'[3]Pillar-6'!$B$5:$B$40,'[3]Pillar-6'!$K$5:$K$40),_xlfn.XLOOKUP(_xlpm.iso,'[3]Pillar-6'!$B$5:$B$40,'[3]Pillar-6'!$L$5:$L$40)),SUMPRODUCT(_xlpm.s,$I$4:$I$31)),"") -> 35.910616 | F37: =IF(E37="","",_xlfn.RANK.EQ(E37,$E$36:$E$71,0)) -> 35 | G37: =IF(E37="","",E37-C37) -> 0.074641857 | H37: =IF(F37="","",D37-F37) -> 1 | I37: =IFERROR(_xlfn.LET(_xlpm.iso,$B37,_xlpm.s,_xlfn.VSTACK(_xlfn.XLOOKUP(_xlpm.iso,'[3]Pillar-1'!$B$5:$B$40,'[3]Pillar-1'!$J$5:$J$40),_xlfn.XLOOKUP(_xlpm.iso,'[3]Pillar-1'!$B$5:$B$40,'[3]Pillar-1'!$K$5:$K$40),_xlfn.XLOOKUP(_xlpm.iso,'[3]Pillar-1'!$B$5:$B$40,'[3]Pillar-1'!$L$5:$L$40),_xlfn.XLOOKUP(_xlpm.iso,'[3]Pillar-2'!$B$5:$B$40,'[3]Pillar-2'!$K$5:$K$40),_xlfn.XLOOKUP(_xlpm.iso,'[3]Pillar-2'!$B$5:$B$40,'[3]Pillar-2'!$L$5:$L$40),_xlfn.XLOOKUP(_xlpm.iso,'[3]Pillar-2'!$B$5:$B$40,'[3]Pillar-2'!$M$5:$M$40),_xlfn.XLOOKUP(_xlpm.iso,'[3]Pillar-2'!$B$5:$B$40,'[3]Pillar-2'!$N$5:$N$40),_xlfn.XLOOKUP(_xlpm.iso,'[3]Pillar-2'!$B$5:$B$40,'[3]Pillar-2'!$O$5:$O$40),_xlfn.XLOOKUP(_xlpm.iso,'[3]Pillar-2'!$B$5:$B$40,'[3]Pillar-2'!$P$5:$P$40),_xlfn.XLOOKUP(_xlpm.iso,'[3]Pillar-2'!$B$5:$B$40,'[3]Pillar-2'!$Q$5:$Q$40),_xlfn.XLOOKUP(_xlpm.iso,'[3]Pillar-2'!$B$5:$B$40,'[3]Pillar-2'!$R$5:$R$40),_xlfn.XLOOKUP(_xlpm.iso,'[3]Pillar-3'!$B$5:$B$40,'[3]Pillar-3'!$H$5:$H$40),_xlfn.XLOOKUP(_xlpm.iso,'[3]Pillar-3'!$B$5:$B$40,'[3]Pillar-3'!$I$5:$I$40),_xlfn.XLOOKUP(_xlpm.iso,'[3]Pillar-3'!$B$5:$B$40,'[3]Pillar-3'!$J$5:$J$40),_xlfn.XLOOKUP(_xlpm.iso,'[3]Pillar-3'!$B$5:$B$40,'[3]Pillar-3'!$K$5:$K$40),_xlfn.XLOOKUP(_xlpm.iso,'[3]Pillar-3'!$B$5:$B$40,'[3]Pillar-3'!$L$5:$L$40),_xlfn.XLOOKUP(_xlpm.iso,'[3]Pillar-4'!$B$5:$B$40,'[3]Pillar-4'!$K$5:$K$40),_xlfn.XLOOKUP(_xlpm.iso,'[3]Pillar-4'!$B$5:$B$40,'[3]Pillar-4'!$L$5:$L$40),_xlfn.XLOOKUP(_xlpm.iso,'[3]Pillar-4'!$B$5:$B$40,'[3]Pillar-4'!$M$5:$M$40),_xlfn.XLOOKUP(_xlpm.iso,'[3]Pillar-4'!$B$5:$B$40,'[3]Pillar-4'!$N$5:$N$40),_xlfn.XLOOKUP(_xlpm.iso,'[3]Pillar-4'!$B$5:$B$40,'[3]Pillar-4'!$O$5:$O$40),_xlfn.XLOOKUP(_xlpm.iso,'[3]Pillar-5'!$B$5:$B$40,'[3]Pillar-5'!$I$5:$I$40),_xlfn.XLOOKUP(_xlpm.iso,'[3]Pillar-5'!$B$5:$B$40,'[3]Pillar-5'!$J$5:$J$40),_xlfn.XLOOKUP(_xlpm.iso,'[3]Pillar-5'!$B$5:$B$40,'[3]Pillar-5'!$K$5:$K$40),_xlfn.XLOOKUP(_xlpm.iso,'[3]Pillar-5'!$B$5:$B$40,'[3]Pillar-5'!$L$5:$L$40),_xlfn.XLOOKUP(_xlpm.iso,'[3]Pillar-6'!$B$5:$B$40,'[3]Pillar-6'!$I$5:$I$40),_xlfn.XLOOKUP(_xlpm.iso,'[3]Pillar-6'!$B$5:$B$40,'[3]Pillar-6'!$K$5:$K$40),_xlfn.XLOOKUP(_xlpm.iso,'[3]Pillar-6'!$B$5:$B$40,'[3]Pillar-6'!$L$5:$L$40)),SUMPRODUCT(_xlpm.s,$K$4:$K$31)),"") -> 35.804635 | J37: =IF(I37="","",_xlfn.RANK.EQ(I37,$I$36:$I$71,0)) -> 36 | K37: =IF(J37="","",D37-J37) -> 0
A38: Bosnia and Herzegovina | B38: BIH | C38: =_xlfn.XLOOKUP($B38,[3]INDEX!$B$4:$B$39,[3]INDEX!$I$4:$I$39,"") -> 36.142382 | D38: =_xlfn.XLOOKUP($B38,[3]INDEX!$B$4:$B$39,[3]INDEX!$J$4:$J$39,"") -> 35 | E38: =IFERROR(_xlfn.LET(_xlpm.iso,$B38,_xlpm.s,_xlfn.VSTACK(_xlfn.XLOOKUP(_xlpm.iso,'[3]Pillar-1'!$B$5:$B$40,'[3]Pillar-1'!$J$5:$J$40),_xlfn.XLOOKUP(_xlpm.iso,'[3]Pillar-1'!$B$5:$B$40,'[3]Pillar-1'!$K$5:$K$40),_xlfn.XLOOKUP(_xlpm.iso,'[3]Pillar-1'!$B$5:$B$40,'[3]Pillar-1'!$L$5:$L$40),_xlfn.XLOOKUP(_xlpm.iso,'[3]Pillar-2'!$B$5:$B$40,'[3]Pillar-2'!$K$5:$K$40),_xlfn.XLOOKUP(_xlpm.iso,'[3]Pillar-2'!$B$5:$B$40,'[3]Pillar-2'!$L$5:$L$40),_xlfn.XLOOKUP(_xlpm.iso,'[3]Pillar-2'!$B$5:$B$40,'[3]Pillar-2'!$M$5:$M$40),_xlfn.XLOOKUP(_xlpm.iso,'[3]Pillar-2'!$B$5:$B$40,'[3]Pillar-2'!$N$5:$N$40),_xlfn.XLOOKUP(_xlpm.iso,'[3]Pillar-2'!$B$5:$B$40,'[3]Pillar-2'!$O$5:$O$40),_xlfn.XLOOKUP(_xlpm.iso,'[3]Pillar-2'!$B$5:$B$40,'[3]Pillar-2'!$P$5:$P$40),_xlfn.XLOOKUP(_xlpm.iso,'[3]Pillar-2'!$B$5:$B$40,'[3]Pillar-2'!$Q$5:$Q$40),_xlfn.XLOOKUP(_xlpm.iso,'[3]Pillar-2'!$B$5:$B$40,'[3]Pillar-2'!$R$5:$R$40),_xlfn.XLOOKUP(_xlpm.iso,'[3]Pillar-3'!$B$5:$B$40,'[3]Pillar-3'!$H$5:$H$40),_xlfn.XLOOKUP(_xlpm.iso,'[3]Pillar-3'!$B$5:$B$40,'[3]Pillar-3'!$I$5:$I$40),_xlfn.XLOOKUP(_xlpm.iso,'[3]Pillar-3'!$B$5:$B$40,'[3]Pillar-3'!$J$5:$J$40),_xlfn.XLOOKUP(_xlpm.iso,'[3]Pillar-3'!$B$5:$B$40,'[3]Pillar-3'!$K$5:$K$40),_xlfn.XLOOKUP(_xlpm.iso,'[3]Pillar-3'!$B$5:$B$40,'[3]Pillar-3'!$L$5:$L$40),_xlfn.XLOOKUP(_xlpm.iso,'[3]Pillar-4'!$B$5:$B$40,'[3]Pillar-4'!$K$5:$K$40),_xlfn.XLOOKUP(_xlpm.iso,'[3]Pillar-4'!$B$5:$B$40,'[3]Pillar-4'!$L$5:$L$40),_xlfn.XLOOKUP(_xlpm.iso,'[3]Pillar-4'!$B$5:$B$40,'[3]Pillar-4'!$M$5:$M$40),_xlfn.XLOOKUP(_xlpm.iso,'[3]Pillar-4'!$B$5:$B$40,'[3]Pillar-4'!$N$5:$N$40),_xlfn.XLOOKUP(_xlpm.iso,'[3]Pillar-4'!$B$5:$B$40,'[3]Pillar-4'!$O$5:$O$40),_xlfn.XLOOKUP(_xlpm.iso,'[3]Pillar-5'!$B$5:$B$40,'[3]Pillar-5'!$I$5:$I$40),_xlfn.XLOOKUP(_xlpm.iso,'[3]Pillar-5'!$B$5:$B$40,'[3]Pillar-5'!$J$5:$J$40),_xlfn.XLOOKUP(_xlpm.iso,'[3]Pillar-5'!$B$5:$B$40,'[3]Pillar-5'!$K$5:$K$40),_xlfn.XLOOKUP(_xlpm.iso,'[3]Pillar-5'!$B$5:$B$40,'[3]Pillar-5'!$L$5:$L$40),_xlfn.XLOOKUP(_xlpm.iso,'[3]Pillar-6'!$B$5:$B$40,'[3]Pillar-6'!$I$5:$I$40),_xlfn.XLOOKUP(_xlpm.iso,'[3]Pillar-6'!$B$5:$B$40,'[3]Pillar-6'!$K$5:$K$40),_xlfn.XLOOKUP(_xlpm.iso,'[3]Pillar-6'!$B$5:$B$40,'[3]Pillar-6'!$L$5:$L$40)),SUMPRODUCT(_xlpm.s,$I$4:$I$31)),"") -> 35.689199 | F38: =IF(E38="","",_xlfn.RANK.EQ(E38,$E$36:$E$71,0)) -> 36 | G38: =IF(E38="","",E38-C38) -> -0.45318365 | H38: =IF(F38="","",D38-F38) -> -1 | I38: =IFERROR(_xlfn.LET(_xlpm.iso,$B38,_xlpm.s,_xlfn.VSTACK(_xlfn.XLOOKUP(_xlpm.iso,'[3]Pillar-1'!$B$5:$B$40,'[3]Pillar-1'!$J$5:$J$40),_xlfn.XLOOKUP(_xlpm.iso,'[3]Pillar-1'!$B$5:$B$40,'[3]Pillar-1'!$K$5:$K$40),_xlfn.XLOOKUP(_xlpm.iso,'[3]Pillar-1'!$B$5:$B$40,'[3]Pillar-1'!$L$5:$L$40),_xlfn.XLOOKUP(_xlpm.iso,'[3]Pillar-2'!$B$5:$B$40,'[3]Pillar-2'!$K$5:$K$40),_xlfn.XLOOKUP(_xlpm.iso,'[3]Pillar-2'!$B$5:$B$40,'[3]Pillar-2'!$L$5:$L$40),_xlfn.XLOOKUP(_xlpm.iso,'[3]Pillar-2'!$B$5:$B$40,'[3]Pillar-2'!$M$5:$M$40),_xlfn.XLOOKUP(_xlpm.iso,'[3]Pillar-2'!$B$5:$B$40,'[3]Pillar-2'!$N$5:$N$40),_xlfn.XLOOKUP(_xlpm.iso,'[3]Pillar-2'!$B$5:$B$40,'[3]Pillar-2'!$O$5:$O$40),_xlfn.XLOOKUP(_xlpm.iso,'[3]Pillar-2'!$B$5:$B$40,'[3]Pillar-2'!$P$5:$P$40),_xlfn.XLOOKUP(_xlpm.iso,'[3]Pillar-2'!$B$5:$B$40,'[3]Pillar-2'!$Q$5:$Q$40),_xlfn.XLOOKUP(_xlpm.iso,'[3]Pillar-2'!$B$5:$B$40,'[3]Pillar-2'!$R$5:$R$40),_xlfn.XLOOKUP(_xlpm.iso,'[3]Pillar-3'!$B$5:$B$40,'[3]Pillar-3'!$H$5:$H$40),_xlfn.XLOOKUP(_xlpm.iso,'[3]Pillar-3'!$B$5:$B$40,'[3]Pillar-3'!$I$5:$I$40),_xlfn.XLOOKUP(_xlpm.iso,'[3]Pillar-3'!$B$5:$B$40,'[3]Pillar-3'!$J$5:$J$40),_xlfn.XLOOKUP(_xlpm.iso,'[3]Pillar-3'!$B$5:$B$40,'[3]Pillar-3'!$K$5:$K$40),_xlfn.XLOOKUP(_xlpm.iso,'[3]Pillar-3'!$B$5:$B$40,'[3]Pillar-3'!$L$5:$L$40),_xlfn.XLOOKUP(_xlpm.iso,'[3]Pillar-4'!$B$5:$B$40,'[3]Pillar-4'!$K$5:$K$40),_xlfn.XLOOKUP(_xlpm.iso,'[3]Pillar-4'!$B$5:$B$40,'[3]Pillar-4'!$L$5:$L$40),_xlfn.XLOOKUP(_xlpm.iso,'[3]Pillar-4'!$B$5:$B$40,'[3]Pillar-4'!$M$5:$M$40),_xlfn.XLOOKUP(_xlpm.iso,'[3]Pillar-4'!$B$5:$B$40,'[3]Pillar-4'!$N$5:$N$40),_xlfn.XLOOKUP(_xlpm.iso,'[3]Pillar-4'!$B$5:$B$40,'[3]Pillar-4'!$O$5:$O$40),_xlfn.XLOOKUP(_xlpm.iso,'[3]Pillar-5'!$B$5:$B$40,'[3]Pillar-5'!$I$5:$I$40),_xlfn.XLOOKUP(_xlpm.iso,'[3]Pillar-5'!$B$5:$B$40,'[3]Pillar-5'!$J$5:$J$40),_xlfn.XLOOKUP(_xlpm.iso,'[3]Pillar-5'!$B$5:$B$40,'[3]Pillar-5'!$K$5:$K$40),_xlfn.XLOOKUP(_xlpm.iso,'[3]Pillar-5'!$B$5:$B$40,'[3]Pillar-5'!$L$5:$L$40),_xlfn.XLOOKUP(_xlpm.iso,'[3]Pillar-6'!$B$5:$B$40,'[3]Pillar-6'!$I$5:$I$40),_xlfn.XLOOKUP(_xlpm.iso,'[3]Pillar-6'!$B$5:$B$40,'[3]Pillar-6'!$K$5:$K$40),_xlfn.XLOOKUP(_xlpm.iso,'[3]Pillar-6'!$B$5:$B$40,'[3]Pillar-6'!$L$5:$L$40)),SUMPRODUCT(_xlpm.s,$K$4:$K$31)),"") -> 35.854068 | J38: =IF(I38="","",_xlfn.RANK.EQ(I38,$I$36:$I$71,0)) -> 35 | K38: =IF(J38="","",D38-J38) -> 0
A39: Brazil | B39: BRA | C39: =_xlfn.XLOOKUP($B39,[3]INDEX!$B$4:$B$39,[3]INDEX!$I$4:$I$39,"") -> 64.650458 | D39: =_xlfn.XLOOKUP($B39,[3]INDEX!$B$4:$B$39,[3]INDEX!$J$4:$J$39,"") -> 5 | E39: =IFERROR(_xlfn.LET(_xlpm.iso,$B39,_xlpm.s,_xlfn.VSTACK(_xlfn.XLOOKUP(_xlpm.iso,'[3]Pillar-1'!$B$5:$B$40,'[3]Pillar-1'!$J$5:$J$40),_xlfn.XLOOKUP(_xlpm.iso,'[3]Pillar-1'!$B$5:$B$40,'[3]Pillar-1'!$K$5:$K$40),_xlfn.XLOOKUP(_xlpm.iso,'[3]Pillar-1'!$B$5:$B$40,'[3]Pillar-1'!$L$5:$L$40),_xlfn.XLOOKUP(_xlpm.iso,'[3]Pillar-2'!$B$5:$B$40,'[3]Pillar-2'!$K$5:$K$40),_xlfn.XLOOKUP(_xlpm.iso,'[3]Pillar-2'!$B$5:$B$40,'[3]Pillar-2'!$L$5:$L$40),_xlfn.XLOOKUP(_xlpm.iso,'[3]Pillar-2'!$B$5:$B$40,'[3]Pillar-2'!$M$5:$M$40),_xlfn.XLOOKUP(_xlpm.iso,'[3]Pillar-2'!$B$5:$B$40,'[3]Pillar-2'!$N$5:$N$40),_xlfn.XLOOKUP(_xlpm.iso,'[3]Pillar-2'!$B$5:$B$40,'[3]Pillar-2'!$O$5:$O$40),_xlfn.XLOOKUP(_xlpm.iso,'[3]Pillar-2'!$B$5:$B$40,'[3]Pillar-2'!$P$5:$P$40),_xlfn.XLOOKUP(_xlpm.iso,'[3]Pillar-2'!$B$5:$B$40,'[3]Pillar-2'!$Q$5:$Q$40),_xlfn.XLOOKUP(_xlpm.iso,'[3]Pillar-2'!$B$5:$B$40,'[3]Pillar-2'!$R$5:$R$40),_xlfn.XLOOKUP(_xlpm.iso,'[3]Pillar-3'!$B$5:$B$40,'[3]Pillar-3'!$H$5:$H$40),_xlfn.XLOOKUP(_xlpm.iso,'[3]Pillar-3'!$B$5:$B$40,'[3]Pillar-3'!$I$5:$I$40),_xlfn.XLOOKUP(_xlpm.iso,'[3]Pillar-3'!$B$5:$B$40,'[3]Pillar-3'!$J$5:$J$40),_xlfn.XLOOKUP(_xlpm.iso,'[3]Pillar-3'!$B$5:$B$40,'[3]Pillar-3'!$K$5:$K$40),_xlfn.XLOOKUP(_xlpm.iso,'[3]Pillar-3'!$B$5:$B$40,'[3]Pillar-3'!$L$5:$L$40),_xlfn.XLOOKUP(_xlpm.iso,'[3]Pillar-4'!$B$5:$B$40,'[3]Pillar-4'!$K$5:$K$40),_xlfn.XLOOKUP(_xlpm.iso,'[3]Pillar-4'!$B$5:$B$40,'[3]Pillar-4'!$L$5:$L$40),_xlfn.XLOOKUP(_xlpm.iso,'[3]Pillar-4'!$B$5:$B$40,'[3]Pillar-4'!$M$5:$M$40),_xlfn.XLOOKUP(_xlpm.iso,'[3]Pillar-4'!$B$5:$B$40,'[3]Pillar-4'!$N$5:$N$40),_xlfn.XLOOKUP(_xlpm.iso,'[3]Pillar-4'!$B$5:$B$40,'[3]Pillar-4'!$O$5:$O$40),_xlfn.XLOOKUP(_xlpm.iso,'[3]Pillar-5'!$B$5:$B$40,'[3]Pillar-5'!$I$5:$I$40),_xlfn.XLOOKUP(_xlpm.iso,'[3]Pillar-5'!$B$5:$B$40,'[3]Pillar-5'!$J$5:$J$40),_xlfn.XLOOKUP(_xlpm.iso,'[3]Pillar-5'!$B$5:$B$40,'[3]Pillar-5'!$K$5:$K$40),_xlfn.XLOOKUP(_xlpm.iso,'[3]Pillar-5'!$B$5:$B$40,'[3]Pillar-5'!$L$5:$L$40),_xlfn.XLOOKUP(_xlpm.iso,'[3]Pillar-6'!$B$5:$B$40,'[3]Pillar-6'!$I$5:$I$40),_xlfn.XLOOKUP(_xlpm.iso,'[3]Pillar-6'!$B$5:$B$40,'[3]Pillar-6'!$K$5:$K$40),_xlfn.XLOOKUP(_xlpm.iso,'[3]Pillar-6'!$B$5:$B$40,'[3]Pillar-6'!$L$5:$L$40)),SUMPRODUCT(_xlpm.s,$I$4:$I$31)),"") -> 63.893083 | F39: =IF(E39="","",_xlfn.RANK.EQ(E39,$E$36:$E$71,0)) -> 5 | G39: =IF(E39="","",E39-C39) -> -0.7573752 | H39: =IF(F39="","",D39-F39) -> 0 | I39: =IFERROR(_xlfn.LET(_xlpm.iso,$B39,_xlpm.s,_xlfn.VSTACK(_xlfn.XLOOKUP(_xlpm.iso,'[3]Pillar-1'!$B$5:$B$40,'[3]Pillar-1'!$J$5:$J$40),_xlfn.XLOOKUP(_xlpm.iso,'[3]Pillar-1'!$B$5:$B$40,'[3]Pillar-1'!$K$5:$K$40),_xlfn.XLOOKUP(_xlpm.iso,'[3]Pillar-1'!$B$5:$B$40,'[3]Pillar-1'!$L$5:$L$40),_xlfn.XLOOKUP(_xlpm.iso,'[3]Pillar-2'!$B$5:$B$40,'[3]Pillar-2'!$K$5:$K$40),_xlfn.XLOOKUP(_xlpm.iso,'[3]Pillar-2'!$B$5:$B$40,'[3]Pillar-2'!$L$5:$L$40),_xlfn.XLOOKUP(_xlpm.iso,'[3]Pillar-2'!$B$5:$B$40,'[3]Pillar-2'!$M$5:$M$40),_xlfn.XLOOKUP(_xlpm.iso,'[3]Pillar-2'!$B$5:$B$40,'[3]Pillar-2'!$N$5:$N$40),_xlfn.XLOOKUP(_xlpm.iso,'[3]Pillar-2'!$B$5:$B$40,'[3]Pillar-2'!$O$5:$O$40),_xlfn.XLOOKUP(_xlpm.iso,'[3]Pillar-2'!$B$5:$B$40,'[3]Pillar-2'!$P$5:$P$40),_xlfn.XLOOKUP(_xlpm.iso,'[3]Pillar-2'!$B$5:$B$40,'[3]Pillar-2'!$Q$5:$Q$40),_xlfn.XLOOKUP(_xlpm.iso,'[3]Pillar-2'!$B$5:$B$40,'[3]Pillar-2'!$R$5:$R$40),_xlfn.XLOOKUP(_xlpm.iso,'[3]Pillar-3'!$B$5:$B$40,'[3]Pillar-3'!$H$5:$H$40),_xlfn.XLOOKUP(_xlpm.iso,'[3]Pillar-3'!$B$5:$B$40,'[3]Pillar-3'!$I$5:$I$40),_xlfn.XLOOKUP(_xlpm.iso,'[3]Pillar-3'!$B$5:$B$40,'[3]Pillar-3'!$J$5:$J$40),_xlfn.XLOOKUP(_xlpm.iso,'[3]Pillar-3'!$B$5:$B$40,'[3]Pillar-3'!$K$5:$K$40),_xlfn.XLOOKUP(_xlpm.iso,'[3]Pillar-3'!$B$5:$B$40,'[3]Pillar-3'!$L$5:$L$40),_xlfn.XLOOKUP(_xlpm.iso,'[3]Pillar-4'!$B$5:$B$40,'[3]Pillar-4'!$K$5:$K$40),_xlfn.XLOOKUP(_xlpm.iso,'[3]Pillar-4'!$B$5:$B$40,'[3]Pillar-4'!$L$5:$L$40),_xlfn.XLOOKUP(_xlpm.iso,'[3]Pillar-4'!$B$5:$B$40,'[3]Pillar-4'!$M$5:$M$40),_xlfn.XLOOKUP(_xlpm.iso,'[3]Pillar-4'!$B$5:$B$40,'[3]Pillar-4'!$N$5:$N$40),_xlfn.XLOOKUP(_xlpm.iso,'[3]Pillar-4'!$B$5:$B$40,'[3]Pillar-4'!$O$5:$O$40),_xlfn.XLOOKUP(_xlpm.iso,'[3]Pillar-5'!$B$5:$B$40,'[3]Pillar-5'!$I$5:$I$40),_xlfn.XLOOKUP(_xlpm.iso,'[3]Pillar-5'!$B$5:$B$40,'[3]Pillar-5'!$J$5:$J$40),_xlfn.XLOOKUP(_xlpm.iso,'[3]Pillar-5'!$B$5:$B$40,'[3]Pillar-5'!$K$5:$K$40),_xlfn.XLOOKUP(_xlpm.iso,'[3]Pillar-5'!$B$5:$B$40,'[3]Pillar-5'!$L$5:$L$40),_xlfn.XLOOKUP(_xlpm.iso,'[3]Pillar-6'!$B$5:$B$40,'[3]Pillar-6'!$I$5:$I$40),_xlfn.XLOOKUP(_xlpm.iso,'[3]Pillar-6'!$B$5:$B$40,'[3]Pillar-6'!$K$5:$K$40),_xlfn.XLOOKUP(_xlpm.iso,'[3]Pillar-6'!$B$5:$B$40,'[3]Pillar-6'!$L$5:$L$40)),SUMPRODUCT(_xlpm.s,$K$4:$K$31)),"") -> 64.208841 | J39: =IF(I39="","",_xlfn.RANK.EQ(I39,$I$36:$I$71,0)) -> 5 | K39: =IF(J39="","",D39-J39) -> 0
A40: Bulgaria | B40: BGR | C40: =_xlfn.XLOOKUP($B40,[3]INDEX!$B$4:$B$39,[3]INDEX!$I$4:$I$39,"") -> 57.30298 | D40: =_xlfn.XLOOKUP($B40,[3]INDEX!$B$4:$B$39,[3]INDEX!$J$4:$J$39,"") -> 11 | E40: =IFERROR(_xlfn.LET(_xlpm.iso,$B40,_xlpm.s,_xlfn.VSTACK(_xlfn.XLOOKUP(_xlpm.iso,'[3]Pillar-1'!$B$5:$B$40,'[3]Pillar-1'!$J$5:$J$40),_xlfn.XLOOKUP(_xlpm.iso,'[3]Pillar-1'!$B$5:$B$40,'[3]Pillar-1'!$K$5:$K$40),_xlfn.XLOOKUP(_xlpm.iso,'[3]Pillar-1'!$B$5:$B$40,'[3]Pillar-1'!$L$5:$L$40),_xlfn.XLOOKUP(_xlpm.iso,'[3]Pillar-2'!$B$5:$B$40,'[3]Pillar-2'!$K$5:$K$40),_xlfn.XLOOKUP(_xlpm.iso,'[3]Pillar-2'!$B$5:$B$40,'[3]Pillar-2'!$L$5:$L$40),_xlfn.XLOOKUP(_xlpm.iso,'[3]Pillar-2'!$B$5:$B$40,'[3]Pillar-2'!$M$5:$M$40),_xlfn.XLOOKUP(_xlpm.iso,'[3]Pillar-2'!$B$5:$B$40,'[3]Pillar-2'!$N$5:$N$40),_xlfn.XLOOKUP(_xlpm.iso,'[3]Pillar-2'!$B$5:$B$40,'[3]Pillar-2'!$O$5:$O$40),_xlfn.XLOOKUP(_xlpm.iso,'[3]Pillar-2'!$B$5:$B$40,'[3]Pillar-2'!$P$5:$P$40),_xlfn.XLOOKUP(_xlpm.iso,'[3]Pillar-2'!$B$5:$B$40,'[3]Pillar-2'!$Q$5:$Q$40),_xlfn.XLOOKUP(_xlpm.iso,'[3]Pillar-2'!$B$5:$B$40,'[3]Pillar-2'!$R$5:$R$40),_xlfn.XLOOKUP(_xlpm.iso,'[3]Pillar-3'!$B$5:$B$40,'[3]Pillar-3'!$H$5:$H$40),_xlfn.XLOOKUP(_xlpm.iso,'[3]Pillar-3'!$B$5:$B$40,'[3]Pillar-3'!$I$5:$I$40),_xlfn.XLOOKUP(_xlpm.iso,'[3]Pillar-3'!$B$5:$B$40,'[3]Pillar-3'!$J$5:$J$40),_xlfn.XLOOKUP(_xlpm.iso,'[3]Pillar-3'!$B$5:$B$40,'[3]Pillar-3'!$K$5:$K$40),_xlfn.XLOOKUP(_xlpm.iso,'[3]Pillar-3'!$B$5:$B$40,'[3]Pillar-3'!$L$5:$L$40),_xlfn.XLOOKUP(_xlpm.iso,'[3]Pillar-4'!$B$5:$B$40,'[3]Pillar-4'!$K$5:$K$40),_xlfn.XLOOKUP(_xlpm.iso,'[3]Pillar-4'!$B$5:$B$40,'[3]Pillar-4'!$L$5:$L$40),_xlfn.XLOOKUP(_xlpm.iso,'[3]Pillar-4'!$B$5:$B$40,'[3]Pillar-4'!$M$5:$M$40),_xlfn.XLOOKUP(_xlpm.iso,'[3]Pillar-4'!$B$5:$B$40,'[3]Pillar-4'!$N$5:$N$40),_xlfn.XLOOKUP(_xlpm.iso,'[3]Pillar-4'!$B$5:$B$40,'[3]Pillar-4'!$O$5:$O$40),_xlfn.XLOOKUP(_xlpm.iso,'[3]Pillar-5'!$B$5:$B$40,'[3]Pillar-5'!$I$5:$I$40),_xlfn.XLOOKUP(_xlpm.iso,'[3]Pillar-5'!$B$5:$B$40,'[3]Pillar-5'!$J$5:$J$40),_xlfn.XLOOKUP(_xlpm.iso,'[3]Pillar-5'!$B$5:$B$40,'[3]Pillar-5'!$K$5:$K$40),_xlfn.XLOOKUP(_xlpm.iso,'[3]Pillar-5'!$B$5:$B$40,'[3]Pillar-5'!$L$5:$L$40),_xlfn.XLOOKUP(_xlpm.iso,'[3]Pillar-6'!$B$5:$B$40,'[3]Pillar-6'!$I$5:$I$40),_xlfn.XLOOKUP(_xlpm.iso,'[3]Pillar-6'!$B$5:$B$40,'[3]Pillar-6'!$K$5:$K$40),_xlfn.XLOOKUP(_xlpm.iso,'[3]Pillar-6'!$B$5:$B$40,'[3]Pillar-6'!$L$5:$L$40)),SUMPRODUCT(_xlpm.s,$I$4:$I$31)),"") -> 56.594006 | F40: =IF(E40="","",_xlfn.RANK.EQ(E40,$E$36:$E$71,0)) -> 12 | G40: =IF(E40="","",E40-C40) -> -0.70897393 | H40: =IF(F40="","",D40-F40) -> -1 | I40: =IFERROR(_xlfn.LET(_xlpm.iso,$B40,_xlpm.s,_xlfn.VSTACK(_xlfn.XLOOKUP(_xlpm.iso,'[3]Pillar-1'!$B$5:$B$40,'[3]Pillar-1'!$J$5:$J$40),_xlfn.XLOOKUP(_xlpm.iso,'[3]Pillar-1'!$B$5:$B$40,'[3]Pillar-1'!$K$5:$K$40),_xlfn.XLOOKUP(_xlpm.iso,'[3]Pillar-1'!$B$5:$B$40,'[3]Pillar-1'!$L$5:$L$40),_xlfn.XLOOKUP(_xlpm.iso,'[3]Pillar-2'!$B$5:$B$40,'[3]Pillar-2'!$K$5:$K$40),_xlfn.XLOOKUP(_xlpm.iso,'[3]Pillar-2'!$B$5:$B$40,'[3]Pillar-2'!$L$5:$L$40),_xlfn.XLOOKUP(_xlpm.iso,'[3]Pillar-2'!$B$5:$B$40,'[3]Pillar-2'!$M$5:$M$40),_xlfn.XLOOKUP(_xlpm.iso,'[3]Pillar-2'!$B$5:$B$40,'[3]Pillar-2'!$N$5:$N$40),_xlfn.XLOOKUP(_xlpm.iso,'[3]Pillar-2'!$B$5:$B$40,'[3]Pillar-2'!$O$5:$O$40),_xlfn.XLOOKUP(_xlpm.iso,'[3]Pillar-2'!$B$5:$B$40,'[3]Pillar-2'!$P$5:$P$40),_xlfn.XLOOKUP(_xlpm.iso,'[3]Pillar-2'!$B$5:$B$40,'[3]Pillar-2'!$Q$5:$Q$40),_xlfn.XLOOKUP(_xlpm.iso,'[3]Pillar-2'!$B$5:$B$40,'[3]Pillar-2'!$R$5:$R$40),_xlfn.XLOOKUP(_xlpm.iso,'[3]Pillar-3'!$B$5:$B$40,'[3]Pillar-3'!$H$5:$H$40),_xlfn.XLOOKUP(_xlpm.iso,'[3]Pillar-3'!$B$5:$B$40,'[3]Pillar-3'!$I$5:$I$40),_xlfn.XLOOKUP(_xlpm.iso,'[3]Pillar-3'!$B$5:$B$40,'[3]Pillar-3'!$J$5:$J$40),_xlfn.XLOOKUP(_xlpm.iso,'[3]Pillar-3'!$B$5:$B$40,'[3]Pillar-3'!$K$5:$K$40),_xlfn.XLOOKUP(_xlpm.iso,'[3]Pillar-3'!$B$5:$B$40,'[3]Pillar-3'!$L$5:$L$40),_xlfn.XLOOKUP(_xlpm.iso,'[3]Pillar-4'!$B$5:$B$40,'[3]Pillar-4'!$K$5:$K$40),_xlfn.XLOOKUP(_xlpm.iso,'[3]Pillar-4'!$B$5:$B$40,'[3]Pillar-4'!$L$5:$L$40),_xlfn.XLOOKUP(_xlpm.iso,'[3]Pillar-4'!$B$5:$B$40,'[3]Pillar-4'!$M$5:$M$40),_xlfn.XLOOKUP(_xlpm.iso,'[3]Pillar-4'!$B$5:$B$40,'[3]Pillar-4'!$N$5:$N$40),_xlfn.XLOOKUP(_xlpm.iso,'[3]Pillar-4'!$B$5:$B$40,'[3]Pillar-4'!$O$5:$O$40),_xlfn.XLOOKUP(_xlpm.iso,'[3]Pillar-5'!$B$5:$B$40,'[3]Pillar-5'!$I$5:$I$40),_xlfn.XLOOKUP(_xlpm.iso,'[3]Pillar-5'!$B$5:$B$40,'[3]Pillar-5'!$J$5:$J$40),_xlfn.XLOOKUP(_xlpm.iso,'[3]Pillar-5'!$B$5:$B$40,'[3]Pillar-5'!$K$5:$K$40),_xlfn.XLOOKUP(_xlpm.iso,'[3]Pillar-5'!$B$5:$B$40,'[3]Pillar-5'!$L$5:$L$40),_xlfn.XLOOKUP(_xlpm.iso,'[3]Pillar-6'!$B$5:$B$40,'[3]Pillar-6'!$I$5:$I$40),_xlfn.XLOOKUP(_xlpm.iso,'[3]Pillar-6'!$B$5:$B$40,'[3]Pillar-6'!$K$5:$K$40),_xlfn.XLOOKUP(_xlpm.iso,'[3]Pillar-6'!$B$5:$B$40,'[3]Pillar-6'!$L$5:$L$40)),SUMPRODUCT(_xlpm.s,$K$4:$K$31)),"") -> 57.033995 | J40: =IF(I40="","",_xlfn.RANK.EQ(I40,$I$36:$I$71,0)) -> 11 | K40: =IF(J40="","",D40-J40) -> 0
A41: Cambodia | B41: KHM | C41: =_xlfn.XLOOKUP($B41,[3]INDEX!$B$4:$B$39,[3]INDEX!$I$4:$I$39,"") -> 49.013545 | D41: =_xlfn.XLOOKUP($B41,[3]INDEX!$B$4:$B$39,[3]INDEX!$J$4:$J$39,"") -> 20 | E41: =IFERROR(_xlfn.LET(_xlpm.iso,$B41,_xlpm.s,_xlfn.VSTACK(_xlfn.XLOOKUP(_xlpm.iso,'[3]Pillar-1'!$B$5:$B$40,'[3]Pillar-1'!$J$5:$J$40),_xlfn.XLOOKUP(_xlpm.iso,'[3]Pillar-1'!$B$5:$B$40,'[3]Pillar-1'!$K$5:$K$40),_xlfn.XLOOKUP(_xlpm.iso,'[3]Pillar-1'!$B$5:$B$40,'[3]Pillar-1'!$L$5:$L$40),_xlfn.XLOOKUP(_xlpm.iso,'[3]Pillar-2'!$B$5:$B$40,'[3]Pillar-2'!$K$5:$K$40),_xlfn.XLOOKUP(_xlpm.iso,'[3]Pillar-2'!$B$5:$B$40,'[3]Pillar-2'!$L$5:$L$40),_xlfn.XLOOKUP(_xlpm.iso,'[3]Pillar-2'!$B$5:$B$40,'[3]Pillar-2'!$M$5:$M$40),_xlfn.XLOOKUP(_xlpm.iso,'[3]Pillar-2'!$B$5:$B$40,'[3]Pillar-2'!$N$5:$N$40),_xlfn.XLOOKUP(_xlpm.iso,'[3]Pillar-2'!$B$5:$B$40,'[3]Pillar-2'!$O$5:$O$40),_xlfn.XLOOKUP(_xlpm.iso,'[3]Pillar-2'!$B$5:$B$40,'[3]Pillar-2'!$P$5:$P$40),_xlfn.XLOOKUP(_xlpm.iso,'[3]Pillar-2'!$B$5:$B$40,'[3]Pillar-2'!$Q$5:$Q$40),_xlfn.XLOOKUP(_xlpm.iso,'[3]Pillar-2'!$B$5:$B$40,'[3]Pillar-2'!$R$5:$R$40),_xlfn.XLOOKUP(_xlpm.iso,'[3]Pillar-3'!$B$5:$B$40,'[3]Pillar-3'!$H$5:$H$40),_xlfn.XLOOKUP(_xlpm.iso,'[3]Pillar-3'!$B$5:$B$40,'[3]Pillar-3'!$I$5:$I$40),_xlfn.XLOOKUP(_xlpm.iso,'[3]Pillar-3'!$B$5:$B$40,'[3]Pillar-3'!$J$5:$J$40),_xlfn.XLOOKUP(_xlpm.iso,'[3]Pillar-3'!$B$5:$B$40,'[3]Pillar-3'!$K$5:$K$40),_xlfn.XLOOKUP(_xlpm.iso,'[3]Pillar-3'!$B$5:$B$40,'[3]Pillar-3'!$L$5:$L$40),_xlfn.XLOOKUP(_xlpm.iso,'[3]Pillar-4'!$B$5:$B$40,'[3]Pillar-4'!$K$5:$K$40),_xlfn.XLOOKUP(_xlpm.iso,'[3]Pillar-4'!$B$5:$B$40,'[3]Pillar-4'!$L$5:$L$40),_xlfn.XLOOKUP(_xlpm.iso,'[3]Pillar-4'!$B$5:$B$40,'[3]Pillar-4'!$M$5:$M$40),_xlfn.XLOOKUP(_xlpm.iso,'[3]Pillar-4'!$B$5:$B$40,'[3]Pillar-4'!$N$5:$N$40),_xlfn.XLOOKUP(_xlpm.iso,'[3]Pillar-4'!$B$5:$B$40,'[3]Pillar-4'!$O$5:$O$40),_xlfn.XLOOKUP(_xlpm.iso,'[3]Pillar-5'!$B$5:$B$40,'[3]Pillar-5'!$I$5:$I$40),_xlfn.XLOOKUP(_xlpm.iso,'[3]Pillar-5'!$B$5:$B$40,'[3]Pillar-5'!$J$5:$J$40),_xlfn.XLOOKUP(_xlpm.iso,'[3]Pillar-5'!$B$5:$B$40,'[3]Pillar-5'!$K$5:$K$40),_xlfn.XLOOKUP(_xlpm.iso,'[3]Pillar-5'!$B$5:$B$40,'[3]Pillar-5'!$L$5:$L$40),_xlfn.XLOOKUP(_xlpm.iso,'[3]Pillar-6'!$B$5:$B$40,'[3]Pillar-6'!$I$5:$I$40),_xlfn.XLOOKUP(_xlpm.iso,'[3]Pillar-6'!$B$5:$B$40,'[3]Pillar-6'!$K$5:$K$40),_xlfn.XLOOKUP(_xlpm.iso,'[3]Pillar-6'!$B$5:$B$40,'[3]Pillar-6'!$L$5:$L$40)),SUMPRODUCT(_xlpm.s,$I$4:$I$31)),"") -> 48.871832 | F41: =IF(E41="","",_xlfn.RANK.EQ(E41,$E$36:$E$71,0)) -> 20 | G41: =IF(E41="","",E41-C41) -> -0.14171363 | H41: =IF(F41="","",D41-F41) -> 0 | I41: =IFERROR(_xlfn.LET(_xlpm.iso,$B41,_xlpm.s,_xlfn.VSTACK(_xlfn.XLOOKUP(_xlpm.iso,'[3]Pillar-1'!$B$5:$B$40,'[3]Pillar-1'!$J$5:$J$40),_xlfn.XLOOKUP(_xlpm.iso,'[3]Pillar-1'!$B$5:$B$40,'[3]Pillar-1'!$K$5:$K$40),_xlfn.XLOOKUP(_xlpm.iso,'[3]Pillar-1'!$B$5:$B$40,'[3]Pillar-1'!$L$5:$L$40),_xlfn.XLOOKUP(_xlpm.iso,'[3]Pillar-2'!$B$5:$B$40,'[3]Pillar-2'!$K$5:$K$40),_xlfn.XLOOKUP(_xlpm.iso,'[3]Pillar-2'!$B$5:$B$40,'[3]Pillar-2'!$L$5:$L$40),_xlfn.XLOOKUP(_xlpm.iso,'[3]Pillar-2'!$B$5:$B$40,'[3]Pillar-2'!$M$5:$M$40),_xlfn.XLOOKUP(_xlpm.iso,'[3]Pillar-2'!$B$5:$B$40,'[3]Pillar-2'!$N$5:$N$40),_xlfn.XLOOKUP(_xlpm.iso,'[3]Pillar-2'!$B$5:$B$40,'[3]Pillar-2'!$O$5:$O$40),_xlfn.XLOOKUP(_xlpm.iso,'[3]Pillar-2'!$B$5:$B$40,'[3]Pillar-2'!$P$5:$P$40),_xlfn.XLOOKUP(_xlpm.iso,'[3]Pillar-2'!$B$5:$B$40,'[3]Pillar-2'!$Q$5:$Q$40),_xlfn.XLOOKUP(_xlpm.iso,'[3]Pillar-2'!$B$5:$B$40,'[3]Pillar-2'!$R$5:$R$40),_xlfn.XLOOKUP(_xlpm.iso,'[3]Pillar-3'!$B$5:$B$40,'[3]Pillar-3'!$H$5:$H$40),_xlfn.XLOOKUP(_xlpm.iso,'[3]Pillar-3'!$B$5:$B$40,'[3]Pillar-3'!$I$5:$I$40),_xlfn.XLOOKUP(_xlpm.iso,'[3]Pillar-3'!$B$5:$B$40,'[3]Pillar-3'!$J$5:$J$40),_xlfn.XLOOKUP(_xlpm.iso,'[3]Pillar-3'!$B$5:$B$40,'[3]Pillar-3'!$K$5:$K$40),_xlfn.XLOOKUP(_xlpm.iso,'[3]Pillar-3'!$B$5:$B$40,'[3]Pillar-3'!$L$5:$L$40),_xlfn.XLOOKUP(_xlpm.iso,'[3]Pillar-4'!$B$5:$B$40,'[3]Pillar-4'!$K$5:$K$40),_xlfn.XLOOKUP(_xlpm.iso,'[3]Pillar-4'!$B$5:$B$40,'[3]Pillar-4'!$L$5:$L$40),_xlfn.XLOOKUP(_xlpm.iso,'[3]Pillar-4'!$B$5:$B$40,'[3]Pillar-4'!$M$5:$M$40),_xlfn.XLOOKUP(_xlpm.iso,'[3]Pillar-4'!$B$5:$B$40,'[3]Pillar-4'!$N$5:$N$40),_xlfn.XLOOKUP(_xlpm.iso,'[3]Pillar-4'!$B$5:$B$40,'[3]Pillar-4'!$O$5:$O$40),_xlfn.XLOOKUP(_xlpm.iso,'[3]Pillar-5'!$B$5:$B$40,'[3]Pillar-5'!$I$5:$I$40),_xlfn.XLOOKUP(_xlpm.iso,'[3]Pillar-5'!$B$5:$B$40,'[3]Pillar-5'!$J$5:$J$40),_xlfn.XLOOKUP(_xlpm.iso,'[3]Pillar-5'!$B$5:$B$40,'[3]Pillar-5'!$K$5:$K$40),_xlfn.XLOOKUP(_xlpm.iso,'[3]Pillar-5'!$B$5:$B$40,'[3]Pillar-5'!$L$5:$L$40),_xlfn.XLOOKUP(_xlpm.iso,'[3]Pillar-6'!$B$5:$B$40,'[3]Pillar-6'!$I$5:$I$40),_xlfn.XLOOKUP(_xlpm.iso,'[3]Pillar-6'!$B$5:$B$40,'[3]Pillar-6'!$K$5:$K$40),_xlfn.XLOOKUP(_xlpm.iso,'[3]Pillar-6'!$B$5:$B$40,'[3]Pillar-6'!$L$5:$L$40)),SUMPRODUCT(_xlpm.s,$K$4:$K$31)),"") -> 48.844807 | J41: =IF(I41="","",_xlfn.RANK.EQ(I41,$I$36:$I$71,0)) -> 20 | K41: =IF(J41="","",D41-J41) -> 0
A42: Canada | B42: CAN | C42: =_xlfn.XLOOKUP($B42,[3]INDEX!$B$4:$B$39,[3]INDEX!$I$4:$I$39,"") -> 66.630184 | D42: =_xlfn.XLOOKUP($B42,[3]INDEX!$B$4:$B$39,[3]INDEX!$J$4:$J$39,"") -> 3 | E42: =IFERROR(_xlfn.LET(_xlpm.iso,$B42,_xlpm.s,_xlfn.VSTACK(_xlfn.XLOOKUP(_xlpm.iso,'[3]Pillar-1'!$B$5:$B$40,'[3]Pillar-1'!$J$5:$J$40),_xlfn.XLOOKUP(_xlpm.iso,'[3]Pillar-1'!$B$5:$B$40,'[3]Pillar-1'!$K$5:$K$40),_xlfn.XLOOKUP(_xlpm.iso,'[3]Pillar-1'!$B$5:$B$40,'[3]Pillar-1'!$L$5:$L$40),_xlfn.XLOOKUP(_xlpm.iso,'[3]Pillar-2'!$B$5:$B$40,'[3]Pillar-2'!$K$5:$K$40),_xlfn.XLOOKUP(_xlpm.iso,'[3]Pillar-2'!$B$5:$B$40,'[3]Pillar-2'!$L$5:$L$40),_xlfn.XLOOKUP(_xlpm.iso,'[3]Pillar-2'!$B$5:$B$40,'[3]Pillar-2'!$M$5:$M$40),_xlfn.XLOOKUP(_xlpm.iso,'[3]Pillar-2'!$B$5:$B$40,'[3]Pillar-2'!$N$5:$N$40),_xlfn.XLOOKUP(_xlpm.iso,'[3]Pillar-2'!$B$5:$B$40,'[3]Pillar-2'!$O$5:$O$40),_xlfn.XLOOKUP(_xlpm.iso,'[3]Pillar-2'!$B$5:$B$40,'[3]Pillar-2'!$P$5:$P$40),_xlfn.XLOOKUP(_xlpm.iso,'[3]Pillar-2'!$B$5:$B$40,'[3]Pillar-2'!$Q$5:$Q$40),_xlfn.XLOOKUP(_xlpm.iso,'[3]Pillar-2'!$B$5:$B$40,'[3]Pillar-2'!$R$5:$R$40),_xlfn.XLOOKUP(_xlpm.iso,'[3]Pillar-3'!$B$5:$B$40,'[3]Pillar-3'!$H$5:$H$40),_xlfn.XLOOKUP(_xlpm.iso,'[3]Pillar-3'!$B$5:$B$40,'[3]Pillar-3'!$I$5:$I$40),_xlfn.XLOOKUP(_xlpm.iso,'[3]Pillar-3'!$B$5:$B$40,'[3]Pillar-3'!$J$5:$J$40),_xlfn.XLOOKUP(_xlpm.iso,'[3]Pillar-3'!$B$5:$B$40,'[3]Pillar-3'!$K$5:$K$40),_xlfn.XLOOKUP(_xlpm.iso,'[3]Pillar-3'!$B$5:$B$40,'[3]Pillar-3'!$L$5:$L$40),_xlfn.XLOOKUP(_xlpm.iso,'[3]Pillar-4'!$B$5:$B$40,'[3]Pillar-4'!$K$5:$K$40),_xlfn.XLOOKUP(_xlpm.iso,'[3]Pillar-4'!$B$5:$B$40,'[3]Pillar-4'!$L$5:$L$40),_xlfn.XLOOKUP(_xlpm.iso,'[3]Pillar-4'!$B$5:$B$40,'[3]Pillar-4'!$M$5:$M$40),_xlfn.XLOOKUP(_xlpm.iso,'[3]Pillar-4'!$B$5:$B$40,'[3]Pillar-4'!$N$5:$N$40),_xlfn.XLOOKUP(_xlpm.iso,'[3]Pillar-4'!$B$5:$B$40,'[3]Pillar-4'!$O$5:$O$40),_xlfn.XLOOKUP(_xlpm.iso,'[3]Pillar-5'!$B$5:$B$40,'[3]Pillar-5'!$I$5:$I$40),_xlfn.XLOOKUP(_xlpm.iso,'[3]Pillar-5'!$B$5:$B$40,'[3]Pillar-5'!$J$5:$J$40),_xlfn.XLOOKUP(_xlpm.iso,'[3]Pillar-5'!$B$5:$B$40,'[3]Pillar-5'!$K$5:$K$40),_xlfn.XLOOKUP(_xlpm.iso,'[3]Pillar-5'!$B$5:$B$40,'[3]Pillar-5'!$L$5:$L$40),_xlfn.XLOOKUP(_xlpm.iso,'[3]Pillar-6'!$B$5:$B$40,'[3]Pillar-6'!$I$5:$I$40),_xlfn.XLOOKUP(_xlpm.iso,'[3]Pillar-6'!$B$5:$B$40,'[3]Pillar-6'!$K$5:$K$40),_xlfn.XLOOKUP(_xlpm.iso,'[3]Pillar-6'!$B$5:$B$40,'[3]Pillar-6'!$L$5:$L$40)),SUMPRODUCT(_xlpm.s,$I$4:$I$31)),"") -> 66.504604 | F42: =IF(E42="","",_xlfn.RANK.EQ(E42,$E$36:$E$71,0)) -> 3 | G42: =IF(E42="","",E42-C42) -> -0.12558098 | H42: =IF(F42="","",D42-F42) -> 0 | I42: =IFERROR(_xlfn.LET(_xlpm.iso,$B42,_xlpm.s,_xlfn.VSTACK(_xlfn.XLOOKUP(_xlpm.iso,'[3]Pillar-1'!$B$5:$B$40,'[3]Pillar-1'!$J$5:$J$40),_xlfn.XLOOKUP(_xlpm.iso,'[3]Pillar-1'!$B$5:$B$40,'[3]Pillar-1'!$K$5:$K$40),_xlfn.XLOOKUP(_xlpm.iso,'[3]Pillar-1'!$B$5:$B$40,'[3]Pillar-1'!$L$5:$L$40),_xlfn.XLOOKUP(_xlpm.iso,'[3]Pillar-2'!$B$5:$B$40,'[3]Pillar-2'!$K$5:$K$40),_xlfn.XLOOKUP(_xlpm.iso,'[3]Pillar-2'!$B$5:$B$40,'[3]Pillar-2'!$L$5:$L$40),_xlfn.XLOOKUP(_xlpm.iso,'[3]Pillar-2'!$B$5:$B$40,'[3]Pillar-2'!$M$5:$M$40),_xlfn.XLOOKUP(_xlpm.iso,'[3]Pillar-2'!$B$5:$B$40,'[3]Pillar-2'!$N$5:$N$40),_xlfn.XLOOKUP(_xlpm.iso,'[3]Pillar-2'!$B$5:$B$40,'[3]Pillar-2'!$O$5:$O$40),_xlfn.XLOOKUP(_xlpm.iso,'[3]Pillar-2'!$B$5:$B$40,'[3]Pillar-2'!$P$5:$P$40),_xlfn.XLOOKUP(_xlpm.iso,'[3]Pillar-2'!$B$5:$B$40,'[3]Pillar-2'!$Q$5:$Q$40),_xlfn.XLOOKUP(_xlpm.iso,'[3]Pillar-2'!$B$5:$B$40,'[3]Pillar-2'!$R$5:$R$40),_xlfn.XLOOKUP(_xlpm.iso,'[3]Pillar-3'!$B$5:$B$40,'[3]Pillar-3'!$H$5:$H$40),_xlfn.XLOOKUP(_xlpm.iso,'[3]Pillar-3'!$B$5:$B$40,'[3]Pillar-3'!$I$5:$I$40),_xlfn.XLOOKUP(_xlpm.iso,'[3]Pillar-3'!$B$5:$B$40,'[3]Pillar-3'!$J$5:$J$40),_xlfn.XLOOKUP(_xlpm.iso,'[3]Pillar-3'!$B$5:$B$40,'[3]Pillar-3'!$K$5:$K$40),_xlfn.XLOOKUP(_xlpm.iso,'[3]Pillar-3'!$B$5:$B$40,'[3]Pillar-3'!$L$5:$L$40),_xlfn.XLOOKUP(_xlpm.iso,'[3]Pillar-4'!$B$5:$B$40,'[3]Pillar-4'!$K$5:$K$40),_xlfn.XLOOKUP(_xlpm.iso,'[3]Pillar-4'!$B$5:$B$40,'[3]Pillar-4'!$L$5:$L$40),_xlfn.XLOOKUP(_xlpm.iso,'[3]Pillar-4'!$B$5:$B$40,'[3]Pillar-4'!$M$5:$M$40),_xlfn.XLOOKUP(_xlpm.iso,'[3]Pillar-4'!$B$5:$B$40,'[3]Pillar-4'!$N$5:$N$40),_xlfn.XLOOKUP(_xlpm.iso,'[3]Pillar-4'!$B$5:$B$40,'[3]Pillar-4'!$O$5:$O$40),_xlfn.XLOOKUP(_xlpm.iso,'[3]Pillar-5'!$B$5:$B$40,'[3]Pillar-5'!$I$5:$I$40),_xlfn.XLOOKUP(_xlpm.iso,'[3]Pillar-5'!$B$5:$B$40,'[3]Pillar-5'!$J$5:$J$40),_xlfn.XLOOKUP(_xlpm.iso,'[3]Pillar-5'!$B$5:$B$40,'[3]Pillar-5'!$K$5:$K$40),_xlfn.XLOOKUP(_xlpm.iso,'[3]Pillar-5'!$B$5:$B$40,'[3]Pillar-5'!$L$5:$L$40),_xlfn.XLOOKUP(_xlpm.iso,'[3]Pillar-6'!$B$5:$B$40,'[3]Pillar-6'!$I$5:$I$40),_xlfn.XLOOKUP(_xlpm.iso,'[3]Pillar-6'!$B$5:$B$40,'[3]Pillar-6'!$K$5:$K$40),_xlfn.XLOOKUP(_xlpm.iso,'[3]Pillar-6'!$B$5:$B$40,'[3]Pillar-6'!$L$5:$L$40)),SUMPRODUCT(_xlpm.s,$K$4:$K$31)),"") -> 66.664621 | J42: =IF(I42="","",_xlfn.RANK.EQ(I42,$I$36:$I$71,0)) -> 3 | K42: =IF(J42="","",D42-J42) -> 0
A43: Chile | B43: CHL | C43: =_xlfn.XLOOKUP($B43,[3]INDEX!$B$4:$B$39,[3]INDEX!$I$4:$I$39,"") -> 76.456821 | D43: =_xlfn.XLOOKUP($B43,[3]INDEX!$B$4:$B$39,[3]INDEX!$J$4:$J$39,"") -> 1 | E43: =IFERROR(_xlfn.LET(_xlpm.iso,$B43,_xlpm.s,_xlfn.VSTACK(_xlfn.XLOOKUP(_xlpm.iso,'[3]Pillar-1'!$B$5:$B$40,'[3]Pillar-1'!$J$5:$J$40),_xlfn.XLOOKUP(_xlpm.iso,'[3]Pillar-1'!$B$5:$B$40,'[3]Pillar-1'!$K$5:$K$40),_xlfn.XLOOKUP(_xlpm.iso,'[3]Pillar-1'!$B$5:$B$40,'[3]Pillar-1'!$L$5:$L$40),_xlfn.XLOOKUP(_xlpm.iso,'[3]Pillar-2'!$B$5:$B$40,'[3]Pillar-2'!$K$5:$K$40),_xlfn.XLOOKUP(_xlpm.iso,'[3]Pillar-2'!$B$5:$B$40,'[3]Pillar-2'!$L$5:$L$40),_xlfn.XLOOKUP(_xlpm.iso,'[3]Pillar-2'!$B$5:$B$40,'[3]Pillar-2'!$M$5:$M$40),_xlfn.XLOOKUP(_xlpm.iso,'[3]Pillar-2'!$B$5:$B$40,'[3]Pillar-2'!$N$5:$N$40),_xlfn.XLOOKUP(_xlpm.iso,'[3]Pillar-2'!$B$5:$B$40,'[3]Pillar-2'!$O$5:$O$40),_xlfn.XLOOKUP(_xlpm.iso,'[3]Pillar-2'!$B$5:$B$40,'[3]Pillar-2'!$P$5:$P$40),_xlfn.XLOOKUP(_xlpm.iso,'[3]Pillar-2'!$B$5:$B$40,'[3]Pillar-2'!$Q$5:$Q$40),_xlfn.XLOOKUP(_xlpm.iso,'[3]Pillar-2'!$B$5:$B$40,'[3]Pillar-2'!$R$5:$R$40),_xlfn.XLOOKUP(_xlpm.iso,'[3]Pillar-3'!$B$5:$B$40,'[3]Pillar-3'!$H$5:$H$40),_xlfn.XLOOKUP(_xlpm.iso,'[3]Pillar-3'!$B$5:$B$40,'[3]Pillar-3'!$I$5:$I$40),_xlfn.XLOOKUP(_xlpm.iso,'[3]Pillar-3'!$B$5:$B$40,'[3]Pillar-3'!$J$5:$J$40),_xlfn.XLOOKUP(_xlpm.iso,'[3]Pillar-3'!$B$5:$B$40,'[3]Pillar-3'!$K$5:$K$40),_xlfn.XLOOKUP(_xlpm.iso,'[3]Pillar-3'!$B$5:$B$40,'[3]Pillar-3'!$L$5:$L$40),_xlfn.XLOOKUP(_xlpm.iso,'[3]Pillar-4'!$B$5:$B$40,'[3]Pillar-4'!$K$5:$K$40),_xlfn.XLOOKUP(_xlpm.iso,'[3]Pillar-4'!$B$5:$B$40,'[3]Pillar-4'!$L$5:$L$40),_xlfn.XLOOKUP(_xlpm.iso,'[3]Pillar-4'!$B$5:$B$40,'[3]Pillar-4'!$M$5:$M$40),_xlfn.XLOOKUP(_xlpm.iso,'[3]Pillar-4'!$B$5:$B$40,'[3]Pillar-4'!$N$5:$N$40),_xlfn.XLOOKUP(_xlpm.iso,'[3]Pillar-4'!$B$5:$B$40,'[3]Pillar-4'!$O$5:$O$40),_xlfn.XLOOKUP(_xlpm.iso,'[3]Pillar-5'!$B$5:$B$40,'[3]Pillar-5'!$I$5:$I$40),_xlfn.XLOOKUP(_xlpm.iso,'[3]Pillar-5'!$B$5:$B$40,'[3]Pillar-5'!$J$5:$J$40),_xlfn.XLOOKUP(_xlpm.iso,'[3]Pillar-5'!$B$5:$B$40,'[3]Pillar-5'!$K$5:$K$40),_xlfn.XLOOKUP(_xlpm.iso,'[3]Pillar-5'!$B$5:$B$40,'[3]Pillar-5'!$L$5:$L$40),_xlfn.XLOOKUP(_xlpm.iso,'[3]Pillar-6'!$B$5:$B$40,'[3]Pillar-6'!$I$5:$I$40),_xlfn.XLOOKUP(_xlpm.iso,'[3]Pillar-6'!$B$5:$B$40,'[3]Pillar-6'!$K$5:$K$40),_xlfn.XLOOKUP(_xlpm.iso,'[3]Pillar-6'!$B$5:$B$40,'[3]Pillar-6'!$L$5:$L$40)),SUMPRODUCT(_xlpm.s,$I$4:$I$31)),"") -> 76.4003 | F43: =IF(E43="","",_xlfn.RANK.EQ(E43,$E$36:$E$71,0)) -> 1 | G43: =IF(E43="","",E43-C43) -> -0.056520609 | H43: =IF(F43="","",D43-F43) -> 0 | I43: =IFERROR(_xlfn.LET(_xlpm.iso,$B43,_xlpm.s,_xlfn.VSTACK(_xlfn.XLOOKUP(_xlpm.iso,'[3]Pillar-1'!$B$5:$B$40,'[3]Pillar-1'!$J$5:$J$40),_xlfn.XLOOKUP(_xlpm.iso,'[3]Pillar-1'!$B$5:$B$40,'[3]Pillar-1'!$K$5:$K$40),_xlfn.XLOOKUP(_xlpm.iso,'[3]Pillar-1'!$B$5:$B$40,'[3]Pillar-1'!$L$5:$L$40),_xlfn.XLOOKUP(_xlpm.iso,'[3]Pillar-2'!$B$5:$B$40,'[3]Pillar-2'!$K$5:$K$40),_xlfn.XLOOKUP(_xlpm.iso,'[3]Pillar-2'!$B$5:$B$40,'[3]Pillar-2'!$L$5:$L$40),_xlfn.XLOOKUP(_xlpm.iso,'[3]Pillar-2'!$B$5:$B$40,'[3]Pillar-2'!$M$5:$M$40),_xlfn.XLOOKUP(_xlpm.iso,'[3]Pillar-2'!$B$5:$B$40,'[3]Pillar-2'!$N$5:$N$40),_xlfn.XLOOKUP(_xlpm.iso,'[3]Pillar-2'!$B$5:$B$40,'[3]Pillar-2'!$O$5:$O$40),_xlfn.XLOOKUP(_xlpm.iso,'[3]Pillar-2'!$B$5:$B$40,'[3]Pillar-2'!$P$5:$P$40),_xlfn.XLOOKUP(_xlpm.iso,'[3]Pillar-2'!$B$5:$B$40,'[3]Pillar-2'!$Q$5:$Q$40),_xlfn.XLOOKUP(_xlpm.iso,'[3]Pillar-2'!$B$5:$B$40,'[3]Pillar-2'!$R$5:$R$40),_xlfn.XLOOKUP(_xlpm.iso,'[3]Pillar-3'!$B$5:$B$40,'[3]Pillar-3'!$H$5:$H$40),_xlfn.XLOOKUP(_xlpm.iso,'[3]Pillar-3'!$B$5:$B$40,'[3]Pillar-3'!$I$5:$I$40),_xlfn.XLOOKUP(_xlpm.iso,'[3]Pillar-3'!$B$5:$B$40,'[3]Pillar-3'!$J$5:$J$40),_xlfn.XLOOKUP(_xlpm.iso,'[3]Pillar-3'!$B$5:$B$40,'[3]Pillar-3'!$K$5:$K$40),_xlfn.XLOOKUP(_xlpm.iso,'[3]Pillar-3'!$B$5:$B$40,'[3]Pillar-3'!$L$5:$L$40),_xlfn.XLOOKUP(_xlpm.iso,'[3]Pillar-4'!$B$5:$B$40,'[3]Pillar-4'!$K$5:$K$40),_xlfn.XLOOKUP(_xlpm.iso,'[3]Pillar-4'!$B$5:$B$40,'[3]Pillar-4'!$L$5:$L$40),_xlfn.XLOOKUP(_xlpm.iso,'[3]Pillar-4'!$B$5:$B$40,'[3]Pillar-4'!$M$5:$M$40),_xlfn.XLOOKUP(_xlpm.iso,'[3]Pillar-4'!$B$5:$B$40,'[3]Pillar-4'!$N$5:$N$40),_xlfn.XLOOKUP(_xlpm.iso,'[3]Pillar-4'!$B$5:$B$40,'[3]Pillar-4'!$O$5:$O$40),_xlfn.XLOOKUP(_xlpm.iso,'[3]Pillar-5'!$B$5:$B$40,'[3]Pillar-5'!$I$5:$I$40),_xlfn.XLOOKUP(_xlpm.iso,'[3]Pillar-5'!$B$5:$B$40,'[3]Pillar-5'!$J$5:$J$40),_xlfn.XLOOKUP(_xlpm.iso,'[3]Pillar-5'!$B$5:$B$40,'[3]Pillar-5'!$K$5:$K$40),_xlfn.XLOOKUP(_xlpm.iso,'[3]Pillar-5'!$B$5:$B$40,'[3]Pillar-5'!$L$5:$L$40),_xlfn.XLOOKUP(_xlpm.iso,'[3]Pillar-6'!$B$5:$B$40,'[3]Pillar-6'!$I$5:$I$40),_xlfn.XLOOKUP(_xlpm.iso,'[3]Pillar-6'!$B$5:$B$40,'[3]Pillar-6'!$K$5:$K$40),_xlfn.XLOOKUP(_xlpm.iso,'[3]Pillar-6'!$B$5:$B$40,'[3]Pillar-6'!$L$5:$L$40)),SUMPRODUCT(_xlpm.s,$K$4:$K$31)),"") -> 76.685524 | J43: =IF(I43="","",_xlfn.RANK.EQ(I43,$I$36:$I$71,0)) -> 1 | K43: =IF(J43="","",D43-J43) -> 0
A44: China | B44: CHN | C44: =_xlfn.XLOOKUP($B44,[3]INDEX!$B$4:$B$39,[3]INDEX!$I$4:$I$39,"") -> 56.080555 | D44: =_xlfn.XLOOKUP($B44,[3]INDEX!$B$4:$B$39,[3]INDEX!$J$4:$J$39,"") -> 13 | E44: =IFERROR(_xlfn.LET(_xlpm.iso,$B44,_xlpm.s,_xlfn.VSTACK(_xlfn.XLOOKUP(_xlpm.iso,'[3]Pillar-1'!$B$5:$B$40,'[3]Pillar-1'!$J$5:$J$40),_xlfn.XLOOKUP(_xlpm.iso,'[3]Pillar-1'!$B$5:$B$40,'[3]Pillar-1'!$K$5:$K$40),_xlfn.XLOOKUP(_xlpm.iso,'[3]Pillar-1'!$B$5:$B$40,'[3]Pillar-1'!$L$5:$L$40),_xlfn.XLOOKUP(_xlpm.iso,'[3]Pillar-2'!$B$5:$B$40,'[3]Pillar-2'!$K$5:$K$40),_xlfn.XLOOKUP(_xlpm.iso,'[3]Pillar-2'!$B$5:$B$40,'[3]Pillar-2'!$L$5:$L$40),_xlfn.XLOOKUP(_xlpm.iso,'[3]Pillar-2'!$B$5:$B$40,'[3]Pillar-2'!$M$5:$M$40),_xlfn.XLOOKUP(_xlpm.iso,'[3]Pillar-2'!$B$5:$B$40,'[3]Pillar-2'!$N$5:$N$40),_xlfn.XLOOKUP(_xlpm.iso,'[3]Pillar-2'!$B$5:$B$40,'[3]Pillar-2'!$O$5:$O$40),_xlfn.XLOOKUP(_xlpm.iso,'[3]Pillar-2'!$B$5:$B$40,'[3]Pillar-2'!$P$5:$P$40),_xlfn.XLOOKUP(_xlpm.iso,'[3]Pillar-2'!$B$5:$B$40,'[3]Pillar-2'!$Q$5:$Q$40),_xlfn.XLOOKUP(_xlpm.iso,'[3]Pillar-2'!$B$5:$B$40,'[3]Pillar-2'!$R$5:$R$40),_xlfn.XLOOKUP(_xlpm.iso,'[3]Pillar-3'!$B$5:$B$40,'[3]Pillar-3'!$H$5:$H$40),_xlfn.XLOOKUP(_xlpm.iso,'[3]Pillar-3'!$B$5:$B$40,'[3]Pillar-3'!$I$5:$I$40),_xlfn.XLOOKUP(_xlpm.iso,'[3]Pillar-3'!$B$5:$B$40,'[3]Pillar-3'!$J$5:$J$40),_xlfn.XLOOKUP(_xlpm.iso,'[3]Pillar-3'!$B$5:$B$40,'[3]Pillar-3'!$K$5:$K$40),_xlfn.XLOOKUP(_xlpm.iso,'[3]Pillar-3'!$B$5:$B$40,'[3]Pillar-3'!$L$5:$L$40),_xlfn.XLOOKUP(_xlpm.iso,'[3]Pillar-4'!$B$5:$B$40,'[3]Pillar-4'!$K$5:$K$40),_xlfn.XLOOKUP(_xlpm.iso,'[3]Pillar-4'!$B$5:$B$40,'[3]Pillar-4'!$L$5:$L$40),_xlfn.XLOOKUP(_xlpm.iso,'[3]Pillar-4'!$B$5:$B$40,'[3]Pillar-4'!$M$5:$M$40),_xlfn.XLOOKUP(_xlpm.iso,'[3]Pillar-4'!$B$5:$B$40,'[3]Pillar-4'!$N$5:$N$40),_xlfn.XLOOKUP(_xlpm.iso,'[3]Pillar-4'!$B$5:$B$40,'[3]Pillar-4'!$O$5:$O$40),_xlfn.XLOOKUP(_xlpm.iso,'[3]Pillar-5'!$B$5:$B$40,'[3]Pillar-5'!$I$5:$I$40),_xlfn.XLOOKUP(_xlpm.iso,'[3]Pillar-5'!$B$5:$B$40,'[3]Pillar-5'!$J$5:$J$40),_xlfn.XLOOKUP(_xlpm.iso,'[3]Pillar-5'!$B$5:$B$40,'[3]Pillar-5'!$K$5:$K$40),_xlfn.XLOOKUP(_xlpm.iso,'[3]Pillar-5'!$B$5:$B$40,'[3]Pillar-5'!$L$5:$L$40),_xlfn.XLOOKUP(_xlpm.iso,'[3]Pillar-6'!$B$5:$B$40,'[3]Pillar-6'!$I$5:$I$40),_xlfn.XLOOKUP(_xlpm.iso,'[3]Pillar-6'!$B$5:$B$40,'[3]Pillar-6'!$K$5:$K$40),_xlfn.XLOOKUP(_xlpm.iso,'[3]Pillar-6'!$B$5:$B$40,'[3]Pillar-6'!$L$5:$L$40)),SUMPRODUCT(_xlpm.s,$I$4:$I$31)),"") -> 55.749368 | F44: =IF(E44="","",_xlfn.RANK.EQ(E44,$E$36:$E$71,0)) -> 13 | G44: =IF(E44="","",E44-C44) -> -0.33118702 | H44: =IF(F44="","",D44-F44) -> 0 | I44: =IFERROR(_xlfn.LET(_xlpm.iso,$B44,_xlpm.s,_xlfn.VSTACK(_xlfn.XLOOKUP(_xlpm.iso,'[3]Pillar-1'!$B$5:$B$40,'[3]Pillar-1'!$J$5:$J$40),_xlfn.XLOOKUP(_xlpm.iso,'[3]Pillar-1'!$B$5:$B$40,'[3]Pillar-1'!$K$5:$K$40),_xlfn.XLOOKUP(_xlpm.iso,'[3]Pillar-1'!$B$5:$B$40,'[3]Pillar-1'!$L$5:$L$40),_xlfn.XLOOKUP(_xlpm.iso,'[3]Pillar-2'!$B$5:$B$40,'[3]Pillar-2'!$K$5:$K$40),_xlfn.XLOOKUP(_xlpm.iso,'[3]Pillar-2'!$B$5:$B$40,'[3]Pillar-2'!$L$5:$L$40),_xlfn.XLOOKUP(_xlpm.iso,'[3]Pillar-2'!$B$5:$B$40,'[3]Pillar-2'!$M$5:$M$40),_xlfn.XLOOKUP(_xlpm.iso,'[3]Pillar-2'!$B$5:$B$40,'[3]Pillar-2'!$N$5:$N$40),_xlfn.XLOOKUP(_xlpm.iso,'[3]Pillar-2'!$B$5:$B$40,'[3]Pillar-2'!$O$5:$O$40),_xlfn.XLOOKUP(_xlpm.iso,'[3]Pillar-2'!$B$5:$B$40,'[3]Pillar-2'!$P$5:$P$40),_xlfn.XLOOKUP(_xlpm.iso,'[3]Pillar-2'!$B$5:$B$40,'[3]Pillar-2'!$Q$5:$Q$40),_xlfn.XLOOKUP(_xlpm.iso,'[3]Pillar-2'!$B$5:$B$40,'[3]Pillar-2'!$R$5:$R$40),_xlfn.XLOOKUP(_xlpm.iso,'[3]Pillar-3'!$B$5:$B$40,'[3]Pillar-3'!$H$5:$H$40),_xlfn.XLOOKUP(_xlpm.iso,'[3]Pillar-3'!$B$5:$B$40,'[3]Pillar-3'!$I$5:$I$40),_xlfn.XLOOKUP(_xlpm.iso,'[3]Pillar-3'!$B$5:$B$40,'[3]Pillar-3'!$J$5:$J$40),_xlfn.XLOOKUP(_xlpm.iso,'[3]Pillar-3'!$B$5:$B$40,'[3]Pillar-3'!$K$5:$K$40),_xlfn.XLOOKUP(_xlpm.iso,'[3]Pillar-3'!$B$5:$B$40,'[3]Pillar-3'!$L$5:$L$40),_xlfn.XLOOKUP(_xlpm.iso,'[3]Pillar-4'!$B$5:$B$40,'[3]Pillar-4'!$K$5:$K$40),_xlfn.XLOOKUP(_xlpm.iso,'[3]Pillar-4'!$B$5:$B$40,'[3]Pillar-4'!$L$5:$L$40),_xlfn.XLOOKUP(_xlpm.iso,'[3]Pillar-4'!$B$5:$B$40,'[3]Pillar-4'!$M$5:$M$40),_xlfn.XLOOKUP(_xlpm.iso,'[3]Pillar-4'!$B$5:$B$40,'[3]Pillar-4'!$N$5:$N$40),_xlfn.XLOOKUP(_xlpm.iso,'[3]Pillar-4'!$B$5:$B$40,'[3]Pillar-4'!$O$5:$O$40),_xlfn.XLOOKUP(_xlpm.iso,'[3]Pillar-5'!$B$5:$B$40,'[3]Pillar-5'!$I$5:$I$40),_xlfn.XLOOKUP(_xlpm.iso,'[3]Pillar-5'!$B$5:$B$40,'[3]Pillar-5'!$J$5:$J$40),_xlfn.XLOOKUP(_xlpm.iso,'[3]Pillar-5'!$B$5:$B$40,'[3]Pillar-5'!$K$5:$K$40),_xlfn.XLOOKUP(_xlpm.iso,'[3]Pillar-5'!$B$5:$B$40,'[3]Pillar-5'!$L$5:$L$40),_xlfn.XLOOKUP(_xlpm.iso,'[3]Pillar-6'!$B$5:$B$40,'[3]Pillar-6'!$I$5:$I$40),_xlfn.XLOOKUP(_xlpm.iso,'[3]Pillar-6'!$B$5:$B$40,'[3]Pillar-6'!$K$5:$K$40),_xlfn.XLOOKUP(_xlpm.iso,'[3]Pillar-6'!$B$5:$B$40,'[3]Pillar-6'!$L$5:$L$40)),SUMPRODUCT(_xlpm.s,$K$4:$K$31)),"") -> 55.570232 | J44: =IF(I44="","",_xlfn.RANK.EQ(I44,$I$36:$I$71,0)) -> 13 | K44: =IF(J44="","",D44-J44) -> 0
A45: Czech Republic | B45: CZE | C45: =_xlfn.XLOOKUP($B45,[3]INDEX!$B$4:$B$39,[3]INDEX!$I$4:$I$39,"") -> 51.304522 | D45: =_xlfn.XLOOKUP($B45,[3]INDEX!$B$4:$B$39,[3]INDEX!$J$4:$J$39,"") -> 19 | E45: =IFERROR(_xlfn.LET(_xlpm.iso,$B45,_xlpm.s,_xlfn.VSTACK(_xlfn.XLOOKUP(_xlpm.iso,'[3]Pillar-1'!$B$5:$B$40,'[3]Pillar-1'!$J$5:$J$40),_xlfn.XLOOKUP(_xlpm.iso,'[3]Pillar-1'!$B$5:$B$40,'[3]Pillar-1'!$K$5:$K$40),_xlfn.XLOOKUP(_xlpm.iso,'[3]Pillar-1'!$B$5:$B$40,'[3]Pillar-1'!$L$5:$L$40),_xlfn.XLOOKUP(_xlpm.iso,'[3]Pillar-2'!$B$5:$B$40,'[3]Pillar-2'!$K$5:$K$40),_xlfn.XLOOKUP(_xlpm.iso,'[3]Pillar-2'!$B$5:$B$40,'[3]Pillar-2'!$L$5:$L$40),_xlfn.XLOOKUP(_xlpm.iso,'[3]Pillar-2'!$B$5:$B$40,'[3]Pillar-2'!$M$5:$M$40),_xlfn.XLOOKUP(_xlpm.iso,'[3]Pillar-2'!$B$5:$B$40,'[3]Pillar-2'!$N$5:$N$40),_xlfn.XLOOKUP(_xlpm.iso,'[3]Pillar-2'!$B$5:$B$40,'[3]Pillar-2'!$O$5:$O$40),_xlfn.XLOOKUP(_xlpm.iso,'[3]Pillar-2'!$B$5:$B$40,'[3]Pillar-2'!$P$5:$P$40),_xlfn.XLOOKUP(_xlpm.iso,'[3]Pillar-2'!$B$5:$B$40,'[3]Pillar-2'!$Q$5:$Q$40),_xlfn.XLOOKUP(_xlpm.iso,'[3]Pillar-2'!$B$5:$B$40,'[3]Pillar-2'!$R$5:$R$40),_xlfn.XLOOKUP(_xlpm.iso,'[3]Pillar-3'!$B$5:$B$40,'[3]Pillar-3'!$H$5:$H$40),_xlfn.XLOOKUP(_xlpm.iso,'[3]Pillar-3'!$B$5:$B$40,'[3]Pillar-3'!$I$5:$I$40),_xlfn.XLOOKUP(_xlpm.iso,'[3]Pillar-3'!$B$5:$B$40,'[3]Pillar-3'!$J$5:$J$40),_xlfn.XLOOKUP(_xlpm.iso,'[3]Pillar-3'!$B$5:$B$40,'[3]Pillar-3'!$K$5:$K$40),_xlfn.XLOOKUP(_xlpm.iso,'[3]Pillar-3'!$B$5:$B$40,'[3]Pillar-3'!$L$5:$L$40),_xlfn.XLOOKUP(_xlpm.iso,'[3]Pillar-4'!$B$5:$B$40,'[3]Pillar-4'!$K$5:$K$40),_xlfn.XLOOKUP(_xlpm.iso,'[3]Pillar-4'!$B$5:$B$40,'[3]Pillar-4'!$L$5:$L$40),_xlfn.XLOOKUP(_xlpm.iso,'[3]Pillar-4'!$B$5:$B$40,'[3]Pillar-4'!$M$5:$M$40),_xlfn.XLOOKUP(_xlpm.iso,'[3]Pillar-4'!$B$5:$B$40,'[3]Pillar-4'!$N$5:$N$40),_xlfn.XLOOKUP(_xlpm.iso,'[3]Pillar-4'!$B$5:$B$40,'[3]Pillar-4'!$O$5:$O$40),_xlfn.XLOOKUP(_xlpm.iso,'[3]Pillar-5'!$B$5:$B$40,'[3]Pillar-5'!$I$5:$I$40),_xlfn.XLOOKUP(_xlpm.iso,'[3]Pillar-5'!$B$5:$B$40,'[3]Pillar-5'!$J$5:$J$40),_xlfn.XLOOKUP(_xlpm.iso,'[3]Pillar-5'!$B$5:$B$40,'[3]Pillar-5'!$K$5:$K$40),_xlfn.XLOOKUP(_xlpm.iso,'[3]Pillar-5'!$B$5:$B$40,'[3]Pillar-5'!$L$5:$L$40),_xlfn.XLOOKUP(_xlpm.iso,'[3]Pillar-6'!$B$5:$B$40,'[3]Pillar-6'!$I$5:$I$40),_xlfn.XLOOKUP(_xlpm.iso,'[3]Pillar-6'!$B$5:$B$40,'[3]Pillar-6'!$K$5:$K$40),_xlfn.XLOOKUP(_xlpm.iso,'[3]Pillar-6'!$B$5:$B$40,'[3]Pillar-6'!$L$5:$L$40)),SUMPRODUCT(_xlpm.s,$I$4:$I$31)),"") -> 51.472191 | F45: =IF(E45="","",_xlfn.RANK.EQ(E45,$E$36:$E$71,0)) -> 18 | G45: =IF(E45="","",E45-C45) -> 0.16766926 | H45: =IF(F45="","",D45-F45) -> 1 | I45: =IFERROR(_xlfn.LET(_xlpm.iso,$B45,_xlpm.s,_xlfn.VSTACK(_xlfn.XLOOKUP(_xlpm.iso,'[3]Pillar-1'!$B$5:$B$40,'[3]Pillar-1'!$J$5:$J$40),_xlfn.XLOOKUP(_xlpm.iso,'[3]Pillar-1'!$B$5:$B$40,'[3]Pillar-1'!$K$5:$K$40),_xlfn.XLOOKUP(_xlpm.iso,'[3]Pillar-1'!$B$5:$B$40,'[3]Pillar-1'!$L$5:$L$40),_xlfn.XLOOKUP(_xlpm.iso,'[3]Pillar-2'!$B$5:$B$40,'[3]Pillar-2'!$K$5:$K$40),_xlfn.XLOOKUP(_xlpm.iso,'[3]Pillar-2'!$B$5:$B$40,'[3]Pillar-2'!$L$5:$L$40),_xlfn.XLOOKUP(_xlpm.iso,'[3]Pillar-2'!$B$5:$B$40,'[3]Pillar-2'!$M$5:$M$40),_xlfn.XLOOKUP(_xlpm.iso,'[3]Pillar-2'!$B$5:$B$40,'[3]Pillar-2'!$N$5:$N$40),_xlfn.XLOOKUP(_xlpm.iso,'[3]Pillar-2'!$B$5:$B$40,'[3]Pillar-2'!$O$5:$O$40),_xlfn.XLOOKUP(_xlpm.iso,'[3]Pillar-2'!$B$5:$B$40,'[3]Pillar-2'!$P$5:$P$40),_xlfn.XLOOKUP(_xlpm.iso,'[3]Pillar-2'!$B$5:$B$40,'[3]Pillar-2'!$Q$5:$Q$40),_xlfn.XLOOKUP(_xlpm.iso,'[3]Pillar-2'!$B$5:$B$40,'[3]Pillar-2'!$R$5:$R$40),_xlfn.XLOOKUP(_xlpm.iso,'[3]Pillar-3'!$B$5:$B$40,'[3]Pillar-3'!$H$5:$H$40),_xlfn.XLOOKUP(_xlpm.iso,'[3]Pillar-3'!$B$5:$B$40,'[3]Pillar-3'!$I$5:$I$40),_xlfn.XLOOKUP(_xlpm.iso,'[3]Pillar-3'!$B$5:$B$40,'[3]Pillar-3'!$J$5:$J$40),_xlfn.XLOOKUP(_xlpm.iso,'[3]Pillar-3'!$B$5:$B$40,'[3]Pillar-3'!$K$5:$K$40),_xlfn.XLOOKUP(_xlpm.iso,'[3]Pillar-3'!$B$5:$B$40,'[3]Pillar-3'!$L$5:$L$40),_xlfn.XLOOKUP(_xlpm.iso,'[3]Pillar-4'!$B$5:$B$40,'[3]Pillar-4'!$K$5:$K$40),_xlfn.XLOOKUP(_xlpm.iso,'[3]Pillar-4'!$B$5:$B$40,'[3]Pillar-4'!$L$5:$L$40),_xlfn.XLOOKUP(_xlpm.iso,'[3]Pillar-4'!$B$5:$B$40,'[3]Pillar-4'!$M$5:$M$40),_xlfn.XLOOKUP(_xlpm.iso,'[3]Pillar-4'!$B$5:$B$40,'[3]Pillar-4'!$N$5:$N$40),_xlfn.XLOOKUP(_xlpm.iso,'[3]Pillar-4'!$B$5:$B$40,'[3]Pillar-4'!$O$5:$O$40),_xlfn.XLOOKUP(_xlpm.iso,'[3]Pillar-5'!$B$5:$B$40,'[3]Pillar-5'!$I$5:$I$40),_xlfn.XLOOKUP(_xlpm.iso,'[3]Pillar-5'!$B$5:$B$40,'[3]Pillar-5'!$J$5:$J$40),_xlfn.XLOOKUP(_xlpm.iso,'[3]Pillar-5'!$B$5:$B$40,'[3]Pillar-5'!$K$5:$K$40),_xlfn.XLOOKUP(_xlpm.iso,'[3]Pillar-5'!$B$5:$B$40,'[3]Pillar-5'!$L$5:$L$40),_xlfn.XLOOKUP(_xlpm.iso,'[3]Pillar-6'!$B$5:$B$40,'[3]Pillar-6'!$I$5:$I$40),_xlfn.XLOOKUP(_xlpm.iso,'[3]Pillar-6'!$B$5:$B$40,'[3]Pillar-6'!$K$5:$K$40),_xlfn.XLOOKUP(_xlpm.iso,'[3]Pillar-6'!$B$5:$B$40,'[3]Pillar-6'!$L$5:$L$40)),SUMPRODUCT(_xlpm.s,$K$4:$K$31)),"") -> 51.61816 | J45: =IF(I45="","",_xlfn.RANK.EQ(I45,$I$36:$I$71,0)) -> 18 | K45: =IF(J45="","",D45-J45) -> 1
A46: Dominican Republic | B46: DOM | C46: =_xlfn.XLOOKUP($B46,[3]INDEX!$B$4:$B$39,[3]INDEX!$I$4:$I$39,"") -> 43.719635 | D46: =_xlfn.XLOOKUP($B46,[3]INDEX!$B$4:$B$39,[3]INDEX!$J$4:$J$39,"") -> 27 | E46: =IFERROR(_xlfn.LET(_xlpm.iso,$B46,_xlpm.s,_xlfn.VSTACK(_xlfn.XLOOKUP(_xlpm.iso,'[3]Pillar-1'!$B$5:$B$40,'[3]Pillar-1'!$J$5:$J$40),_xlfn.XLOOKUP(_xlpm.iso,'[3]Pillar-1'!$B$5:$B$40,'[3]Pillar-1'!$K$5:$K$40),_xlfn.XLOOKUP(_xlpm.iso,'[3]Pillar-1'!$B$5:$B$40,'[3]Pillar-1'!$L$5:$L$40),_xlfn.XLOOKUP(_xlpm.iso,'[3]Pillar-2'!$B$5:$B$40,'[3]Pillar-2'!$K$5:$K$40),_xlfn.XLOOKUP(_xlpm.iso,'[3]Pillar-2'!$B$5:$B$40,'[3]Pillar-2'!$L$5:$L$40),_xlfn.XLOOKUP(_xlpm.iso,'[3]Pillar-2'!$B$5:$B$40,'[3]Pillar-2'!$M$5:$M$40),_xlfn.XLOOKUP(_xlpm.iso,'[3]Pillar-2'!$B$5:$B$40,'[3]Pillar-2'!$N$5:$N$40),_xlfn.XLOOKUP(_xlpm.iso,'[3]Pillar-2'!$B$5:$B$40,'[3]Pillar-2'!$O$5:$O$40),_xlfn.XLOOKUP(_xlpm.iso,'[3]Pillar-2'!$B$5:$B$40,'[3]Pillar-2'!$P$5:$P$40),_xlfn.XLOOKUP(_xlpm.iso,'[3]Pillar-2'!$B$5:$B$40,'[3]Pillar-2'!$Q$5:$Q$40),_xlfn.XLOOKUP(_xlpm.iso,'[3]Pillar-2'!$B$5:$B$40,'[3]Pillar-2'!$R$5:$R$40),_xlfn.XLOOKUP(_xlpm.iso,'[3]Pillar-3'!$B$5:$B$40,'[3]Pillar-3'!$H$5:$H$40),_xlfn.XLOOKUP(_xlpm.iso,'[3]Pillar-3'!$B$5:$B$40,'[3]Pillar-3'!$I$5:$I$40),_xlfn.XLOOKUP(_xlpm.iso,'[3]Pillar-3'!$B$5:$B$40,'[3]Pillar-3'!$J$5:$J$40),_xlfn.XLOOKUP(_xlpm.iso,'[3]Pillar-3'!$B$5:$B$40,'[3]Pillar-3'!$K$5:$K$40),_xlfn.XLOOKUP(_xlpm.iso,'[3]Pillar-3'!$B$5:$B$40,'[3]Pillar-3'!$L$5:$L$40),_xlfn.XLOOKUP(_xlpm.iso,'[3]Pillar-4'!$B$5:$B$40,'[3]Pillar-4'!$K$5:$K$40),_xlfn.XLOOKUP(_xlpm.iso,'[3]Pillar-4'!$B$5:$B$40,'[3]Pillar-4'!$L$5:$L$40),_xlfn.XLOOKUP(_xlpm.iso,'[3]Pillar-4'!$B$5:$B$40,'[3]Pillar-4'!$M$5:$M$40),_xlfn.XLOOKUP(_xlpm.iso,'[3]Pillar-4'!$B$5:$B$40,'[3]Pillar-4'!$N$5:$N$40),_xlfn.XLOOKUP(_xlpm.iso,'[3]Pillar-4'!$B$5:$B$40,'[3]Pillar-4'!$O$5:$O$40),_xlfn.XLOOKUP(_xlpm.iso,'[3]Pillar-5'!$B$5:$B$40,'[3]Pillar-5'!$I$5:$I$40),_xlfn.XLOOKUP(_xlpm.iso,'[3]Pillar-5'!$B$5:$B$40,'[3]Pillar-5'!$J$5:$J$40),_xlfn.XLOOKUP(_xlpm.iso,'[3]Pillar-5'!$B$5:$B$40,'[3]Pillar-5'!$K$5:$K$40),_xlfn.XLOOKUP(_xlpm.iso,'[3]Pillar-5'!$B$5:$B$40,'[3]Pillar-5'!$L$5:$L$40),_xlfn.XLOOKUP(_xlpm.iso,'[3]Pillar-6'!$B$5:$B$40,'[3]Pillar-6'!$I$5:$I$40),_xlfn.XLOOKUP(_xlpm.iso,'[3]Pillar-6'!$B$5:$B$40,'[3]Pillar-6'!$K$5:$K$40),_xlfn.XLOOKUP(_xlpm.iso,'[3]Pillar-6'!$B$5:$B$40,'[3]Pillar-6'!$L$5:$L$40)),SUMPRODUCT(_xlpm.s,$I$4:$I$31)),"") -> 43.622288 | F46: =IF(E46="","",_xlfn.RANK.EQ(E46,$E$36:$E$71,0)) -> 27 | G46: =IF(E46="","",E46-C46) -> -0.097346845 | H46: =IF(F46="","",D46-F46) -> 0 | I46: =IFERROR(_xlfn.LET(_xlpm.iso,$B46,_xlpm.s,_xlfn.VSTACK(_xlfn.XLOOKUP(_xlpm.iso,'[3]Pillar-1'!$B$5:$B$40,'[3]Pillar-1'!$J$5:$J$40),_xlfn.XLOOKUP(_xlpm.iso,'[3]Pillar-1'!$B$5:$B$40,'[3]Pillar-1'!$K$5:$K$40),_xlfn.XLOOKUP(_xlpm.iso,'[3]Pillar-1'!$B$5:$B$40,'[3]Pillar-1'!$L$5:$L$40),_xlfn.XLOOKUP(_xlpm.iso,'[3]Pillar-2'!$B$5:$B$40,'[3]Pillar-2'!$K$5:$K$40),_xlfn.XLOOKUP(_xlpm.iso,'[3]Pillar-2'!$B$5:$B$40,'[3]Pillar-2'!$L$5:$L$40),_xlfn.XLOOKUP(_xlpm.iso,'[3]Pillar-2'!$B$5:$B$40,'[3]Pillar-2'!$M$5:$M$40),_xlfn.XLOOKUP(_xlpm.iso,'[3]Pillar-2'!$B$5:$B$40,'[3]Pillar-2'!$N$5:$N$40),_xlfn.XLOOKUP(_xlpm.iso,'[3]Pillar-2'!$B$5:$B$40,'[3]Pillar-2'!$O$5:$O$40),_xlfn.XLOOKUP(_xlpm.iso,'[3]Pillar-2'!$B$5:$B$40,'[3]Pillar-2'!$P$5:$P$40),_xlfn.XLOOKUP(_xlpm.iso,'[3]Pillar-2'!$B$5:$B$40,'[3]Pillar-2'!$Q$5:$Q$40),_xlfn.XLOOKUP(_xlpm.iso,'[3]Pillar-2'!$B$5:$B$40,'[3]Pillar-2'!$R$5:$R$40),_xlfn.XLOOKUP(_xlpm.iso,'[3]Pillar-3'!$B$5:$B$40,'[3]Pillar-3'!$H$5:$H$40),_xlfn.XLOOKUP(_xlpm.iso,'[3]Pillar-3'!$B$5:$B$40,'[3]Pillar-3'!$I$5:$I$40),_xlfn.XLOOKUP(_xlpm.iso,'[3]Pillar-3'!$B$5:$B$40,'[3]Pillar-3'!$J$5:$J$40),_xlfn.XLOOKUP(_xlpm.iso,'[3]Pillar-3'!$B$5:$B$40,'[3]Pillar-3'!$K$5:$K$40),_xlfn.XLOOKUP(_xlpm.iso,'[3]Pillar-3'!$B$5:$B$40,'[3]Pillar-3'!$L$5:$L$40),_xlfn.XLOOKUP(_xlpm.iso,'[3]Pillar-4'!$B$5:$B$40,'[3]Pillar-4'!$K$5:$K$40),_xlfn.XLOOKUP(_xlpm.iso,'[3]Pillar-4'!$B$5:$B$40,'[3]Pillar-4'!$L$5:$L$40),_xlfn.XLOOKUP(_xlpm.iso,'[3]Pillar-4'!$B$5:$B$40,'[3]Pillar-4'!$M$5:$M$40),_xlfn.XLOOKUP(_xlpm.iso,'[3]Pillar-4'!$B$5:$B$40,'[3]Pillar-4'!$N$5:$N$40),_xlfn.XLOOKUP(_xlpm.iso,'[3]Pillar-4'!$B$5:$B$40,'[3]Pillar-4'!$O$5:$O$40),_xlfn.XLOOKUP(_xlpm.iso,'[3]Pillar-5'!$B$5:$B$40,'[3]Pillar-5'!$I$5:$I$40),_xlfn.XLOOKUP(_xlpm.iso,'[3]Pillar-5'!$B$5:$B$40,'[3]Pillar-5'!$J$5:$J$40),_xlfn.XLOOKUP(_xlpm.iso,'[3]Pillar-5'!$B$5:$B$40,'[3]Pillar-5'!$K$5:$K$40),_xlfn.XLOOKUP(_xlpm.iso,'[3]Pillar-5'!$B$5:$B$40,'[3]Pillar-5'!$L$5:$L$40),_xlfn.XLOOKUP(_xlpm.iso,'[3]Pillar-6'!$B$5:$B$40,'[3]Pillar-6'!$I$5:$I$40),_xlfn.XLOOKUP(_xlpm.iso,'[3]Pillar-6'!$B$5:$B$40,'[3]Pillar-6'!$K$5:$K$40),_xlfn.XLOOKUP(_xlpm.iso,'[3]Pillar-6'!$B$5:$B$40,'[3]Pillar-6'!$L$5:$L$40)),SUMPRODUCT(_xlpm.s,$K$4:$K$31)),"") -> 43.649824 | J46: =IF(I46="","",_xlfn.RANK.EQ(I46,$I$36:$I$71,0)) -> 27 | K46: =IF(J46="","",D46-J46) -> 0
A47: Germany | B47: DEU | C47: =_xlfn.XLOOKUP($B47,[3]INDEX!$B$4:$B$39,[3]INDEX!$I$4:$I$39,"") -> 75.33112 | D47: =_xlfn.XLOOKUP($B47,[3]INDEX!$B$4:$B$39,[3]INDEX!$J$4:$J$39,"") -> 2 | E47: =IFERROR(_xlfn.LET(_xlpm.iso,$B47,_xlpm.s,_xlfn.VSTACK(_xlfn.XLOOKUP(_xlpm.iso,'[3]Pillar-1'!$B$5:$B$40,'[3]Pillar-1'!$J$5:$J$40),_xlfn.XLOOKUP(_xlpm.iso,'[3]Pillar-1'!$B$5:$B$40,'[3]Pillar-1'!$K$5:$K$40),_xlfn.XLOOKUP(_xlpm.iso,'[3]Pillar-1'!$B$5:$B$40,'[3]Pillar-1'!$L$5:$L$40),_xlfn.XLOOKUP(_xlpm.iso,'[3]Pillar-2'!$B$5:$B$40,'[3]Pillar-2'!$K$5:$K$40),_xlfn.XLOOKUP(_xlpm.iso,'[3]Pillar-2'!$B$5:$B$40,'[3]Pillar-2'!$L$5:$L$40),_xlfn.XLOOKUP(_xlpm.iso,'[3]Pillar-2'!$B$5:$B$40,'[3]Pillar-2'!$M$5:$M$40),_xlfn.XLOOKUP(_xlpm.iso,'[3]Pillar-2'!$B$5:$B$40,'[3]Pillar-2'!$N$5:$N$40),_xlfn.XLOOKUP(_xlpm.iso,'[3]Pillar-2'!$B$5:$B$40,'[3]Pillar-2'!$O$5:$O$40),_xlfn.XLOOKUP(_xlpm.iso,'[3]Pillar-2'!$B$5:$B$40,'[3]Pillar-2'!$P$5:$P$40),_xlfn.XLOOKUP(_xlpm.iso,'[3]Pillar-2'!$B$5:$B$40,'[3]Pillar-2'!$Q$5:$Q$40),_xlfn.XLOOKUP(_xlpm.iso,'[3]Pillar-2'!$B$5:$B$40,'[3]Pillar-2'!$R$5:$R$40),_xlfn.XLOOKUP(_xlpm.iso,'[3]Pillar-3'!$B$5:$B$40,'[3]Pillar-3'!$H$5:$H$40),_xlfn.XLOOKUP(_xlpm.iso,'[3]Pillar-3'!$B$5:$B$40,'[3]Pillar-3'!$I$5:$I$40),_xlfn.XLOOKUP(_xlpm.iso,'[3]Pillar-3'!$B$5:$B$40,'[3]Pillar-3'!$J$5:$J$40),_xlfn.XLOOKUP(_xlpm.iso,'[3]Pillar-3'!$B$5:$B$40,'[3]Pillar-3'!$K$5:$K$40),_xlfn.XLOOKUP(_xlpm.iso,'[3]Pillar-3'!$B$5:$B$40,'[3]Pillar-3'!$L$5:$L$40),_xlfn.XLOOKUP(_xlpm.iso,'[3]Pillar-4'!$B$5:$B$40,'[3]Pillar-4'!$K$5:$K$40),_xlfn.XLOOKUP(_xlpm.iso,'[3]Pillar-4'!$B$5:$B$40,'[3]Pillar-4'!$L$5:$L$40),_xlfn.XLOOKUP(_xlpm.iso,'[3]Pillar-4'!$B$5:$B$40,'[3]Pillar-4'!$M$5:$M$40),_xlfn.XLOOKUP(_xlpm.iso,'[3]Pillar-4'!$B$5:$B$40,'[3]Pillar-4'!$N$5:$N$40),_xlfn.XLOOKUP(_xlpm.iso,'[3]Pillar-4'!$B$5:$B$40,'[3]Pillar-4'!$O$5:$O$40),_xlfn.XLOOKUP(_xlpm.iso,'[3]Pillar-5'!$B$5:$B$40,'[3]Pillar-5'!$I$5:$I$40),_xlfn.XLOOKUP(_xlpm.iso,'[3]Pillar-5'!$B$5:$B$40,'[3]Pillar-5'!$J$5:$J$40),_xlfn.XLOOKUP(_xlpm.iso,'[3]Pillar-5'!$B$5:$B$40,'[3]Pillar-5'!$K$5:$K$40),_xlfn.XLOOKUP(_xlpm.iso,'[3]Pillar-5'!$B$5:$B$40,'[3]Pillar-5'!$L$5:$L$40),_xlfn.XLOOKUP(_xlpm.iso,'[3]Pillar-6'!$B$5:$B$40,'[3]Pillar-6'!$I$5:$I$40),_xlfn.XLOOKUP(_xlpm.iso,'[3]Pillar-6'!$B$5:$B$40,'[3]Pillar-6'!$K$5:$K$40),_xlfn.XLOOKUP(_xlpm.iso,'[3]Pillar-6'!$B$5:$B$40,'[3]Pillar-6'!$L$5:$L$40)),SUMPRODUCT(_xlpm.s,$I$4:$I$31)),"") -> 75.099739 | F47: =IF(E47="","",_xlfn.RANK.EQ(E47,$E$36:$E$71,0)) -> 2 | G47: =IF(E47="","",E47-C47) -> -0.23138149 | H47: =IF(F47="","",D47-F47) -> 0 | I47: =IFERROR(_xlfn.LET(_xlpm.iso,$B47,_xlpm.s,_xlfn.VSTACK(_xlfn.XLOOKUP(_xlpm.iso,'[3]Pillar-1'!$B$5:$B$40,'[3]Pillar-1'!$J$5:$J$40),_xlfn.XLOOKUP(_xlpm.iso,'[3]Pillar-1'!$B$5:$B$40,'[3]Pillar-1'!$K$5:$K$40),_xlfn.XLOOKUP(_xlpm.iso,'[3]Pillar-1'!$B$5:$B$40,'[3]Pillar-1'!$L$5:$L$40),_xlfn.XLOOKUP(_xlpm.iso,'[3]Pillar-2'!$B$5:$B$40,'[3]Pillar-2'!$K$5:$K$40),_xlfn.XLOOKUP(_xlpm.iso,'[3]Pillar-2'!$B$5:$B$40,'[3]Pillar-2'!$L$5:$L$40),_xlfn.XLOOKUP(_xlpm.iso,'[3]Pillar-2'!$B$5:$B$40,'[3]Pillar-2'!$M$5:$M$40),_xlfn.XLOOKUP(_xlpm.iso,'[3]Pillar-2'!$B$5:$B$40,'[3]Pillar-2'!$N$5:$N$40),_xlfn.XLOOKUP(_xlpm.iso,'[3]Pillar-2'!$B$5:$B$40,'[3]Pillar-2'!$O$5:$O$40),_xlfn.XLOOKUP(_xlpm.iso,'[3]Pillar-2'!$B$5:$B$40,'[3]Pillar-2'!$P$5:$P$40),_xlfn.XLOOKUP(_xlpm.iso,'[3]Pillar-2'!$B$5:$B$40,'[3]Pillar-2'!$Q$5:$Q$40),_xlfn.XLOOKUP(_xlpm.iso,'[3]Pillar-2'!$B$5:$B$40,'[3]Pillar-2'!$R$5:$R$40),_xlfn.XLOOKUP(_xlpm.iso,'[3]Pillar-3'!$B$5:$B$40,'[3]Pillar-3'!$H$5:$H$40),_xlfn.XLOOKUP(_xlpm.iso,'[3]Pillar-3'!$B$5:$B$40,'[3]Pillar-3'!$I$5:$I$40),_xlfn.XLOOKUP(_xlpm.iso,'[3]Pillar-3'!$B$5:$B$40,'[3]Pillar-3'!$J$5:$J$40),_xlfn.XLOOKUP(_xlpm.iso,'[3]Pillar-3'!$B$5:$B$40,'[3]Pillar-3'!$K$5:$K$40),_xlfn.XLOOKUP(_xlpm.iso,'[3]Pillar-3'!$B$5:$B$40,'[3]Pillar-3'!$L$5:$L$40),_xlfn.XLOOKUP(_xlpm.iso,'[3]Pillar-4'!$B$5:$B$40,'[3]Pillar-4'!$K$5:$K$40),_xlfn.XLOOKUP(_xlpm.iso,'[3]Pillar-4'!$B$5:$B$40,'[3]Pillar-4'!$L$5:$L$40),_xlfn.XLOOKUP(_xlpm.iso,'[3]Pillar-4'!$B$5:$B$40,'[3]Pillar-4'!$M$5:$M$40),_xlfn.XLOOKUP(_xlpm.iso,'[3]Pillar-4'!$B$5:$B$40,'[3]Pillar-4'!$N$5:$N$40),_xlfn.XLOOKUP(_xlpm.iso,'[3]Pillar-4'!$B$5:$B$40,'[3]Pillar-4'!$O$5:$O$40),_xlfn.XLOOKUP(_xlpm.iso,'[3]Pillar-5'!$B$5:$B$40,'[3]Pillar-5'!$I$5:$I$40),_xlfn.XLOOKUP(_xlpm.iso,'[3]Pillar-5'!$B$5:$B$40,'[3]Pillar-5'!$J$5:$J$40),_xlfn.XLOOKUP(_xlpm.iso,'[3]Pillar-5'!$B$5:$B$40,'[3]Pillar-5'!$K$5:$K$40),_xlfn.XLOOKUP(_xlpm.iso,'[3]Pillar-5'!$B$5:$B$40,'[3]Pillar-5'!$L$5:$L$40),_xlfn.XLOOKUP(_xlpm.iso,'[3]Pillar-6'!$B$5:$B$40,'[3]Pillar-6'!$I$5:$I$40),_xlfn.XLOOKUP(_xlpm.iso,'[3]Pillar-6'!$B$5:$B$40,'[3]Pillar-6'!$K$5:$K$40),_xlfn.XLOOKUP(_xlpm.iso,'[3]Pillar-6'!$B$5:$B$40,'[3]Pillar-6'!$L$5:$L$40)),SUMPRODUCT(_xlpm.s,$K$4:$K$31)),"") -> 75.461094 | J47: =IF(I47="","",_xlfn.RANK.EQ(I47,$I$36:$I$71,0)) -> 2 | K47: =IF(J47="","",D47-J47) -> 0
... A71: Vietnam | B71: VNM | C71: =_xlfn.XLOOKUP($B71,[3]INDEX!$B$4:$B$39,[3]INDEX!$I$4:$I$39,"") -> 59.047171 | D71: =_xlfn.XLOOKUP($B71,[3]INDEX!$B$4:$B$39,[3]INDEX!$J$4:$J$39,"") -> 8 | E71: =IFERROR(_xlfn.LET(_xlpm.iso,$B71,_xlpm.s,_xlfn.VSTACK(_xlfn.XLOOKUP(_xlpm.iso,'[3]Pillar-1'!$B$5:$B$40,'[3]Pillar-1'!$J$5:$J$40),_xlfn.XLOOKUP(_xlpm.iso,'[3]Pillar-1'!$B$5:$B$40,'[3]Pillar-1'!$K$5:$K$40),_xlfn.XLOOKUP(_xlpm.iso,'[3]Pillar-1'!$B$5:$B$40,'[3]Pillar-1'!$L$5:$L$40),_xlfn.XLOOKUP(_xlpm.iso,'[3]Pillar-2'!$B$5:$B$40,'[3]Pillar-2'!$K$5:$K$40),_xlfn.XLOOKUP(_xlpm.iso,'[3]Pillar-2'!$B$5:$B$40,'[3]Pillar-2'!$L$5:$L$40),_xlfn.XLOOKUP(_xlpm.iso,'[3]Pillar-2'!$B$5:$B$40,'[3]Pillar-2'!$M$5:$M$40),_xlfn.XLOOKUP(_xlpm.iso,'[3]Pillar-2'!$B$5:$B$40,'[3]Pillar-2'!$N$5:$N$40),_xlfn.XLOOKUP(_xlpm.iso,'[3]Pillar-2'!$B$5:$B$40,'[3]Pillar-2'!$O$5:$O$40),_xlfn.XLOOKUP(_xlpm.iso,'[3]Pillar-2'!$B$5:$B$40,'[3]Pillar-2'!$P$5:$P$40),_xlfn.XLOOKUP(_xlpm.iso,'[3]Pillar-2'!$B$5:$B$40,'[3]Pillar-2'!$Q$5:$Q$40),_xlfn.XLOOKUP(_xlpm.iso,'[3]Pillar-2'!$B$5:$B$40,'[3]Pillar-2'!$R$5:$R$40),_xlfn.XLOOKUP(_xlpm.iso,'[3]Pillar-3'!$B$5:$B$40,'[3]Pillar-3'!$H$5:$H$40),_xlfn.XLOOKUP(_xlpm.iso,'[3]Pillar-3'!$B$5:$B$40,'[3]Pillar-3'!$I$5:$I$40),_xlfn.XLOOKUP(_xlpm.iso,'[3]Pillar-3'!$B$5:$B$40,'[3]Pillar-3'!$J$5:$J$40),_xlfn.XLOOKUP(_xlpm.iso,'[3]Pillar-3'!$B$5:$B$40,'[3]Pillar-3'!$K$5:$K$40),_xlfn.XLOOKUP(_xlpm.iso,'[3]Pillar-3'!$B$5:$B$40,'[3]Pillar-3'!$L$5:$L$40),_xlfn.XLOOKUP(_xlpm.iso,'[3]Pillar-4'!$B$5:$B$40,'[3]Pillar-4'!$K$5:$K$40),_xlfn.XLOOKUP(_xlpm.iso,'[3]Pillar-4'!$B$5:$B$40,'[3]Pillar-4'!$L$5:$L$40),_xlfn.XLOOKUP(_xlpm.iso,'[3]Pillar-4'!$B$5:$B$40,'[3]Pillar-4'!$M$5:$M$40),_xlfn.XLOOKUP(_xlpm.iso,'[3]Pillar-4'!$B$5:$B$40,'[3]Pillar-4'!$N$5:$N$40),_xlfn.XLOOKUP(_xlpm.iso,'[3]Pillar-4'!$B$5:$B$40,'[3]Pillar-4'!$O$5:$O$40),_xlfn.XLOOKUP(_xlpm.iso,'[3]Pillar-5'!$B$5:$B$40,'[3]Pillar-5'!$I$5:$I$40),_xlfn.XLOOKUP(_xlpm.iso,'[3]Pillar-5'!$B$5:$B$40,'[3]Pillar-5'!$J$5:$J$40),_xlfn.XLOOKUP(_xlpm.iso,'[3]Pillar-5'!$B$5:$B$40,'[3]Pillar-5'!$K$5:$K$40),_xlfn.XLOOKUP(_xlpm.iso,'[3]Pillar-5'!$B$5:$B$40,'[3]Pillar-5'!$L$5:$L$40),_xlfn.XLOOKUP(_xlpm.iso,'[3]Pillar-6'!$B$5:$B$40,'[3]Pillar-6'!$I$5:$I$40),_xlfn.XLOOKUP(_xlpm.iso,'[3]Pillar-6'!$B$5:$B$40,'[3]Pillar-6'!$K$5:$K$40),_xlfn.XLOOKUP(_xlpm.iso,'[3]Pillar-6'!$B$5:$B$40,'[3]Pillar-6'!$L$5:$L$40)),SUMPRODUCT(_xlpm.s,$I$4:$I$31)),"") -> 58.922583 | F71: =IF(E71="","",_xlfn.RANK.EQ(E71,$E$36:$E$71,0)) -> 8 | G71: =IF(E71="","",E71-C71) -> -0.1245889 | H71: =IF(F71="","",D71-F71) -> 0 | I71: =IFERROR(_xlfn.LET(_xlpm.iso,$B71,_xlpm.s,_xlfn.VSTACK(_xlfn.XLOOKUP(_xlpm.iso,'[3]Pillar-1'!$B$5:$B$40,'[3]Pillar-1'!$J$5:$J$40),_xlfn.XLOOKUP(_xlpm.iso,'[3]Pillar-1'!$B$5:$B$40,'[3]Pillar-1'!$K$5:$K$40),_xlfn.XLOOKUP(_xlpm.iso,'[3]Pillar-1'!$B$5:$B$40,'[3]Pillar-1'!$L$5:$L$40),_xlfn.XLOOKUP(_xlpm.iso,'[3]Pillar-2'!$B$5:$B$40,'[3]Pillar-2'!$K$5:$K$40),_xlfn.XLOOKUP(_xlpm.iso,'[3]Pillar-2'!$B$5:$B$40,'[3]Pillar-2'!$L$5:$L$40),_xlfn.XLOOKUP(_xlpm.iso,'[3]Pillar-2'!$B$5:$B$40,'[3]Pillar-2'!$M$5:$M$40),_xlfn.XLOOKUP(_xlpm.iso,'[3]Pillar-2'!$B$5:$B$40,'[3]Pillar-2'!$N$5:$N$40),_xlfn.XLOOKUP(_xlpm.iso,'[3]Pillar-2'!$B$5:$B$40,'[3]Pillar-2'!$O$5:$O$40),_xlfn.XLOOKUP(_xlpm.iso,'[3]Pillar-2'!$B$5:$B$40,'[3]Pillar-2'!$P$5:$P$40),_xlfn.XLOOKUP(_xlpm.iso,'[3]Pillar-2'!$B$5:$B$40,'[3]Pillar-2'!$Q$5:$Q$40),_xlfn.XLOOKUP(_xlpm.iso,'[3]Pillar-2'!$B$5:$B$40,'[3]Pillar-2'!$R$5:$R$40),_xlfn.XLOOKUP(_xlpm.iso,'[3]Pillar-3'!$B$5:$B$40,'[3]Pillar-3'!$H$5:$H$40),_xlfn.XLOOKUP(_xlpm.iso,'[3]Pillar-3'!$B$5:$B$40,'[3]Pillar-3'!$I$5:$I$40),_xlfn.XLOOKUP(_xlpm.iso,'[3]Pillar-3'!$B$5:$B$40,'[3]Pillar-3'!$J$5:$J$40),_xlfn.XLOOKUP(_xlpm.iso,'[3]Pillar-3'!$B$5:$B$40,'[3]Pillar-3'!$K$5:$K$40),_xlfn.XLOOKUP(_xlpm.iso,'[3]Pillar-3'!$B$5:$B$40,'[3]Pillar-3'!$L$5:$L$40),_xlfn.XLOOKUP(_xlpm.iso,'[3]Pillar-4'!$B$5:$B$40,'[3]Pillar-4'!$K$5:$K$40),_xlfn.XLOOKUP(_xlpm.iso,'[3]Pillar-4'!$B$5:$B$40,'[3]Pillar-4'!$L$5:$L$40),_xlfn.XLOOKUP(_xlpm.iso,'[3]Pillar-4'!$B$5:$B$40,'[3]Pillar-4'!$M$5:$M$40),_xlfn.XLOOKUP(_xlpm.iso,'[3]Pillar-4'!$B$5:$B$40,'[3]Pillar-4'!$N$5:$N$40),_xlfn.XLOOKUP(_xlpm.iso,'[3]Pillar-4'!$B$5:$B$40,'[3]Pillar-4'!$O$5:$O$40),_xlfn.XLOOKUP(_xlpm.iso,'[3]Pillar-5'!$B$5:$B$40,'[3]Pillar-5'!$I$5:$I$40),_xlfn.XLOOKUP(_xlpm.iso,'[3]Pillar-5'!$B$5:$B$40,'[3]Pillar-5'!$J$5:$J$40),_xlfn.XLOOKUP(_xlpm.iso,'[3]Pillar-5'!$B$5:$B$40,'[3]Pillar-5'!$K$5:$K$40),_xlfn.XLOOKUP(_xlpm.iso,'[3]Pillar-5'!$B$5:$B$40,'[3]Pillar-5'!$L$5:$L$40),_xlfn.XLOOKUP(_xlpm.iso,'[3]Pillar-6'!$B$5:$B$40,'[3]Pillar-6'!$I$5:$I$40),_xlfn.XLOOKUP(_xlpm.iso,'[3]Pillar-6'!$B$5:$B$40,'[3]Pillar-6'!$K$5:$K$40),_xlfn.XLOOKUP(_xlpm.iso,'[3]Pillar-6'!$B$5:$B$40,'[3]Pillar-6'!$L$5:$L$40)),SUMPRODUCT(_xlpm.s,$K$4:$K$31)),"") -> 59.039306 | J71: =IF(I71="","",_xlfn.RANK.EQ(I71,$I$36:$I$71,0)) -> 8 | K71: =IF(J71="","",D71-J71) -> 0
A74: The final scoring table shows only the constructs selected to change indicator weights. The broader analysis identified several additional signals that were omitted from the multiplier calculation.
A75: Construct or signal | D75: Why it was not scored directly
A76: X01 – Grid connection and reliability deliverability | D76: Important to coal-to-clean execution, but no final index indicator directly measures transmission access, connection queues, curtailment or replacement-power deliverability.
A77: X02 – Jurisdiction-specific carbon-market integrity reputation | D77: Important to buyers, but difficult to convert into a consistent country score without introducing subjective reputational judgements or double-counting the existing Article 6 and VCM indicators.
A78: X03 – Jurisdiction-level project bankability signals | D78: Cuts across finance, regulation, contracts, currency and government support. Applying it to several indicators would amplify the same event repeatedly.
A79: X04 – Plant-specific community support and funding delivery | D79: Highly relevant at project level, but the base index contains national-level social indicators rather than plant-specific consent, compensation and funding-delivery data.

Sheet Streamlit
A1: Country | B1: ISO3 | C1: Eligible | D1: Base index rank | E1: Base index score | F1: PILLAR 1 score Energy system conditions | G1: PILLAR 2 score Policy and transition commitment | H1: PILLAR 3 score Governance and institutional capacity | I1: PILLAR 4 score Carbon market maturity | J1: PILLAR 5 score Macro-financial conditions | K1: PILLAR 6 score Just transition and social credibility | L1: P1_Indicator1_Score | M1: P1_Indicator2_Score | N1: P1_Indicator3_Score | O1: P2_Indicator1_Score | P1: P2_Indicator2_Score | Q1: P2_Indicator3_Score | R1: P2_Indicator4_Score | S1: P2_Indicator5_Score | T1: P2_Indicator6_Score | U1: P2_Indicator7_Score | V1: P2_Indicator8_Score | W1: P3_Indicator1_Score | X1: P3_Indicator2_Score | Y1: P3_Indicator3_Score | Z1: P3_Indicator4_Score | AA1: P3_Indicator5_Score | AB1: P4_Indicator1_Score | AC1: P4_Indicator2_Score | AD1: P4_Indicator3_Score | AE1: P4_Indicator4_Score | AF1: P4_Indicator5_Score | AG1: P5_Indicator1_Score | AH1: P5_Indicator2_Score | AI1: P5_Indicator3_Score | AJ1: P5_Indicator4_Score | AK1: P6_Indicator1_Score | AL1: P6_Indicator2_Score | AM1: P6_Indicator3_Score
A2: {=_xlfn._xlws.FILTER(Screening!$A$2:$B$216,Screening!$L$2:$L$216="Yes","")} -> Australia | B2: AUS | C2: =IF($B2="","",IFERROR(INDEX(Screening!$A$2:$R$219,MATCH($B2,Screening!$B$2:$B$219,0),MATCH("Include in final index",Screening!$A$1:$R$1,0)),"")) -> Yes | D2: =IF($B2="","",IFERROR(INDEX('INDEX ranked'!$A$3:$J$200,MATCH($B2,'INDEX ranked'!$B$3:$B$200,0),MATCH("Rank",'INDEX ranked'!$A$2:$J$2,0)),"")) -> 6 | E2: =IF($B2="","",IFERROR(INDEX('INDEX ranked'!$A$3:$J$200,MATCH($B2,'INDEX ranked'!$B$3:$B$200,0),MATCH("Overall index score",'INDEX ranked'!$A$2:$J$2,0)),"")) -> 63.028005 | F2: =IF($B2="","",IFERROR(INDEX('INDEX ranked'!$A$3:$J$200,MATCH($B2,'INDEX ranked'!$B$3:$B$200,0),MATCH(F$1,'INDEX ranked'!$A$2:$J$2,0)),"")) -> 46.551741 | G2: =IF($B2="","",IFERROR(INDEX('INDEX ranked'!$A$3:$J$200,MATCH($B2,'INDEX ranked'!$B$3:$B$200,0),MATCH(G$1,'INDEX ranked'!$A$2:$J$2,0)),"")) -> 69.782657 | H2: =IF($B2="","",IFERROR(INDEX('INDEX ranked'!$A$3:$J$200,MATCH($B2,'INDEX ranked'!$B$3:$B$200,0),MATCH(H$1,'INDEX ranked'!$A$2:$J$2,0)),"")) -> 83.6035 | I2: =IF($B2="","",IFERROR(INDEX('INDEX ranked'!$A$3:$J$200,MATCH($B2,'INDEX ranked'!$B$3:$B$200,0),MATCH(I$1,'INDEX ranked'!$A$2:$J$2,0)),"")) -> 38.13411 | J2: =IF($B2="","",IFERROR(INDEX('INDEX ranked'!$A$3:$J$200,MATCH($B2,'INDEX ranked'!$B$3:$B$200,0),MATCH(J$1,'INDEX ranked'!$A$2:$J$2,0)),"")) -> 74.902856 | K2: =IF($B2="","",IFERROR(INDEX('INDEX ranked'!$A$3:$J$200,MATCH($B2,'INDEX ranked'!$B$3:$B$200,0),MATCH(K$1,'INDEX ranked'!$A$2:$J$2,0)),"")) -> 83.5835 | L2: =IF($B2="","",IFERROR(INDEX('Pillar-1'!$A$5:$M$216,MATCH($B2,'Pillar-1'!$B$5:$B$216,0),MATCH(L$1,'Pillar-1'!$A$4:$M$4,0)),"")) -> 39.436783 | M2: =IF($B2="","",IFERROR(INDEX('Pillar-1'!$A$5:$M$216,MATCH($B2,'Pillar-1'!$B$5:$B$216,0),MATCH(M$1,'Pillar-1'!$A$4:$M$4,0)),"")) -> 67.574429 | N2: =IF($B2="","",IFERROR(INDEX('Pillar-1'!$A$5:$M$216,MATCH($B2,'Pillar-1'!$B$5:$B$216,0),MATCH(N$1,'Pillar-1'!$A$4:$M$4,0)),"")) -> 35.647252 | O2: =IF($B2="","",IFERROR(INDEX('Pillar-2'!$A$5:$S$216,MATCH($B2,'Pillar-2'!$B$5:$B$216,0),MATCH(O$1,'Pillar-2'!$A$4:$S$4,0)),"")) -> 67.981481 | P2: =IF($B2="","",IFERROR(INDEX('Pillar-2'!$A$5:$S$216,MATCH($B2,'Pillar-2'!$B$5:$B$216,0),MATCH(P$1,'Pillar-2'!$A$4:$S$4,0)),"")) -> 94.050399 | Q2: =IF($B2="","",IFERROR(INDEX('Pillar-2'!$A$5:$S$216,MATCH($B2,'Pillar-2'!$B$5:$B$216,0),MATCH(Q$1,'Pillar-2'!$A$4:$S$4,0)),"")) -> 100 | R2: =IF($B2="","",IFERROR(INDEX('Pillar-2'!$A$5:$S$216,MATCH($B2,'Pillar-2'!$B$5:$B$216,0),MATCH(R$1,'Pillar-2'!$A$4:$S$4,0)),"")) -> 82.282874 | S2: =IF($B2="","",IFERROR(INDEX('Pillar-2'!$A$5:$S$216,MATCH($B2,'Pillar-2'!$B$5:$B$216,0),MATCH(S$1,'Pillar-2'!$A$4:$S$4,0)),"")) -> 81.444233 | T2: =IF($B2="","",IFERROR(INDEX('Pillar-2'!$A$5:$S$216,MATCH($B2,'Pillar-2'!$B$5:$B$216,0),MATCH(T$1,'Pillar-2'!$A$4:$S$4,0)),"")) -> 86.619533 | U2: =IF($B2="","",IFERROR(INDEX('Pillar-2'!$A$5:$S$216,MATCH($B2,'Pillar-2'!$B$5:$B$216,0),MATCH(U$1,'Pillar-2'!$A$4:$S$4,0)),"")) -> 100 | V2: =IF($B2="","",IFERROR(INDEX('Pillar-2'!$A$5:$S$216,MATCH($B2,'Pillar-2'!$B$5:$B$216,0),MATCH(V$1,'Pillar-2'!$A$4:$S$4,0)),"")) -> 0 | W2: =IF($B2="","",IFERROR(INDEX('Pillar-3'!$A$5:$M$217,MATCH($B2,'Pillar-3'!$B$5:$B$217,0),MATCH(W$1,'Pillar-3'!$A$4:$M$4,0)),"")) -> 79.44 | X2: =IF($B2="","",IFERROR(INDEX('Pillar-3'!$A$5:$M$217,MATCH($B2,'Pillar-3'!$B$5:$B$217,0),MATCH(X$1,'Pillar-3'!$A$4:$M$4,0)),"")) -> 86.52 | Y2: =IF($B2="","",IFERROR(INDEX('Pillar-3'!$A$5:$M$217,MATCH($B2,'Pillar-3'!$B$5:$B$217,0),MATCH(Y$1,'Pillar-3'!$A$4:$M$4,0)),"")) -> 82.03 | Z2: =IF($B2="","",IFERROR(INDEX('Pillar-3'!$A$5:$M$217,MATCH($B2,'Pillar-3'!$B$5:$B$217,0),MATCH(Z$1,'Pillar-3'!$A$4:$M$4,0)),"")) -> 82.27 | AA2: =IF($B2="","",IFERROR(INDEX('Pillar-3'!$A$5:$M$217,MATCH($B2,'Pillar-3'!$B$5:$B$217,0),MATCH(AA$1,'Pillar-3'!$A$4:$M$4,0)),"")) -> 85.34 | AB2: =IF($B2="","",IFERROR(INDEX('Pillar-4'!$A$5:$R$217,MATCH($B2,'Pillar-4'!$B$5:$B$217,0),MATCH(AB$1,'Pillar-4'!$A$4:$R$4,0)),"")) -> 38.793495 | AC2: =IF($B2="","",IFERROR(INDEX('Pillar-4'!$A$5:$R$217,MATCH($B2,'Pillar-4'!$B$5:$B$217,0),MATCH(AC$1,'Pillar-4'!$A$4:$R$4,0)),"")) -> 68.347903 | AD2: =IF($B2="","",IFERROR(INDEX('Pillar-4'!$A$5:$R$217,MATCH($B2,'Pillar-4'!$B$5:$B$217,0),MATCH(AD$1,'Pillar-4'!$A$4:$R$4,0)),"")) -> 69.705537 | AE2: =IF($B2="","",IFERROR(INDEX('Pillar-4'!$A$5:$R$217,MATCH($B2,'Pillar-4'!$B$5:$B$217,0),MATCH(AE$1,'Pillar-4'!$A$4:$R$4,0)),"")) -> 0 | AF2: =IF($B2="","",IFERROR(INDEX('Pillar-4'!$A$5:$R$217,MATCH($B2,'Pillar-4'!$B$5:$B$217,0),MATCH(AF$1,'Pillar-4'!$A$4:$R$4,0)),"")) -> 25 | AG2: =IF($B2="","",IFERROR(INDEX('Pillar-5'!$A$5:$Q$216,MATCH($B2,'Pillar-5'!$B$5:$B$216,0),MATCH(AG$1,'Pillar-5'!$A$4:$Q$4,0)),"")) -> 64.658675 | AH2: =IF($B2="","",IFERROR(INDEX('Pillar-5'!$A$5:$Q$216,MATCH($B2,'Pillar-5'!$B$5:$B$216,0),MATCH(AH$1,'Pillar-5'!$A$4:$Q$4,0)),"")) -> 100 | AI2: =IF($B2="","",IFERROR(INDEX('Pillar-5'!$A$5:$Q$216,MATCH($B2,'Pillar-5'!$B$5:$B$216,0),MATCH(AI$1,'Pillar-5'!$A$4:$Q$4,0)),"")) -> 66.259333 | AJ2: =IF($B2="","",IFERROR(INDEX('Pillar-5'!$A$5:$Q$216,MATCH($B2,'Pillar-5'!$B$5:$B$216,0),MATCH(AJ$1,'Pillar-5'!$A$4:$Q$4,0)),"")) -> 69.013548 | AK2: =IF($B2="","",IFERROR(INDEX('Pillar-6'!$A$5:$Q$216,MATCH($B2,'Pillar-6'!$B$5:$B$216,0),MATCH(AK$1,'Pillar-6'!$A$4:$Q$4,0)),"")) -> 60 | AL2: =IF($B2="","",IFERROR(INDEX('Pillar-6'!$A$5:$Q$216,MATCH($B2,'Pillar-6'!$B$5:$B$216,0),MATCH(AL$1,'Pillar-6'!$A$4:$Q$4,0)),"")) -> 94.63 | AM2: =IF($B2="","",IFERROR(INDEX('Pillar-6'!$A$5:$Q$216,MATCH($B2,'Pillar-6'!$B$5:$B$216,0),MATCH(AM$1,'Pillar-6'!$A$4:$Q$4,0)),"")) -> 100
A3: Bangladesh | B3: BGD | C3: =IF($B3="","",IFERROR(INDEX(Screening!$A$2:$R$219,MATCH($B3,Screening!$B$2:$B$219,0),MATCH("Include in final index",Screening!$A$1:$R$1,0)),"")) -> Yes | D3: =IF($B3="","",IFERROR(INDEX('INDEX ranked'!$A$3:$J$200,MATCH($B3,'INDEX ranked'!$B$3:$B$200,0),MATCH("Rank",'INDEX ranked'!$A$2:$J$2,0)),"")) -> 36 | E3: =IF($B3="","",IFERROR(INDEX('INDEX ranked'!$A$3:$J$200,MATCH($B3,'INDEX ranked'!$B$3:$B$200,0),MATCH("Overall index score",'INDEX ranked'!$A$2:$J$2,0)),"")) -> 35.835974 | F3: =IF($B3="","",IFERROR(INDEX('INDEX ranked'!$A$3:$J$200,MATCH($B3,'INDEX ranked'!$B$3:$B$200,0),MATCH(F$1,'INDEX ranked'!$A$2:$J$2,0)),"")) -> 3.9510783 | G3: =IF($B3="","",IFERROR(INDEX('INDEX ranked'!$A$3:$J$200,MATCH($B3,'INDEX ranked'!$B$3:$B$200,0),MATCH(G$1,'INDEX ranked'!$A$2:$J$2,0)),"")) -> 12.97493 | H3: =IF($B3="","",IFERROR(INDEX('INDEX ranked'!$A$3:$J$200,MATCH($B3,'INDEX ranked'!$B$3:$B$200,0),MATCH(H$1,'INDEX ranked'!$A$2:$J$2,0)),"")) -> 37.0855 | I3: =IF($B3="","",IFERROR(INDEX('INDEX ranked'!$A$3:$J$200,MATCH($B3,'INDEX ranked'!$B$3:$B$200,0),MATCH(I$1,'INDEX ranked'!$A$2:$J$2,0)),"")) -> 77.299124 | J3: =IF($B3="","",IFERROR(INDEX('INDEX ranked'!$A$3:$J$200,MATCH($B3,'INDEX ranked'!$B$3:$B$200,0),MATCH(J$1,'INDEX ranked'!$A$2:$J$2,0)),"")) -> 46.704982 | K3: =IF($B3="","",IFERROR(INDEX('INDEX ranked'!$A$3:$J$200,MATCH($B3,'INDEX ranked'!$B$3:$B$200,0),MATCH(K$1,'INDEX ranked'!$A$2:$J$2,0)),"")) -> 44.22375 | L3: =IF($B3="","",IFERROR(INDEX('Pillar-1'!$A$5:$M$216,MATCH($B3,'Pillar-1'!$B$5:$B$216,0),MATCH(L$1,'Pillar-1'!$A$4:$M$4,0)),"")) -> 0.98505041 | M3: =IF($B3="","",IFERROR(INDEX('Pillar-1'!$A$5:$M$216,MATCH($B3,'Pillar-1'!$B$5:$B$216,0),MATCH(M$1,'Pillar-1'!$A$4:$M$4,0)),"")) -> 2.3771059 | N3: =IF($B3="","",IFERROR(INDEX('Pillar-1'!$A$5:$M$216,MATCH($B3,'Pillar-1'!$B$5:$B$216,0),MATCH(N$1,'Pillar-1'!$A$4:$M$4,0)),"")) -> 8.2662253 | O3: =IF($B3="","",IFERROR(INDEX('Pillar-2'!$A$5:$S$216,MATCH($B3,'Pillar-2'!$B$5:$B$216,0),MATCH(O$1,'Pillar-2'!$A$4:$S$4,0)),"")) -> 26.785714 | P3: =IF($B3="","",IFERROR(INDEX('Pillar-2'!$A$5:$S$216,MATCH($B3,'Pillar-2'!$B$5:$B$216,0),MATCH(P$1,'Pillar-2'!$A$4:$S$4,0)),"")) -> 53.69254 | Q3: =IF($B3="","",IFERROR(INDEX('Pillar-2'!$A$5:$S$216,MATCH($B3,'Pillar-2'!$B$5:$B$216,0),MATCH(Q$1,'Pillar-2'!$A$4:$S$4,0)),"")) -> 0 | R3: =IF($B3="","",IFERROR(INDEX('Pillar-2'!$A$5:$S$216,MATCH($B3,'Pillar-2'!$B$5:$B$216,0),MATCH(R$1,'Pillar-2'!$A$4:$S$4,0)),"")) -> 0 | S3: =IF($B3="","",IFERROR(INDEX('Pillar-2'!$A$5:$S$216,MATCH($B3,'Pillar-2'!$B$5:$B$216,0),MATCH(S$1,'Pillar-2'!$A$4:$S$4,0)),"")) -> 8.3228202 | T3: =IF($B3="","",IFERROR(INDEX('Pillar-2'!$A$5:$S$216,MATCH($B3,'Pillar-2'!$B$5:$B$216,0),MATCH(T$1,'Pillar-2'!$A$4:$S$4,0)),"")) -> 2.1387486 | U3: =IF($B3="","",IFERROR(INDEX('Pillar-2'!$A$5:$S$216,MATCH($B3,'Pillar-2'!$B$5:$B$216,0),MATCH(U$1,'Pillar-2'!$A$4:$S$4,0)),"")) -> 0 | V3: =IF($B3="","",IFERROR(INDEX('Pillar-2'!$A$5:$S$216,MATCH($B3,'Pillar-2'!$B$5:$B$216,0),MATCH(V$1,'Pillar-2'!$A$4:$S$4,0)),"")) -> 0 | W3: =IF($B3="","",IFERROR(INDEX('Pillar-3'!$A$5:$M$217,MATCH($B3,'Pillar-3'!$B$5:$B$217,0),MATCH(W$1,'Pillar-3'!$A$4:$M$4,0)),"")) -> 40.9 | X3: =IF($B3="","",IFERROR(INDEX('Pillar-3'!$A$5:$M$217,MATCH($B3,'Pillar-3'!$B$5:$B$217,0),MATCH(X$1,'Pillar-3'!$A$4:$M$4,0)),"")) -> 39.31 | Y3: =IF($B3="","",IFERROR(INDEX('Pillar-3'!$A$5:$M$217,MATCH($B3,'Pillar-3'!$B$5:$B$217,0),MATCH(Y$1,'Pillar-3'!$A$4:$M$4,0)),"")) -> 39.88 | Z3: =IF($B3="","",IFERROR(INDEX('Pillar-3'!$A$5:$M$217,MATCH($B3,'Pillar-3'!$B$5:$B$217,0),MATCH(Z$1,'Pillar-3'!$A$4:$M$4,0)),"")) -> 40.44 | AA3: =IF($B3="","",IFERROR(INDEX('Pillar-3'!$A$5:$M$217,MATCH($B3,'Pillar-3'!$B$5:$B$217,0),MATCH(AA$1,'Pillar-3'!$A$4:$M$4,0)),"")) -> 25.55 | AB3: =IF($B3="","",IFERROR(INDEX('Pillar-4'!$A$5:$R$217,MATCH($B3,'Pillar-4'!$B$5:$B$217,0),MATCH(AB$1,'Pillar-4'!$A$4:$R$4,0)),"")) -> 67.340065 | AC3: =IF($B3="","",IFERROR(INDEX('Pillar-4'!$A$5:$R$217,MATCH($B3,'Pillar-4'!$B$5:$B$217,0),MATCH(AC$1,'Pillar-4'!$A$4:$R$4,0)),"")) -> 86.118444 | AD3: =IF($B3="","",IFERROR(INDEX('Pillar-4'!$A$5:$R$217,MATCH($B3,'Pillar-4'!$B$5:$B$217,0),MATCH(AD$1,'Pillar-4'!$A$4:$R$4,0)),"")) -> 79.049483 | AE3: =IF($B3="","",IFERROR(INDEX('Pillar-4'!$A$5:$R$217,MATCH($B3,'Pillar-4'!$B$5:$B$217,0),MATCH(AE$1,'Pillar-4'!$A$4:$R$4,0)),"")) -> 80 | AF3: =IF($B3="","",IFERROR(INDEX('Pillar-4'!$A$5:$R$217,MATCH($B3,'Pillar-4'!$B$5:$B$217,0),MATCH(AF$1,'Pillar-4'!$A$4:$R$4,0)),"")) -> 75 | AG3: =IF($B3="","",IFERROR(INDEX('Pillar-5'!$A$5:$Q$216,MATCH($B3,'Pillar-5'!$B$5:$B$216,0),MATCH(AG$1,'Pillar-5'!$A$4:$Q$4,0)),"")) -> 17.905586 | AH3: =IF($B3="","",IFERROR(INDEX('Pillar-5'!$A$5:$Q$216,MATCH($B3,'Pillar-5'!$B$5:$B$216,0),MATCH(AH$1,'Pillar-5'!$A$4:$Q$4,0)),"")) -> 50 | AI3: =IF($B3="","",IFERROR(INDEX('Pillar-5'!$A$5:$Q$216,MATCH($B3,'Pillar-5'!$B$5:$B$216,0),MATCH(AI$1,'Pillar-5'!$A$4:$Q$4,0)),"")) -> 72.685333 | AJ3: =IF($B3="","",IFERROR(INDEX('Pillar-5'!$A$5:$Q$216,MATCH($B3,'Pillar-5'!$B$5:$B$216,0),MATCH(AJ$1,'Pillar-5'!$A$4:$Q$4,0)),"")) -> 57.184957 | AK3: =IF($B3="","",IFERROR(INDEX('Pillar-6'!$A$5:$Q$216,MATCH($B3,'Pillar-6'!$B$5:$B$216,0),MATCH(AK$1,'Pillar-6'!$A$4:$Q$4,0)),"")) -> 20 | AL3: =IF($B3="","",IFERROR(INDEX('Pillar-6'!$A$5:$Q$216,MATCH($B3,'Pillar-6'!$B$5:$B$216,0),MATCH(AL$1,'Pillar-6'!$A$4:$Q$4,0)),"")) -> 38.275 | AM3: =IF($B3="","",IFERROR(INDEX('Pillar-6'!$A$5:$Q$216,MATCH($B3,'Pillar-6'!$B$5:$B$216,0),MATCH(AM$1,'Pillar-6'!$A$4:$Q$4,0)),"")) -> 100
A4: Bosnia and Herzegovina | B4: BIH | C4: =IF($B4="","",IFERROR(INDEX(Screening!$A$2:$R$219,MATCH($B4,Screening!$B$2:$B$219,0),MATCH("Include in final index",Screening!$A$1:$R$1,0)),"")) -> Yes | D4: =IF($B4="","",IFERROR(INDEX('INDEX ranked'!$A$3:$J$200,MATCH($B4,'INDEX ranked'!$B$3:$B$200,0),MATCH("Rank",'INDEX ranked'!$A$2:$J$2,0)),"")) -> 35 | E4: =IF($B4="","",IFERROR(INDEX('INDEX ranked'!$A$3:$J$200,MATCH($B4,'INDEX ranked'!$B$3:$B$200,0),MATCH("Overall index score",'INDEX ranked'!$A$2:$J$2,0)),"")) -> 36.142382 | F4: =IF($B4="","",IFERROR(INDEX('INDEX ranked'!$A$3:$J$200,MATCH($B4,'INDEX ranked'!$B$3:$B$200,0),MATCH(F$1,'INDEX ranked'!$A$2:$J$2,0)),"")) -> 28.514445 | G4: =IF($B4="","",IFERROR(INDEX('INDEX ranked'!$A$3:$J$200,MATCH($B4,'INDEX ranked'!$B$3:$B$200,0),MATCH(G$1,'INDEX ranked'!$A$2:$J$2,0)),"")) -> 38.326415 | H4: =IF($B4="","",IFERROR(INDEX('INDEX ranked'!$A$3:$J$200,MATCH($B4,'INDEX ranked'!$B$3:$B$200,0),MATCH(H$1,'INDEX ranked'!$A$2:$J$2,0)),"")) -> 45.607 | I4: =IF($B4="","",IFERROR(INDEX('INDEX ranked'!$A$3:$J$200,MATCH($B4,'INDEX ranked'!$B$3:$B$200,0),MATCH(I$1,'INDEX ranked'!$A$2:$J$2,0)),"")) -> 0 | J4: =IF($B4="","",IFERROR(INDEX('INDEX ranked'!$A$3:$J$200,MATCH($B4,'INDEX ranked'!$B$3:$B$200,0),MATCH(J$1,'INDEX ranked'!$A$2:$J$2,0)),"")) -> 66.484901 | K4: =IF($B4="","",IFERROR(INDEX('INDEX ranked'!$A$3:$J$200,MATCH($B4,'INDEX ranked'!$B$3:$B$200,0),MATCH(K$1,'INDEX ranked'!$A$2:$J$2,0)),"")) -> 59.60425 | L4: =IF($B4="","",IFERROR(INDEX('Pillar-1'!$A$5:$M$216,MATCH($B4,'Pillar-1'!$B$5:$B$216,0),MATCH(L$1,'Pillar-1'!$A$4:$M$4,0)),"")) -> 45.555684 | M4: =IF($B4="","",IFERROR(INDEX('Pillar-1'!$A$5:$M$216,MATCH($B4,'Pillar-1'!$B$5:$B$216,0),MATCH(M$1,'Pillar-1'!$A$4:$M$4,0)),"")) -> 10.939303 | N4: =IF($B4="","",IFERROR(INDEX('Pillar-1'!$A$5:$M$216,MATCH($B4,'Pillar-1'!$B$5:$B$216,0),MATCH(N$1,'Pillar-1'!$A$4:$M$4,0)),"")) -> 26.537613 | O4: =IF($B4="","",IFERROR(INDEX('Pillar-2'!$A$5:$S$216,MATCH($B4,'Pillar-2'!$B$5:$B$216,0),MATCH(O$1,'Pillar-2'!$A$4:$S$4,0)),"")) -> 35.833333 | P4: =IF($B4="","",IFERROR(INDEX('Pillar-2'!$A$5:$S$216,MATCH($B4,'Pillar-2'!$B$5:$B$216,0),MATCH(P$1,'Pillar-2'!$A$4:$S$4,0)),"")) -> 24.827737 | Q4: =IF($B4="","",IFERROR(INDEX('Pillar-2'!$A$5:$S$216,MATCH($B4,'Pillar-2'!$B$5:$B$216,0),MATCH(Q$1,'Pillar-2'!$A$4:$S$4,0)),"")) -> 100 | R4: =IF($B4="","",IFERROR(INDEX('Pillar-2'!$A$5:$S$216,MATCH($B4,'Pillar-2'!$B$5:$B$216,0),MATCH(R$1,'Pillar-2'!$A$4:$S$4,0)),"")) -> 69.155612 | S4: =IF($B4="","",IFERROR(INDEX('Pillar-2'!$A$5:$S$216,MATCH($B4,'Pillar-2'!$B$5:$B$216,0),MATCH(S$1,'Pillar-2'!$A$4:$S$4,0)),"")) -> 43.597079 | T4: =IF($B4="","",IFERROR(INDEX('Pillar-2'!$A$5:$S$216,MATCH($B4,'Pillar-2'!$B$5:$B$216,0),MATCH(T$1,'Pillar-2'!$A$4:$S$4,0)),"")) -> 56.545677 | U4: =IF($B4="","",IFERROR(INDEX('Pillar-2'!$A$5:$S$216,MATCH($B4,'Pillar-2'!$B$5:$B$216,0),MATCH(U$1,'Pillar-2'!$A$4:$S$4,0)),"")) -> 0 | V4: =IF($B4="","",IFERROR(INDEX('Pillar-2'!$A$5:$S$216,MATCH($B4,'Pillar-2'!$B$5:$B$216,0),MATCH(V$1,'Pillar-2'!$A$4:$S$4,0)),"")) -> 0 | W4: =IF($B4="","",IFERROR(INDEX('Pillar-3'!$A$5:$M$217,MATCH($B4,'Pillar-3'!$B$5:$B$217,0),MATCH(W$1,'Pillar-3'!$A$4:$M$4,0)),"")) -> 57.34 | X4: =IF($B4="","",IFERROR(INDEX('Pillar-3'!$A$5:$M$217,MATCH($B4,'Pillar-3'!$B$5:$B$217,0),MATCH(X$1,'Pillar-3'!$A$4:$M$4,0)),"")) -> 38.99 | Y4: =IF($B4="","",IFERROR(INDEX('Pillar-3'!$A$5:$M$217,MATCH($B4,'Pillar-3'!$B$5:$B$217,0),MATCH(Y$1,'Pillar-3'!$A$4:$M$4,0)),"")) -> 49.35 | Z4: =IF($B4="","",IFERROR(INDEX('Pillar-3'!$A$5:$M$217,MATCH($B4,'Pillar-3'!$B$5:$B$217,0),MATCH(Z$1,'Pillar-3'!$A$4:$M$4,0)),"")) -> 51.47 | AA4: =IF($B4="","",IFERROR(INDEX('Pillar-3'!$A$5:$M$217,MATCH($B4,'Pillar-3'!$B$5:$B$217,0),MATCH(AA$1,'Pillar-3'!$A$4:$M$4,0)),"")) -> 37.47 | AB4: =IF($B4="","",IFERROR(INDEX('Pillar-4'!$A$5:$R$217,MATCH($B4,'Pillar-4'!$B$5:$B$217,0),MATCH(AB$1,'Pillar-4'!$A$4:$R$4,0)),"")) -> 0 | AC4: =IF($B4="","",IFERROR(INDEX('Pillar-4'!$A$5:$R$217,MATCH($B4,'Pillar-4'!$B$5:$B$217,0),MATCH(AC$1,'Pillar-4'!$A$4:$R$4,0)),"")) -> 0 | AD4: =IF($B4="","",IFERROR(INDEX('Pillar-4'!$A$5:$R$217,MATCH($B4,'Pillar-4'!$B$5:$B$217,0),MATCH(AD$1,'Pillar-4'!$A$4:$R$4,0)),"")) -> 0 | AE4: =IF($B4="","",IFERROR(INDEX('Pillar-4'!$A$5:$R$217,MATCH($B4,'Pillar-4'!$B$5:$B$217,0),MATCH(AE$1,'Pillar-4'!$A$4:$R$4,0)),"")) -> 0 | AF4: =IF($B4="","",IFERROR(INDEX('Pillar-4'!$A$5:$R$217,MATCH($B4,'Pillar-4'!$B$5:$B$217,0),MATCH(AF$1,'Pillar-4'!$A$4:$R$4,0)),"")) -> 0 | AG4: =IF($B4="","",IFERROR(INDEX('Pillar-5'!$A$5:$Q$216,MATCH($B4,'Pillar-5'!$B$5:$B$216,0),MATCH(AG$1,'Pillar-5'!$A$4:$Q$4,0)),"")) -> 24.133689 | AH4: =IF($B4="","",IFERROR(INDEX('Pillar-5'!$A$5:$Q$216,MATCH($B4,'Pillar-5'!$B$5:$B$216,0),MATCH(AH$1,'Pillar-5'!$A$4:$Q$4,0)),"")) -> 100 | AI4: =IF($B4="","",IFERROR(INDEX('Pillar-5'!$A$5:$Q$216,MATCH($B4,'Pillar-5'!$B$5:$B$216,0),MATCH(AI$1,'Pillar-5'!$A$4:$Q$4,0)),"")) -> 80.398 | AJ4: =IF($B4="","",IFERROR(INDEX('Pillar-5'!$A$5:$Q$216,MATCH($B4,'Pillar-5'!$B$5:$B$216,0),MATCH(AJ$1,'Pillar-5'!$A$4:$Q$4,0)),"")) -> 72.660777 | AK4: =IF($B4="","",IFERROR(INDEX('Pillar-6'!$A$5:$Q$216,MATCH($B4,'Pillar-6'!$B$5:$B$216,0),MATCH(AK$1,'Pillar-6'!$A$4:$Q$4,0)),"")) -> 60 | AL4: =IF($B4="","",IFERROR(INDEX('Pillar-6'!$A$5:$Q$216,MATCH($B4,'Pillar-6'!$B$5:$B$216,0),MATCH(AL$1,'Pillar-6'!$A$4:$Q$4,0)),"")) -> 63.565 | AM4: =IF($B4="","",IFERROR(INDEX('Pillar-6'!$A$5:$Q$216,MATCH($B4,'Pillar-6'!$B$5:$B$216,0),MATCH(AM$1,'Pillar-6'!$A$4:$Q$4,0)),"")) -> 50
A5: Brazil | B5: BRA | C5: =IF($B5="","",IFERROR(INDEX(Screening!$A$2:$R$219,MATCH($B5,Screening!$B$2:$B$219,0),MATCH("Include in final index",Screening!$A$1:$R$1,0)),"")) -> Yes | D5: =IF($B5="","",IFERROR(INDEX('INDEX ranked'!$A$3:$J$200,MATCH($B5,'INDEX ranked'!$B$3:$B$200,0),MATCH("Rank",'INDEX ranked'!$A$2:$J$2,0)),"")) -> 5 | E5: =IF($B5="","",IFERROR(INDEX('INDEX ranked'!$A$3:$J$200,MATCH($B5,'INDEX ranked'!$B$3:$B$200,0),MATCH("Overall index score",'INDEX ranked'!$A$2:$J$2,0)),"")) -> 64.650458 | F5: =IF($B5="","",IFERROR(INDEX('INDEX ranked'!$A$3:$J$200,MATCH($B5,'INDEX ranked'!$B$3:$B$200,0),MATCH(F$1,'INDEX ranked'!$A$2:$J$2,0)),"")) -> 86.575121 | G5: =IF($B5="","",IFERROR(INDEX('INDEX ranked'!$A$3:$J$200,MATCH($B5,'INDEX ranked'!$B$3:$B$200,0),MATCH(G$1,'INDEX ranked'!$A$2:$J$2,0)),"")) -> 56.001412 | H5: =IF($B5="","",IFERROR(INDEX('INDEX ranked'!$A$3:$J$200,MATCH($B5,'INDEX ranked'!$B$3:$B$200,0),MATCH(H$1,'INDEX ranked'!$A$2:$J$2,0)),"")) -> 47.772 | I5: =IF($B5="","",IFERROR(INDEX('INDEX ranked'!$A$3:$J$200,MATCH($B5,'INDEX ranked'!$B$3:$B$200,0),MATCH(I$1,'INDEX ranked'!$A$2:$J$2,0)),"")) -> 72.481828 | J5: =IF($B5="","",IFERROR(INDEX('INDEX ranked'!$A$3:$J$200,MATCH($B5,'INDEX ranked'!$B$3:$B$200,0),MATCH(J$1,'INDEX ranked'!$A$2:$J$2,0)),"")) -> 53.849575 | K5: =IF($B5="","",IFERROR(INDEX('INDEX ranked'!$A$3:$J$200,MATCH($B5,'INDEX ranked'!$B$3:$B$200,0),MATCH(K$1,'INDEX ranked'!$A$2:$J$2,0)),"")) -> 63.9555 | L5: =IF($B5="","",IFERROR(INDEX('Pillar-1'!$A$5:$M$216,MATCH($B5,'Pillar-1'!$B$5:$B$216,0),MATCH(L$1,'Pillar-1'!$A$4:$M$4,0)),"")) -> 100 | M5: =IF($B5="","",IFERROR(INDEX('Pillar-1'!$A$5:$M$216,MATCH($B5,'Pillar-1'!$B$5:$B$216,0),MATCH(M$1,'Pillar-1'!$A$4:$M$4,0)),"")) -> 55.250404 | N5: =IF($B5="","",IFERROR(INDEX('Pillar-1'!$A$5:$M$216,MATCH($B5,'Pillar-1'!$B$5:$B$216,0),MATCH(N$1,'Pillar-1'!$A$4:$M$4,0)),"")) -> 100 | O5: =IF($B5="","",IFERROR(INDEX('Pillar-2'!$A$5:$S$216,MATCH($B5,'Pillar-2'!$B$5:$B$216,0),MATCH(O$1,'Pillar-2'!$A$4:$S$4,0)),"")) -> 65.092593 | P5: =IF($B5="","",IFERROR(INDEX('Pillar-2'!$A$5:$S$216,MATCH($B5,'Pillar-2'!$B$5:$B$216,0),MATCH(P$1,'Pillar-2'!$A$4:$S$4,0)),"")) -> 100 | Q5: =IF($B5="","",IFERROR(INDEX('Pillar-2'!$A$5:$S$216,MATCH($B5,'Pillar-2'!$B$5:$B$216,0),MATCH(Q$1,'Pillar-2'!$A$4:$S$4,0)),"")) -> 100 | R5: =IF($B5="","",IFERROR(INDEX('Pillar-2'!$A$5:$S$216,MATCH($B5,'Pillar-2'!$B$5:$B$216,0),MATCH(R$1,'Pillar-2'!$A$4:$S$4,0)),"")) -> 46.420397 | S5: =IF($B5="","",IFERROR(INDEX('Pillar-2'!$A$5:$S$216,MATCH($B5,'Pillar-2'!$B$5:$B$216,0),MATCH(S$1,'Pillar-2'!$A$4:$S$4,0)),"")) -> 46.859397 | T5: =IF($B5="","",IFERROR(INDEX('Pillar-2'!$A$5:$S$216,MATCH($B5,'Pillar-2'!$B$5:$B$216,0),MATCH(T$1,'Pillar-2'!$A$4:$S$4,0)),"")) -> 42.459064 | U5: =IF($B5="","",IFERROR(INDEX('Pillar-2'!$A$5:$S$216,MATCH($B5,'Pillar-2'!$B$5:$B$216,0),MATCH(U$1,'Pillar-2'!$A$4:$S$4,0)),"")) -> 70 | V5: =IF($B5="","",IFERROR(INDEX('Pillar-2'!$A$5:$S$216,MATCH($B5,'Pillar-2'!$B$5:$B$216,0),MATCH(V$1,'Pillar-2'!$A$4:$S$4,0)),"")) -> 0 | W5: =IF($B5="","",IFERROR(INDEX('Pillar-3'!$A$5:$M$217,MATCH($B5,'Pillar-3'!$B$5:$B$217,0),MATCH(W$1,'Pillar-3'!$A$4:$M$4,0)),"")) -> 57 | X5: =IF($B5="","",IFERROR(INDEX('Pillar-3'!$A$5:$M$217,MATCH($B5,'Pillar-3'!$B$5:$B$217,0),MATCH(X$1,'Pillar-3'!$A$4:$M$4,0)),"")) -> 46.98 | Y5: =IF($B5="","",IFERROR(INDEX('Pillar-3'!$A$5:$M$217,MATCH($B5,'Pillar-3'!$B$5:$B$217,0),MATCH(Y$1,'Pillar-3'!$A$4:$M$4,0)),"")) -> 50.22 | Z5: =IF($B5="","",IFERROR(INDEX('Pillar-3'!$A$5:$M$217,MATCH($B5,'Pillar-3'!$B$5:$B$217,0),MATCH(Z$1,'Pillar-3'!$A$4:$M$4,0)),"")) -> 49.28 | AA5: =IF($B5="","",IFERROR(INDEX('Pillar-3'!$A$5:$M$217,MATCH($B5,'Pillar-3'!$B$5:$B$217,0),MATCH(AA$1,'Pillar-3'!$A$4:$M$4,0)),"")) -> 39.58 | AB5: =IF($B5="","",IFERROR(INDEX('Pillar-4'!$A$5:$R$217,MATCH($B5,'Pillar-4'!$B$5:$B$217,0),MATCH(AB$1,'Pillar-4'!$A$4:$R$4,0)),"")) -> 77.378252 | AC5: =IF($B5="","",IFERROR(INDEX('Pillar-4'!$A$5:$R$217,MATCH($B5,'Pillar-4'!$B$5:$B$217,0),MATCH(AC$1,'Pillar-4'!$A$4:$R$4,0)),"")) -> 93.390611 | AD5: =IF($B5="","",IFERROR(INDEX('Pillar-4'!$A$5:$R$217,MATCH($B5,'Pillar-4'!$B$5:$B$217,0),MATCH(AD$1,'Pillar-4'!$A$4:$R$4,0)),"")) -> 92.187035 | AE5: =IF($B5="","",IFERROR(INDEX('Pillar-4'!$A$5:$R$217,MATCH($B5,'Pillar-4'!$B$5:$B$217,0),MATCH(AE$1,'Pillar-4'!$A$4:$R$4,0)),"")) -> 60 | AF5: =IF($B5="","",IFERROR(INDEX('Pillar-4'!$A$5:$R$217,MATCH($B5,'Pillar-4'!$B$5:$B$217,0),MATCH(AF$1,'Pillar-4'!$A$4:$R$4,0)),"")) -> 50 | AG5: =IF($B5="","",IFERROR(INDEX('Pillar-5'!$A$5:$Q$216,MATCH($B5,'Pillar-5'!$B$5:$B$216,0),MATCH(AG$1,'Pillar-5'!$A$4:$Q$4,0)),"")) -> 37.815437 | AH5: =IF($B5="","",IFERROR(INDEX('Pillar-5'!$A$5:$Q$216,MATCH($B5,'Pillar-5'!$B$5:$B$216,0),MATCH(AH$1,'Pillar-5'!$A$4:$Q$4,0)),"")) -> 100 | AI5: =IF($B5="","",IFERROR(INDEX('Pillar-5'!$A$5:$Q$216,MATCH($B5,'Pillar-5'!$B$5:$B$216,0),MATCH(AI$1,'Pillar-5'!$A$4:$Q$4,0)),"")) -> 41.981333 | AJ5: =IF($B5="","",IFERROR(INDEX('Pillar-5'!$A$5:$Q$216,MATCH($B5,'Pillar-5'!$B$5:$B$216,0),MATCH(AJ$1,'Pillar-5'!$A$4:$Q$4,0)),"")) -> 36.43471 | AK5: =IF($B5="","",IFERROR(INDEX('Pillar-6'!$A$5:$Q$216,MATCH($B5,'Pillar-6'!$B$5:$B$216,0),MATCH(AK$1,'Pillar-6'!$A$4:$Q$4,0)),"")) -> 45 | AL5: =IF($B5="","",IFERROR(INDEX('Pillar-6'!$A$5:$Q$216,MATCH($B5,'Pillar-6'!$B$5:$B$216,0),MATCH(AL$1,'Pillar-6'!$A$4:$Q$4,0)),"")) -> 73.79 | AM5: =IF($B5="","",IFERROR(INDEX('Pillar-6'!$A$5:$Q$216,MATCH($B5,'Pillar-6'!$B$5:$B$216,0),MATCH(AM$1,'Pillar-6'!$A$4:$Q$4,0)),"")) -> 75
A6: Bulgaria | B6: BGR | C6: =IF($B6="","",IFERROR(INDEX(Screening!$A$2:$R$219,MATCH($B6,Screening!$B$2:$B$219,0),MATCH("Include in final index",Screening!$A$1:$R$1,0)),"")) -> Yes | D6: =IF($B6="","",IFERROR(INDEX('INDEX ranked'!$A$3:$J$200,MATCH($B6,'INDEX ranked'!$B$3:$B$200,0),MATCH("Rank",'INDEX ranked'!$A$2:$J$2,0)),"")) -> 11 | E6: =IF($B6="","",IFERROR(INDEX('INDEX ranked'!$A$3:$J$200,MATCH($B6,'INDEX ranked'!$B$3:$B$200,0),MATCH("Overall index score",'INDEX ranked'!$A$2:$J$2,0)),"")) -> 57.30298 | F6: =IF($B6="","",IFERROR(INDEX('INDEX ranked'!$A$3:$J$200,MATCH($B6,'INDEX ranked'!$B$3:$B$200,0),MATCH(F$1,'INDEX ranked'!$A$2:$J$2,0)),"")) -> 55.203175 | G6: =IF($B6="","",IFERROR(INDEX('INDEX ranked'!$A$3:$J$200,MATCH($B6,'INDEX ranked'!$B$3:$B$200,0),MATCH(G$1,'INDEX ranked'!$A$2:$J$2,0)),"")) -> 69.049865 | H6: =IF($B6="","",IFERROR(INDEX('INDEX ranked'!$A$3:$J$200,MATCH($B6,'INDEX ranked'!$B$3:$B$200,0),MATCH(H$1,'INDEX ranked'!$A$2:$J$2,0)),"")) -> 54.431 | I6: =IF($B6="","",IFERROR(INDEX('INDEX ranked'!$A$3:$J$200,MATCH($B6,'INDEX ranked'!$B$3:$B$200,0),MATCH(I$1,'INDEX ranked'!$A$2:$J$2,0)),"")) -> 31.90232 | J6: =IF($B6="","",IFERROR(INDEX('INDEX ranked'!$A$3:$J$200,MATCH($B6,'INDEX ranked'!$B$3:$B$200,0),MATCH(J$1,'INDEX ranked'!$A$2:$J$2,0)),"")) -> 67.029884 | K6: =IF($B6="","",IFERROR(INDEX('INDEX ranked'!$A$3:$J$200,MATCH($B6,'INDEX ranked'!$B$3:$B$200,0),MATCH(K$1,'INDEX ranked'!$A$2:$J$2,0)),"")) -> 78.52775 | L6: =IF($B6="","",IFERROR(INDEX('Pillar-1'!$A$5:$M$216,MATCH($B6,'Pillar-1'!$B$5:$B$216,0),MATCH(L$1,'Pillar-1'!$A$4:$M$4,0)),"")) -> 33.456948 | M6: =IF($B6="","",IFERROR(INDEX('Pillar-1'!$A$5:$M$216,MATCH($B6,'Pillar-1'!$B$5:$B$216,0),MATCH(M$1,'Pillar-1'!$A$4:$M$4,0)),"")) -> 41.472421 | N6: =IF($B6="","",IFERROR(INDEX('Pillar-1'!$A$5:$M$216,MATCH($B6,'Pillar-1'!$B$5:$B$216,0),MATCH(N$1,'Pillar-1'!$A$4:$M$4,0)),"")) -> 88.718619 | O6: =IF($B6="","",IFERROR(INDEX('Pillar-2'!$A$5:$S$216,MATCH($B6,'Pillar-2'!$B$5:$B$216,0),MATCH(O$1,'Pillar-2'!$A$4:$S$4,0)),"")) -> 27.63 | P6: =IF($B6="","",IFERROR(INDEX('Pillar-2'!$A$5:$S$216,MATCH($B6,'Pillar-2'!$B$5:$B$216,0),MATCH(P$1,'Pillar-2'!$A$4:$S$4,0)),"")) -> 100 | Q6: =IF($B6="","",IFERROR(INDEX('Pillar-2'!$A$5:$S$216,MATCH($B6,'Pillar-2'!$B$5:$B$216,0),MATCH(Q$1,'Pillar-2'!$A$4:$S$4,0)),"")) -> 100 | R6: =IF($B6="","",IFERROR(INDEX('Pillar-2'!$A$5:$S$216,MATCH($B6,'Pillar-2'!$B$5:$B$216,0),MATCH(R$1,'Pillar-2'!$A$4:$S$4,0)),"")) -> 84.684862 | S6: =IF($B6="","",IFERROR(INDEX('Pillar-2'!$A$5:$S$216,MATCH($B6,'Pillar-2'!$B$5:$B$216,0),MATCH(S$1,'Pillar-2'!$A$4:$S$4,0)),"")) -> 63.185202 | T6: =IF($B6="","",IFERROR(INDEX('Pillar-2'!$A$5:$S$216,MATCH($B6,'Pillar-2'!$B$5:$B$216,0),MATCH(T$1,'Pillar-2'!$A$4:$S$4,0)),"")) -> 87.373216 | U6: =IF($B6="","",IFERROR(INDEX('Pillar-2'!$A$5:$S$216,MATCH($B6,'Pillar-2'!$B$5:$B$216,0),MATCH(U$1,'Pillar-2'!$A$4:$S$4,0)),"")) -> 100 | V6: =IF($B6="","",IFERROR(INDEX('Pillar-2'!$A$5:$S$216,MATCH($B6,'Pillar-2'!$B$5:$B$216,0),MATCH(V$1,'Pillar-2'!$A$4:$S$4,0)),"")) -> 25 | W6: =IF($B6="","",IFERROR(INDEX('Pillar-3'!$A$5:$M$217,MATCH($B6,'Pillar-3'!$B$5:$B$217,0),MATCH(W$1,'Pillar-3'!$A$4:$M$4,0)),"")) -> 66.58 | X6: =IF($B6="","",IFERROR(INDEX('Pillar-3'!$A$5:$M$217,MATCH($B6,'Pillar-3'!$B$5:$B$217,0),MATCH(X$1,'Pillar-3'!$A$4:$M$4,0)),"")) -> 52.17 | Y6: =IF($B6="","",IFERROR(INDEX('Pillar-3'!$A$5:$M$217,MATCH($B6,'Pillar-3'!$B$5:$B$217,0),MATCH(Y$1,'Pillar-3'!$A$4:$M$4,0)),"")) -> 59.41 | Z6: =IF($B6="","",IFERROR(INDEX('Pillar-3'!$A$5:$M$217,MATCH($B6,'Pillar-3'!$B$5:$B$217,0),MATCH(Z$1,'Pillar-3'!$A$4:$M$4,0)),"")) -> 56.39 | AA6: =IF($B6="","",IFERROR(INDEX('Pillar-3'!$A$5:$M$217,MATCH($B6,'Pillar-3'!$B$5:$B$217,0),MATCH(AA$1,'Pillar-3'!$A$4:$M$4,0)),"")) -> 43 | AB6: =IF($B6="","",IFERROR(INDEX('Pillar-4'!$A$5:$R$217,MATCH($B6,'Pillar-4'!$B$5:$B$217,0),MATCH(AB$1,'Pillar-4'!$A$4:$R$4,0)),"")) -> 27.909492 | AC6: =IF($B6="","",IFERROR(INDEX('Pillar-4'!$A$5:$R$217,MATCH($B6,'Pillar-4'!$B$5:$B$217,0),MATCH(AC$1,'Pillar-4'!$A$4:$R$4,0)),"")) -> 74.895699 | AD6: =IF($B6="","",IFERROR(INDEX('Pillar-4'!$A$5:$R$217,MATCH($B6,'Pillar-4'!$B$5:$B$217,0),MATCH(AD$1,'Pillar-4'!$A$4:$R$4,0)),"")) -> 75.608549 | AE6: =IF($B6="","",IFERROR(INDEX('Pillar-4'!$A$5:$R$217,MATCH($B6,'Pillar-4'!$B$5:$B$217,0),MATCH(AE$1,'Pillar-4'!$A$4:$R$4,0)),"")) -> 0 | AF6: =IF($B6="","",IFERROR(INDEX('Pillar-4'!$A$5:$R$217,MATCH($B6,'Pillar-4'!$B$5:$B$217,0),MATCH(AF$1,'Pillar-4'!$A$4:$R$4,0)),"")) -> 0 | AG6: =IF($B6="","",IFERROR(INDEX('Pillar-5'!$A$5:$Q$216,MATCH($B6,'Pillar-5'!$B$5:$B$216,0),MATCH(AG$1,'Pillar-5'!$A$4:$Q$4,0)),"")) -> 23.533951 | AH6: =IF($B6="","",IFERROR(INDEX('Pillar-5'!$A$5:$Q$216,MATCH($B6,'Pillar-5'!$B$5:$B$216,0),MATCH(AH$1,'Pillar-5'!$A$4:$Q$4,0)),"")) -> 100 | AI6: =IF($B6="","",IFERROR(INDEX('Pillar-5'!$A$5:$Q$216,MATCH($B6,'Pillar-5'!$B$5:$B$216,0),MATCH(AI$1,'Pillar-5'!$A$4:$Q$4,0)),"")) -> 84.106667 | AJ6: =IF($B6="","",IFERROR(INDEX('Pillar-5'!$A$5:$Q$216,MATCH($B6,'Pillar-5'!$B$5:$B$216,0),MATCH(AJ$1,'Pillar-5'!$A$4:$Q$4,0)),"")) -> 72.593461 | AK6: =IF($B6="","",IFERROR(INDEX('Pillar-6'!$A$5:$Q$216,MATCH($B6,'Pillar-6'!$B$5:$B$216,0),MATCH(AK$1,'Pillar-6'!$A$4:$Q$4,0)),"")) -> 60 | AL6: =IF($B6="","",IFERROR(INDEX('Pillar-6'!$A$5:$Q$216,MATCH($B6,'Pillar-6'!$B$5:$B$216,0),MATCH(AL$1,'Pillar-6'!$A$4:$Q$4,0)),"")) -> 83.395 | AM6: =IF($B6="","",IFERROR(INDEX('Pillar-6'!$A$5:$Q$216,MATCH($B6,'Pillar-6'!$B$5:$B$216,0),MATCH(AM$1,'Pillar-6'!$A$4:$Q$4,0)),"")) -> 100
A7: Cambodia | B7: KHM | C7: =IF($B7="","",IFERROR(INDEX(Screening!$A$2:$R$219,MATCH($B7,Screening!$B$2:$B$219,0),MATCH("Include in final index",Screening!$A$1:$R$1,0)),"")) -> Yes | D7: =IF($B7="","",IFERROR(INDEX('INDEX ranked'!$A$3:$J$200,MATCH($B7,'INDEX ranked'!$B$3:$B$200,0),MATCH("Rank",'INDEX ranked'!$A$2:$J$2,0)),"")) -> 20 | E7: =IF($B7="","",IFERROR(INDEX('INDEX ranked'!$A$3:$J$200,MATCH($B7,'INDEX ranked'!$B$3:$B$200,0),MATCH("Overall index score",'INDEX ranked'!$A$2:$J$2,0)),"")) -> 49.013545 | F7: =IF($B7="","",IFERROR(INDEX('INDEX ranked'!$A$3:$J$200,MATCH($B7,'INDEX ranked'!$B$3:$B$200,0),MATCH(F$1,'INDEX ranked'!$A$2:$J$2,0)),"")) -> 32.203217 | G7: =IF($B7="","",IFERROR(INDEX('INDEX ranked'!$A$3:$J$200,MATCH($B7,'INDEX ranked'!$B$3:$B$200,0),MATCH(G$1,'INDEX ranked'!$A$2:$J$2,0)),"")) -> 17.988229 | H7: =IF($B7="","",IFERROR(INDEX('INDEX ranked'!$A$3:$J$200,MATCH($B7,'INDEX ranked'!$B$3:$B$200,0),MATCH(H$1,'INDEX ranked'!$A$2:$J$2,0)),"")) -> 41.782 | I7: =IF($B7="","",IFERROR(INDEX('INDEX ranked'!$A$3:$J$200,MATCH($B7,'INDEX ranked'!$B$3:$B$200,0),MATCH(I$1,'INDEX ranked'!$A$2:$J$2,0)),"")) -> 78.86397 | J7: =IF($B7="","",IFERROR(INDEX('INDEX ranked'!$A$3:$J$200,MATCH($B7,'INDEX ranked'!$B$3:$B$200,0),MATCH(J$1,'INDEX ranked'!$A$2:$J$2,0)),"")) -> 84.482081 | K7: =IF($B7="","",IFERROR(INDEX('INDEX ranked'!$A$3:$J$200,MATCH($B7,'INDEX ranked'!$B$3:$B$200,0),MATCH(K$1,'INDEX ranked'!$A$2:$J$2,0)),"")) -> 42.6285 | L7: =IF($B7="","",IFERROR(INDEX('Pillar-1'!$A$5:$M$216,MATCH($B7,'Pillar-1'!$B$5:$B$216,0),MATCH(L$1,'Pillar-1'!$A$4:$M$4,0)),"")) -> 40.120524 | M7: =IF($B7="","",IFERROR(INDEX('Pillar-1'!$A$5:$M$216,MATCH($B7,'Pillar-1'!$B$5:$B$216,0),MATCH(M$1,'Pillar-1'!$A$4:$M$4,0)),"")) -> 15.555043 | N7: =IF($B7="","",IFERROR(INDEX('Pillar-1'!$A$5:$M$216,MATCH($B7,'Pillar-1'!$B$5:$B$216,0),MATCH(N$1,'Pillar-1'!$A$4:$M$4,0)),"")) -> 38.555775 | O7: =IF($B7="","",IFERROR(INDEX('Pillar-2'!$A$5:$S$216,MATCH($B7,'Pillar-2'!$B$5:$B$216,0),MATCH(O$1,'Pillar-2'!$A$4:$S$4,0)),"")) -> 16.507937 | P7: =IF($B7="","",IFERROR(INDEX('Pillar-2'!$A$5:$S$216,MATCH($B7,'Pillar-2'!$B$5:$B$216,0),MATCH(P$1,'Pillar-2'!$A$4:$S$4,0)),"")) -> 100 | Q7: =IF($B7="","",IFERROR(INDEX('Pillar-2'!$A$5:$S$216,MATCH($B7,'Pillar-2'!$B$5:$B$216,0),MATCH(Q$1,'Pillar-2'!$A$4:$S$4,0)),"")) -> 0.060638069 | R7: =IF($B7="","",IFERROR(INDEX('Pillar-2'!$A$5:$S$216,MATCH($B7,'Pillar-2'!$B$5:$B$216,0),MATCH(R$1,'Pillar-2'!$A$4:$S$4,0)),"")) -> 0 | S7: =IF($B7="","",IFERROR(INDEX('Pillar-2'!$A$5:$S$216,MATCH($B7,'Pillar-2'!$B$5:$B$216,0),MATCH(S$1,'Pillar-2'!$A$4:$S$4,0)),"")) -> 0 | T7: =IF($B7="","",IFERROR(INDEX('Pillar-2'!$A$5:$S$216,MATCH($B7,'Pillar-2'!$B$5:$B$216,0),MATCH(T$1,'Pillar-2'!$A$4:$S$4,0)),"")) -> 0 | U7: =IF($B7="","",IFERROR(INDEX('Pillar-2'!$A$5:$S$216,MATCH($B7,'Pillar-2'!$B$5:$B$216,0),MATCH(U$1,'Pillar-2'!$A$4:$S$4,0)),"")) -> 0 | V7: =IF($B7="","",IFERROR(INDEX('Pillar-2'!$A$5:$S$216,MATCH($B7,'Pillar-2'!$B$5:$B$216,0),MATCH(V$1,'Pillar-2'!$A$4:$S$4,0)),"")) -> 0 | W7: =IF($B7="","",IFERROR(INDEX('Pillar-3'!$A$5:$M$217,MATCH($B7,'Pillar-3'!$B$5:$B$217,0),MATCH(W$1,'Pillar-3'!$A$4:$M$4,0)),"")) -> 68.09 | X7: =IF($B7="","",IFERROR(INDEX('Pillar-3'!$A$5:$M$217,MATCH($B7,'Pillar-3'!$B$5:$B$217,0),MATCH(X$1,'Pillar-3'!$A$4:$M$4,0)),"")) -> 45.63 | Y7: =IF($B7="","",IFERROR(INDEX('Pillar-3'!$A$5:$M$217,MATCH($B7,'Pillar-3'!$B$5:$B$217,0),MATCH(Y$1,'Pillar-3'!$A$4:$M$4,0)),"")) -> 44.91 | Z7: =IF($B7="","",IFERROR(INDEX('Pillar-3'!$A$5:$M$217,MATCH($B7,'Pillar-3'!$B$5:$B$217,0),MATCH(Z$1,'Pillar-3'!$A$4:$M$4,0)),"")) -> 38.79 | AA7: =IF($B7="","",IFERROR(INDEX('Pillar-3'!$A$5:$M$217,MATCH($B7,'Pillar-3'!$B$5:$B$217,0),MATCH(AA$1,'Pillar-3'!$A$4:$M$4,0)),"")) -> 22.9 | AB7: =IF($B7="","",IFERROR(INDEX('Pillar-4'!$A$5:$R$217,MATCH($B7,'Pillar-4'!$B$5:$B$217,0),MATCH(AB$1,'Pillar-4'!$A$4:$R$4,0)),"")) -> 47.3295 | AC7: =IF($B7="","",IFERROR(INDEX('Pillar-4'!$A$5:$R$217,MATCH($B7,'Pillar-4'!$B$5:$B$217,0),MATCH(AC$1,'Pillar-4'!$A$4:$R$4,0)),"")) -> 88.76267 | AD7: =IF($B7="","",IFERROR(INDEX('Pillar-4'!$A$5:$R$217,MATCH($B7,'Pillar-4'!$B$5:$B$217,0),MATCH(AD$1,'Pillar-4'!$A$4:$R$4,0)),"")) -> 85.97024 | AE7: =IF($B7="","",IFERROR(INDEX('Pillar-4'!$A$5:$R$217,MATCH($B7,'Pillar-4'!$B$5:$B$217,0),MATCH(AE$1,'Pillar-4'!$A$4:$R$4,0)),"")) -> 100 | AF7: =IF($B7="","",IFERROR(INDEX('Pillar-4'!$A$5:$R$217,MATCH($B7,'Pillar-4'!$B$5:$B$217,0),MATCH(AF$1,'Pillar-4'!$A$4:$R$4,0)),"")) -> 75 | AG7: =IF($B7="","",IFERROR(INDEX('Pillar-5'!$A$5:$Q$216,MATCH($B7,'Pillar-5'!$B$5:$B$216,0),MATCH(AG$1,'Pillar-5'!$A$4:$Q$4,0)),"")) -> 62.329883 | AH7: =IF($B7="","",IFERROR(INDEX('Pillar-5'!$A$5:$Q$216,MATCH($B7,'Pillar-5'!$B$5:$B$216,0),MATCH(AH$1,'Pillar-5'!$A$4:$Q$4,0)),"")) -> 100 | AI7: =IF($B7="","",IFERROR(INDEX('Pillar-5'!$A$5:$Q$216,MATCH($B7,'Pillar-5'!$B$5:$B$216,0),MATCH(AI$1,'Pillar-5'!$A$4:$Q$4,0)),"")) -> 82.574667 | AJ7: =IF($B7="","",IFERROR(INDEX('Pillar-5'!$A$5:$Q$216,MATCH($B7,'Pillar-5'!$B$5:$B$216,0),MATCH(AJ$1,'Pillar-5'!$A$4:$Q$4,0)),"")) -> 97.07273 | AK7: =IF($B7="","",IFERROR(INDEX('Pillar-6'!$A$5:$Q$216,MATCH($B7,'Pillar-6'!$B$5:$B$216,0),MATCH(AK$1,'Pillar-6'!$A$4:$Q$4,0)),"")) -> 20 | AL7: =IF($B7="","",IFERROR(INDEX('Pillar-6'!$A$5:$Q$216,MATCH($B7,'Pillar-6'!$B$5:$B$216,0),MATCH(AL$1,'Pillar-6'!$A$4:$Q$4,0)),"")) -> 34.73 | AM7: =IF($B7="","",IFERROR(INDEX('Pillar-6'!$A$5:$Q$216,MATCH($B7,'Pillar-6'!$B$5:$B$216,0),MATCH(AM$1,'Pillar-6'!$A$4:$Q$4,0)),"")) -> 100
A8: Canada | B8: CAN | C8: =IF($B8="","",IFERROR(INDEX(Screening!$A$2:$R$219,MATCH($B8,Screening!$B$2:$B$219,0),MATCH("Include in final index",Screening!$A$1:$R$1,0)),"")) -> Yes | D8: =IF($B8="","",IFERROR(INDEX('INDEX ranked'!$A$3:$J$200,MATCH($B8,'INDEX ranked'!$B$3:$B$200,0),MATCH("Rank",'INDEX ranked'!$A$2:$J$2,0)),"")) -> 3 | E8: =IF($B8="","",IFERROR(INDEX('INDEX ranked'!$A$3:$J$200,MATCH($B8,'INDEX ranked'!$B$3:$B$200,0),MATCH("Overall index score",'INDEX ranked'!$A$2:$J$2,0)),"")) -> 66.630184 | F8: =IF($B8="","",IFERROR(INDEX('INDEX ranked'!$A$3:$J$200,MATCH($B8,'INDEX ranked'!$B$3:$B$200,0),MATCH(F$1,'INDEX ranked'!$A$2:$J$2,0)),"")) -> 66.642502 | G8: =IF($B8="","",IFERROR(INDEX('INDEX ranked'!$A$3:$J$200,MATCH($B8,'INDEX ranked'!$B$3:$B$200,0),MATCH(G$1,'INDEX ranked'!$A$2:$J$2,0)),"")) -> 61.782231 | H8: =IF($B8="","",IFERROR(INDEX('INDEX ranked'!$A$3:$J$200,MATCH($B8,'INDEX ranked'!$B$3:$B$200,0),MATCH(H$1,'INDEX ranked'!$A$2:$J$2,0)),"")) -> 80.6845 | I8: =IF($B8="","",IFERROR(INDEX('INDEX ranked'!$A$3:$J$200,MATCH($B8,'INDEX ranked'!$B$3:$B$200,0),MATCH(I$1,'INDEX ranked'!$A$2:$J$2,0)),"")) -> 45.087058 | J8: =IF($B8="","",IFERROR(INDEX('INDEX ranked'!$A$3:$J$200,MATCH($B8,'INDEX ranked'!$B$3:$B$200,0),MATCH(J$1,'INDEX ranked'!$A$2:$J$2,0)),"")) -> 79.666175 | K8: =IF($B8="","",IFERROR(INDEX('INDEX ranked'!$A$3:$J$200,MATCH($B8,'INDEX ranked'!$B$3:$B$200,0),MATCH(K$1,'INDEX ranked'!$A$2:$J$2,0)),"")) -> 78.75225 | L8: =IF($B8="","",IFERROR(INDEX('Pillar-1'!$A$5:$M$216,MATCH($B8,'Pillar-1'!$B$5:$B$216,0),MATCH(L$1,'Pillar-1'!$A$4:$M$4,0)),"")) -> 73.276162 | M8: =IF($B8="","",IFERROR(INDEX('Pillar-1'!$A$5:$M$216,MATCH($B8,'Pillar-1'!$B$5:$B$216,0),MATCH(M$1,'Pillar-1'!$A$4:$M$4,0)),"")) -> 19.986153 | N8: =IF($B8="","",IFERROR(INDEX('Pillar-1'!$A$5:$M$216,MATCH($B8,'Pillar-1'!$B$5:$B$216,0),MATCH(N$1,'Pillar-1'!$A$4:$M$4,0)),"")) -> 100 | O8: =IF($B8="","",IFERROR(INDEX('Pillar-2'!$A$5:$S$216,MATCH($B8,'Pillar-2'!$B$5:$B$216,0),MATCH(O$1,'Pillar-2'!$A$4:$S$4,0)),"")) -> 33.648148 | P8: =IF($B8="","",IFERROR(INDEX('Pillar-2'!$A$5:$S$216,MATCH($B8,'Pillar-2'!$B$5:$B$216,0),MATCH(P$1,'Pillar-2'!$A$4:$S$4,0)),"")) -> 100 | Q8: =IF($B8="","",IFERROR(INDEX('Pillar-2'!$A$5:$S$216,MATCH($B8,'Pillar-2'!$B$5:$B$216,0),MATCH(Q$1,'Pillar-2'!$A$4:$S$4,0)),"")) -> 100 | R8: =IF($B8="","",IFERROR(INDEX('Pillar-2'!$A$5:$S$216,MATCH($B8,'Pillar-2'!$B$5:$B$216,0),MATCH(R$1,'Pillar-2'!$A$4:$S$4,0)),"")) -> 54.281003 | S8: =IF($B8="","",IFERROR(INDEX('Pillar-2'!$A$5:$S$216,MATCH($B8,'Pillar-2'!$B$5:$B$216,0),MATCH(S$1,'Pillar-2'!$A$4:$S$4,0)),"")) -> 0.43355426 | T8: =IF($B8="","",IFERROR(INDEX('Pillar-2'!$A$5:$S$216,MATCH($B8,'Pillar-2'!$B$5:$B$216,0),MATCH(T$1,'Pillar-2'!$A$4:$S$4,0)),"")) -> 2.2338233 | U8: =IF($B8="","",IFERROR(INDEX('Pillar-2'!$A$5:$S$216,MATCH($B8,'Pillar-2'!$B$5:$B$216,0),MATCH(U$1,'Pillar-2'!$A$4:$S$4,0)),"")) -> 100 | V8: =IF($B8="","",IFERROR(INDEX('Pillar-2'!$A$5:$S$216,MATCH($B8,'Pillar-2'!$B$5:$B$216,0),MATCH(V$1,'Pillar-2'!$A$4:$S$4,0)),"")) -> 75 | W8: =IF($B8="","",IFERROR(INDEX('Pillar-3'!$A$5:$M$217,MATCH($B8,'Pillar-3'!$B$5:$B$217,0),MATCH(W$1,'Pillar-3'!$A$4:$M$4,0)),"")) -> 76.12 | X8: =IF($B8="","",IFERROR(INDEX('Pillar-3'!$A$5:$M$217,MATCH($B8,'Pillar-3'!$B$5:$B$217,0),MATCH(X$1,'Pillar-3'!$A$4:$M$4,0)),"")) -> 85.54 | Y8: =IF($B8="","",IFERROR(INDEX('Pillar-3'!$A$5:$M$217,MATCH($B8,'Pillar-3'!$B$5:$B$217,0),MATCH(Y$1,'Pillar-3'!$A$4:$M$4,0)),"")) -> 76.35 | Z8: =IF($B8="","",IFERROR(INDEX('Pillar-3'!$A$5:$M$217,MATCH($B8,'Pillar-3'!$B$5:$B$217,0),MATCH(Z$1,'Pillar-3'!$A$4:$M$4,0)),"")) -> 82.11 | AA8: =IF($B8="","",IFERROR(INDEX('Pillar-3'!$A$5:$M$217,MATCH($B8,'Pillar-3'!$B$5:$B$217,0),MATCH(AA$1,'Pillar-3'!$A$4:$M$4,0)),"")) -> 80.89 | AB8: =IF($B8="","",IFERROR(INDEX('Pillar-4'!$A$5:$R$217,MATCH($B8,'Pillar-4'!$B$5:$B$217,0),MATCH(AB$1,'Pillar-4'!$A$4:$R$4,0)),"")) -> 54.264331 | AC8: =IF($B8="","",IFERROR(INDEX('Pillar-4'!$A$5:$R$217,MATCH($B8,'Pillar-4'!$B$5:$B$217,0),MATCH(AC$1,'Pillar-4'!$A$4:$R$4,0)),"")) -> 81.013002 | AD8: =IF($B8="","",IFERROR(INDEX('Pillar-4'!$A$5:$R$217,MATCH($B8,'Pillar-4'!$B$5:$B$217,0),MATCH(AD$1,'Pillar-4'!$A$4:$R$4,0)),"")) -> 78.543942 | AE8: =IF($B8="","",IFERROR(INDEX('Pillar-4'!$A$5:$R$217,MATCH($B8,'Pillar-4'!$B$5:$B$217,0),MATCH(AE$1,'Pillar-4'!$A$4:$R$4,0)),"")) -> 0 | AF8: =IF($B8="","",IFERROR(INDEX('Pillar-4'!$A$5:$R$217,MATCH($B8,'Pillar-4'!$B$5:$B$217,0),MATCH(AF$1,'Pillar-4'!$A$4:$R$4,0)),"")) -> 25 | AG8: =IF($B8="","",IFERROR(INDEX('Pillar-5'!$A$5:$Q$216,MATCH($B8,'Pillar-5'!$B$5:$B$216,0),MATCH(AG$1,'Pillar-5'!$A$4:$Q$4,0)),"")) -> 100 | AH8: =IF($B8="","",IFERROR(INDEX('Pillar-5'!$A$5:$Q$216,MATCH($B8,'Pillar-5'!$B$5:$B$216,0),MATCH(AH$1,'Pillar-5'!$A$4:$Q$4,0)),"")) -> 100 | AI8: =IF($B8="","",IFERROR(INDEX('Pillar-5'!$A$5:$Q$216,MATCH($B8,'Pillar-5'!$B$5:$B$216,0),MATCH(AI$1,'Pillar-5'!$A$4:$Q$4,0)),"")) -> 26.654 | AJ8: =IF($B8="","",IFERROR(INDEX('Pillar-5'!$A$5:$Q$216,MATCH($B8,'Pillar-5'!$B$5:$B$216,0),MATCH(AJ$1,'Pillar-5'!$A$4:$Q$4,0)),"")) -> 77.341501 | AK8: =IF($B8="","",IFERROR(INDEX('Pillar-6'!$A$5:$Q$216,MATCH($B8,'Pillar-6'!$B$5:$B$216,0),MATCH(AK$1,'Pillar-6'!$A$4:$Q$4,0)),"")) -> 60 | AL8: =IF($B8="","",IFERROR(INDEX('Pillar-6'!$A$5:$Q$216,MATCH($B8,'Pillar-6'!$B$5:$B$216,0),MATCH(AL$1,'Pillar-6'!$A$4:$Q$4,0)),"")) -> 95.005 | AM8: =IF($B8="","",IFERROR(INDEX('Pillar-6'!$A$5:$Q$216,MATCH($B8,'Pillar-6'!$B$5:$B$216,0),MATCH(AM$1,'Pillar-6'!$A$4:$Q$4,0)),"")) -> 75
A9: Chile | B9: CHL | C9: =IF($B9="","",IFERROR(INDEX(Screening!$A$2:$R$219,MATCH($B9,Screening!$B$2:$B$219,0),MATCH("Include in final index",Screening!$A$1:$R$1,0)),"")) -> Yes | D9: =IF($B9="","",IFERROR(INDEX('INDEX ranked'!$A$3:$J$200,MATCH($B9,'INDEX ranked'!$B$3:$B$200,0),MATCH("Rank",'INDEX ranked'!$A$2:$J$2,0)),"")) -> 1 | E9: =IF($B9="","",IFERROR(INDEX('INDEX ranked'!$A$3:$J$200,MATCH($B9,'INDEX ranked'!$B$3:$B$200,0),MATCH("Overall index score",'INDEX ranked'!$A$2:$J$2,0)),"")) -> 76.456821 | F9: =IF($B9="","",IFERROR(INDEX('INDEX ranked'!$A$3:$J$200,MATCH($B9,'INDEX ranked'!$B$3:$B$200,0),MATCH(F$1,'INDEX ranked'!$A$2:$J$2,0)),"")) -> 84.124011 | G9: =IF($B9="","",IFERROR(INDEX('INDEX ranked'!$A$3:$J$200,MATCH($B9,'INDEX ranked'!$B$3:$B$200,0),MATCH(G$1,'INDEX ranked'!$A$2:$J$2,0)),"")) -> 96.046667 | H9: =IF($B9="","",IFERROR(INDEX('INDEX ranked'!$A$3:$J$200,MATCH($B9,'INDEX ranked'!$B$3:$B$200,0),MATCH(H$1,'INDEX ranked'!$A$2:$J$2,0)),"")) -> 68.9345 | I9: =IF($B9="","",IFERROR(INDEX('INDEX ranked'!$A$3:$J$200,MATCH($B9,'INDEX ranked'!$B$3:$B$200,0),MATCH(I$1,'INDEX ranked'!$A$2:$J$2,0)),"")) -> 66.186105 | J9: =IF($B9="","",IFERROR(INDEX('INDEX ranked'!$A$3:$J$200,MATCH($B9,'INDEX ranked'!$B$3:$B$200,0),MATCH(J$1,'INDEX ranked'!$A$2:$J$2,0)),"")) -> 64.399427 | K9: =IF($B9="","",IFERROR(INDEX('INDEX ranked'!$A$3:$J$200,MATCH($B9,'INDEX ranked'!$B$3:$B$200,0),MATCH(K$1,'INDEX ranked'!$A$2:$J$2,0)),"")) -> 71.85375 | L9: =IF($B9="","",IFERROR(INDEX('Pillar-1'!$A$5:$M$216,MATCH($B9,'Pillar-1'!$B$5:$B$216,0),MATCH(L$1,'Pillar-1'!$A$4:$M$4,0)),"")) -> 79.962916 | M9: =IF($B9="","",IFERROR(INDEX('Pillar-1'!$A$5:$M$216,MATCH($B9,'Pillar-1'!$B$5:$B$216,0),MATCH(M$1,'Pillar-1'!$A$4:$M$4,0)),"")) -> 79.344565 | N9: =IF($B9="","",IFERROR(INDEX('Pillar-1'!$A$5:$M$216,MATCH($B9,'Pillar-1'!$B$5:$B$216,0),MATCH(N$1,'Pillar-1'!$A$4:$M$4,0)),"")) -> 92.381775 | O9: =IF($B9="","",IFERROR(INDEX('Pillar-2'!$A$5:$S$216,MATCH($B9,'Pillar-2'!$B$5:$B$216,0),MATCH(O$1,'Pillar-2'!$A$4:$S$4,0)),"")) -> 67.055556 | P9: =IF($B9="","",IFERROR(INDEX('Pillar-2'!$A$5:$S$216,MATCH($B9,'Pillar-2'!$B$5:$B$216,0),MATCH(P$1,'Pillar-2'!$A$4:$S$4,0)),"")) -> 100 | Q9: =IF($B9="","",IFERROR(INDEX('Pillar-2'!$A$5:$S$216,MATCH($B9,'Pillar-2'!$B$5:$B$216,0),MATCH(Q$1,'Pillar-2'!$A$4:$S$4,0)),"")) -> 100 | R9: =IF($B9="","",IFERROR(INDEX('Pillar-2'!$A$5:$S$216,MATCH($B9,'Pillar-2'!$B$5:$B$216,0),MATCH(R$1,'Pillar-2'!$A$4:$S$4,0)),"")) -> 100 | S9: =IF($B9="","",IFERROR(INDEX('Pillar-2'!$A$5:$S$216,MATCH($B9,'Pillar-2'!$B$5:$B$216,0),MATCH(S$1,'Pillar-2'!$A$4:$S$4,0)),"")) -> 100 | T9: =IF($B9="","",IFERROR(INDEX('Pillar-2'!$A$5:$S$216,MATCH($B9,'Pillar-2'!$B$5:$B$216,0),MATCH(T$1,'Pillar-2'!$A$4:$S$4,0)),"")) -> 100 | U9: =IF($B9="","",IFERROR(INDEX('Pillar-2'!$A$5:$S$216,MATCH($B9,'Pillar-2'!$B$5:$B$216,0),MATCH(U$1,'Pillar-2'!$A$4:$S$4,0)),"")) -> 100 | V9: =IF($B9="","",IFERROR(INDEX('Pillar-2'!$A$5:$S$216,MATCH($B9,'Pillar-2'!$B$5:$B$216,0),MATCH(V$1,'Pillar-2'!$A$4:$S$4,0)),"")) -> 100 | W9: =IF($B9="","",IFERROR(INDEX('Pillar-3'!$A$5:$M$217,MATCH($B9,'Pillar-3'!$B$5:$B$217,0),MATCH(W$1,'Pillar-3'!$A$4:$M$4,0)),"")) -> 67.97 | X9: =IF($B9="","",IFERROR(INDEX('Pillar-3'!$A$5:$M$217,MATCH($B9,'Pillar-3'!$B$5:$B$217,0),MATCH(X$1,'Pillar-3'!$A$4:$M$4,0)),"")) -> 70.09 | Y9: =IF($B9="","",IFERROR(INDEX('Pillar-3'!$A$5:$M$217,MATCH($B9,'Pillar-3'!$B$5:$B$217,0),MATCH(Y$1,'Pillar-3'!$A$4:$M$4,0)),"")) -> 67.18 | Z9: =IF($B9="","",IFERROR(INDEX('Pillar-3'!$A$5:$M$217,MATCH($B9,'Pillar-3'!$B$5:$B$217,0),MATCH(Z$1,'Pillar-3'!$A$4:$M$4,0)),"")) -> 68.86 | AA9: =IF($B9="","",IFERROR(INDEX('Pillar-3'!$A$5:$M$217,MATCH($B9,'Pillar-3'!$B$5:$B$217,0),MATCH(AA$1,'Pillar-3'!$A$4:$M$4,0)),"")) -> 70.24 | AB9: =IF($B9="","",IFERROR(INDEX('Pillar-4'!$A$5:$R$217,MATCH($B9,'Pillar-4'!$B$5:$B$217,0),MATCH(AB$1,'Pillar-4'!$A$4:$R$4,0)),"")) -> 49.170963 | AC9: =IF($B9="","",IFERROR(INDEX('Pillar-4'!$A$5:$R$217,MATCH($B9,'Pillar-4'!$B$5:$B$217,0),MATCH(AC$1,'Pillar-4'!$A$4:$R$4,0)),"")) -> 79.591755 | AD9: =IF($B9="","",IFERROR(INDEX('Pillar-4'!$A$5:$R$217,MATCH($B9,'Pillar-4'!$B$5:$B$217,0),MATCH(AD$1,'Pillar-4'!$A$4:$R$4,0)),"")) -> 79.557076 | AE9: =IF($B9="","",IFERROR(INDEX('Pillar-4'!$A$5:$R$217,MATCH($B9,'Pillar-4'!$B$5:$B$217,0),MATCH(AE$1,'Pillar-4'!$A$4:$R$4,0)),"")) -> 80 | AF9: =IF($B9="","",IFERROR(INDEX('Pillar-4'!$A$5:$R$217,MATCH($B9,'Pillar-4'!$B$5:$B$217,0),MATCH(AF$1,'Pillar-4'!$A$4:$R$4,0)),"")) -> 50 | AG9: =IF($B9="","",IFERROR(INDEX('Pillar-5'!$A$5:$Q$216,MATCH($B9,'Pillar-5'!$B$5:$B$216,0),MATCH(AG$1,'Pillar-5'!$A$4:$Q$4,0)),"")) -> 52.021918 | AH9: =IF($B9="","",IFERROR(INDEX('Pillar-5'!$A$5:$Q$216,MATCH($B9,'Pillar-5'!$B$5:$B$216,0),MATCH(AH$1,'Pillar-5'!$A$4:$Q$4,0)),"")) -> 100 | AI9: =IF($B9="","",IFERROR(INDEX('Pillar-5'!$A$5:$Q$216,MATCH($B9,'Pillar-5'!$B$5:$B$216,0),MATCH(AI$1,'Pillar-5'!$A$4:$Q$4,0)),"")) -> 72.233333 | AJ9: =IF($B9="","",IFERROR(INDEX('Pillar-5'!$A$5:$Q$216,MATCH($B9,'Pillar-5'!$B$5:$B$216,0),MATCH(AJ$1,'Pillar-5'!$A$4:$Q$4,0)),"")) -> 37.384738 | AK9: =IF($B9="","",IFERROR(INDEX('Pillar-6'!$A$5:$Q$216,MATCH($B9,'Pillar-6'!$B$5:$B$216,0),MATCH(AK$1,'Pillar-6'!$A$4:$Q$4,0)),"")) -> 60 | AL9: =IF($B9="","",IFERROR(INDEX('Pillar-6'!$A$5:$Q$216,MATCH($B9,'Pillar-6'!$B$5:$B$216,0),MATCH(AL$1,'Pillar-6'!$A$4:$Q$4,0)),"")) -> 79.675 | AM9: =IF($B9="","",IFERROR(INDEX('Pillar-6'!$A$5:$Q$216,MATCH($B9,'Pillar-6'!$B$5:$B$216,0),MATCH(AM$1,'Pillar-6'!$A$4:$Q$4,0)),"")) -> 75
A10: China | B10: CHN | C10: =IF($B10="","",IFERROR(INDEX(Screening!$A$2:$R$219,MATCH($B10,Screening!$B$2:$B$219,0),MATCH("Include in final index",Screening!$A$1:$R$1,0)),"")) -> Yes | D10: =IF($B10="","",IFERROR(INDEX('INDEX ranked'!$A$3:$J$200,MATCH($B10,'INDEX ranked'!$B$3:$B$200,0),MATCH("Rank",'INDEX ranked'!$A$2:$J$2,0)),"")) -> 13 | E10: =IF($B10="","",IFERROR(INDEX('INDEX ranked'!$A$3:$J$200,MATCH($B10,'INDEX ranked'!$B$3:$B$200,0),MATCH("Overall index score",'INDEX ranked'!$A$2:$J$2,0)),"")) -> 56.080555 | F10: =IF($B10="","",IFERROR(INDEX('INDEX ranked'!$A$3:$J$200,MATCH($B10,'INDEX ranked'!$B$3:$B$200,0),MATCH(F$1,'INDEX ranked'!$A$2:$J$2,0)),"")) -> 38.100942 | G10: =IF($B10="","",IFERROR(INDEX('INDEX ranked'!$A$3:$J$200,MATCH($B10,'INDEX ranked'!$B$3:$B$200,0),MATCH(G$1,'INDEX ranked'!$A$2:$J$2,0)),"")) -> 43.783305 | H10: =IF($B10="","",IFERROR(INDEX('INDEX ranked'!$A$3:$J$200,MATCH($B10,'INDEX ranked'!$B$3:$B$200,0),MATCH(H$1,'INDEX ranked'!$A$2:$J$2,0)),"")) -> 56.281 | I10: =IF($B10="","",IFERROR(INDEX('INDEX ranked'!$A$3:$J$200,MATCH($B10,'INDEX ranked'!$B$3:$B$200,0),MATCH(I$1,'INDEX ranked'!$A$2:$J$2,0)),"")) -> 63.496375 | J10: =IF($B10="","",IFERROR(INDEX('INDEX ranked'!$A$3:$J$200,MATCH($B10,'INDEX ranked'!$B$3:$B$200,0),MATCH(J$1,'INDEX ranked'!$A$2:$J$2,0)),"")) -> 80.979037 | K10: =IF($B10="","",IFERROR(INDEX('INDEX ranked'!$A$3:$J$200,MATCH($B10,'INDEX ranked'!$B$3:$B$200,0),MATCH(K$1,'INDEX ranked'!$A$2:$J$2,0)),"")) -> 64.15425 | L10: =IF($B10="","",IFERROR(INDEX('Pillar-1'!$A$5:$M$216,MATCH($B10,'Pillar-1'!$B$5:$B$216,0),MATCH(L$1,'Pillar-1'!$A$4:$M$4,0)),"")) -> 37.849113 | M10: =IF($B10="","",IFERROR(INDEX('Pillar-1'!$A$5:$M$216,MATCH($B10,'Pillar-1'!$B$5:$B$216,0),MATCH(M$1,'Pillar-1'!$A$4:$M$4,0)),"")) -> 41.610893 | N10: =IF($B10="","",IFERROR(INDEX('Pillar-1'!$A$5:$M$216,MATCH($B10,'Pillar-1'!$B$5:$B$216,0),MATCH(N$1,'Pillar-1'!$A$4:$M$4,0)),"")) -> 35.344241 | O10: =IF($B10="","",IFERROR(INDEX('Pillar-2'!$A$5:$S$216,MATCH($B10,'Pillar-2'!$B$5:$B$216,0),MATCH(O$1,'Pillar-2'!$A$4:$S$4,0)),"")) -> 58.410053 | P10: =IF($B10="","",IFERROR(INDEX('Pillar-2'!$A$5:$S$216,MATCH($B10,'Pillar-2'!$B$5:$B$216,0),MATCH(P$1,'Pillar-2'!$A$4:$S$4,0)),"")) -> 75.679682 | Q10: =IF($B10="","",IFERROR(INDEX('Pillar-2'!$A$5:$S$216,MATCH($B10,'Pillar-2'!$B$5:$B$216,0),MATCH(Q$1,'Pillar-2'!$A$4:$S$4,0)),"")) -> 8.6092234 | R10: =IF($B10="","",IFERROR(INDEX('Pillar-2'!$A$5:$S$216,MATCH($B10,'Pillar-2'!$B$5:$B$216,0),MATCH(R$1,'Pillar-2'!$A$4:$S$4,0)),"")) -> 62.515689 | S10: =IF($B10="","",IFERROR(INDEX('Pillar-2'!$A$5:$S$216,MATCH($B10,'Pillar-2'!$B$5:$B$216,0),MATCH(S$1,'Pillar-2'!$A$4:$S$4,0)),"")) -> 36.688641 | T10: =IF($B10="","",IFERROR(INDEX('Pillar-2'!$A$5:$S$216,MATCH($B10,'Pillar-2'!$B$5:$B$216,0),MATCH(T$1,'Pillar-2'!$A$4:$S$4,0)),"")) -> 46.596542 | U10: =IF($B10="","",IFERROR(INDEX('Pillar-2'!$A$5:$S$216,MATCH($B10,'Pillar-2'!$B$5:$B$216,0),MATCH(U$1,'Pillar-2'!$A$4:$S$4,0)),"")) -> 100 | V10: =IF($B10="","",IFERROR(INDEX('Pillar-2'!$A$5:$S$216,MATCH($B10,'Pillar-2'!$B$5:$B$216,0),MATCH(V$1,'Pillar-2'!$A$4:$S$4,0)),"")) -> 0 | W10: =IF($B10="","",IFERROR(INDEX('Pillar-3'!$A$5:$M$217,MATCH($B10,'Pillar-3'!$B$5:$B$217,0),MATCH(W$1,'Pillar-3'!$A$4:$M$4,0)),"")) -> 63.28 | X10: =IF($B10="","",IFERROR(INDEX('Pillar-3'!$A$5:$M$217,MATCH($B10,'Pillar-3'!$B$5:$B$217,0),MATCH(X$1,'Pillar-3'!$A$4:$M$4,0)),"")) -> 68.76 | Y10: =IF($B10="","",IFERROR(INDEX('Pillar-3'!$A$5:$M$217,MATCH($B10,'Pillar-3'!$B$5:$B$217,0),MATCH(Y$1,'Pillar-3'!$A$4:$M$4,0)),"")) -> 53.74 | Z10: =IF($B10="","",IFERROR(INDEX('Pillar-3'!$A$5:$M$217,MATCH($B10,'Pillar-3'!$B$5:$B$217,0),MATCH(Z$1,'Pillar-3'!$A$4:$M$4,0)),"")) -> 46.99 | AA10: =IF($B10="","",IFERROR(INDEX('Pillar-3'!$A$5:$M$217,MATCH($B10,'Pillar-3'!$B$5:$B$217,0),MATCH(AA$1,'Pillar-3'!$A$4:$M$4,0)),"")) -> 49.65 | AB10: =IF($B10="","",IFERROR(INDEX('Pillar-4'!$A$5:$R$217,MATCH($B10,'Pillar-4'!$B$5:$B$217,0),MATCH(AB$1,'Pillar-4'!$A$4:$R$4,0)),"")) -> 98.244506 | AC10: =IF($B10="","",IFERROR(INDEX('Pillar-4'!$A$5:$R$217,MATCH($B10,'Pillar-4'!$B$5:$B$217,0),MATCH(AC$1,'Pillar-4'!$A$4:$R$4,0)),"")) -> 96.462949 | AD10: =IF($B10="","",IFERROR(INDEX('Pillar-4'!$A$5:$R$217,MATCH($B10,'Pillar-4'!$B$5:$B$217,0),MATCH(AD$1,'Pillar-4'!$A$4:$R$4,0)),"")) -> 95.365892 | AE10: =IF($B10="","",IFERROR(INDEX('Pillar-4'!$A$5:$R$217,MATCH($B10,'Pillar-4'!$B$5:$B$217,0),MATCH(AE$1,'Pillar-4'!$A$4:$R$4,0)),"")) -> 20 | AF10: =IF($B10="","",IFERROR(INDEX('Pillar-4'!$A$5:$R$217,MATCH($B10,'Pillar-4'!$B$5:$B$217,0),MATCH(AF$1,'Pillar-4'!$A$4:$R$4,0)),"")) -> 25 | AG10: =IF($B10="","",IFERROR(INDEX('Pillar-5'!$A$5:$Q$216,MATCH($B10,'Pillar-5'!$B$5:$B$216,0),MATCH(AG$1,'Pillar-5'!$A$4:$Q$4,0)),"")) -> 97.082998 | AH10: =IF($B10="","",IFERROR(INDEX('Pillar-5'!$A$5:$Q$216,MATCH($B10,'Pillar-5'!$B$5:$B$216,0),MATCH(AH$1,'Pillar-5'!$A$4:$Q$4,0)),"")) -> 100 | AI10: =IF($B10="","",IFERROR(INDEX('Pillar-5'!$A$5:$Q$216,MATCH($B10,'Pillar-5'!$B$5:$B$216,0),MATCH(AI$1,'Pillar-5'!$A$4:$Q$4,0)),"")) -> 39.719333 | AJ10: =IF($B10="","",IFERROR(INDEX('Pillar-5'!$A$5:$Q$216,MATCH($B10,'Pillar-5'!$B$5:$B$216,0),MATCH(AJ$1,'Pillar-5'!$A$4:$Q$4,0)),"")) -> 75.641082 | AK10: =IF($B10="","",IFERROR(INDEX('Pillar-6'!$A$5:$Q$216,MATCH($B10,'Pillar-6'!$B$5:$B$216,0),MATCH(AK$1,'Pillar-6'!$A$4:$Q$4,0)),"")) -> 20 | AL10: =IF($B10="","",IFERROR(INDEX('Pillar-6'!$A$5:$Q$216,MATCH($B10,'Pillar-6'!$B$5:$B$216,0),MATCH(AL$1,'Pillar-6'!$A$4:$Q$4,0)),"")) -> 82.565 | AM10: =IF($B10="","",IFERROR(INDEX('Pillar-6'!$A$5:$Q$216,MATCH($B10,'Pillar-6'!$B$5:$B$216,0),MATCH(AM$1,'Pillar-6'!$A$4:$Q$4,0)),"")) -> 100
A11: Czech Republic | B11: CZE | C11: =IF($B11="","",IFERROR(INDEX(Screening!$A$2:$R$219,MATCH($B11,Screening!$B$2:$B$219,0),MATCH("Include in final index",Screening!$A$1:$R$1,0)),"")) -> Yes | D11: =IF($B11="","",IFERROR(INDEX('INDEX ranked'!$A$3:$J$200,MATCH($B11,'INDEX ranked'!$B$3:$B$200,0),MATCH("Rank",'INDEX ranked'!$A$2:$J$2,0)),"")) -> 19 | E11: =IF($B11="","",IFERROR(INDEX('INDEX ranked'!$A$3:$J$200,MATCH($B11,'INDEX ranked'!$B$3:$B$200,0),MATCH("Overall index score",'INDEX ranked'!$A$2:$J$2,0)),"")) -> 51.304522 | F11: =IF($B11="","",IFERROR(INDEX('INDEX ranked'!$A$3:$J$200,MATCH($B11,'INDEX ranked'!$B$3:$B$200,0),MATCH(F$1,'INDEX ranked'!$A$2:$J$2,0)),"")) -> 32.268071 | G11: =IF($B11="","",IFERROR(INDEX('INDEX ranked'!$A$3:$J$200,MATCH($B11,'INDEX ranked'!$B$3:$B$200,0),MATCH(G$1,'INDEX ranked'!$A$2:$J$2,0)),"")) -> 74.69426 | H11: =IF($B11="","",IFERROR(INDEX('INDEX ranked'!$A$3:$J$200,MATCH($B11,'INDEX ranked'!$B$3:$B$200,0),MATCH(H$1,'INDEX ranked'!$A$2:$J$2,0)),"")) -> 74.202 | I11: =IF($B11="","",IFERROR(INDEX('INDEX ranked'!$A$3:$J$200,MATCH($B11,'INDEX ranked'!$B$3:$B$200,0),MATCH(I$1,'INDEX ranked'!$A$2:$J$2,0)),"")) -> 4 | J11: =IF($B11="","",IFERROR(INDEX('INDEX ranked'!$A$3:$J$200,MATCH($B11,'INDEX ranked'!$B$3:$B$200,0),MATCH(J$1,'INDEX ranked'!$A$2:$J$2,0)),"")) -> 62.885372 | K11: =IF($B11="","",IFERROR(INDEX('INDEX ranked'!$A$3:$J$200,MATCH($B11,'INDEX ranked'!$B$3:$B$200,0),MATCH(K$1,'INDEX ranked'!$A$2:$J$2,0)),"")) -> 85.4895 | L11: =IF($B11="","",IFERROR(INDEX('Pillar-1'!$A$5:$M$216,MATCH($B11,'Pillar-1'!$B$5:$B$216,0),MATCH(L$1,'Pillar-1'!$A$4:$M$4,0)),"")) -> 18.368293 | M11: =IF($B11="","",IFERROR(INDEX('Pillar-1'!$A$5:$M$216,MATCH($B11,'Pillar-1'!$B$5:$B$216,0),MATCH(M$1,'Pillar-1'!$A$4:$M$4,0)),"")) -> 13.108701 | N11: =IF($B11="","",IFERROR(INDEX('Pillar-1'!$A$5:$M$216,MATCH($B11,'Pillar-1'!$B$5:$B$216,0),MATCH(N$1,'Pillar-1'!$A$4:$M$4,0)),"")) -> 62.590168 | O11: =IF($B11="","",IFERROR(INDEX('Pillar-2'!$A$5:$S$216,MATCH($B11,'Pillar-2'!$B$5:$B$216,0),MATCH(O$1,'Pillar-2'!$A$4:$S$4,0)),"")) -> 77.703704 | P11: =IF($B11="","",IFERROR(INDEX('Pillar-2'!$A$5:$S$216,MATCH($B11,'Pillar-2'!$B$5:$B$216,0),MATCH(P$1,'Pillar-2'!$A$4:$S$4,0)),"")) -> 100 | Q11: =IF($B11="","",IFERROR(INDEX('Pillar-2'!$A$5:$S$216,MATCH($B11,'Pillar-2'!$B$5:$B$216,0),MATCH(Q$1,'Pillar-2'!$A$4:$S$4,0)),"")) -> 100 | R11: =IF($B11="","",IFERROR(INDEX('Pillar-2'!$A$5:$S$216,MATCH($B11,'Pillar-2'!$B$5:$B$216,0),MATCH(R$1,'Pillar-2'!$A$4:$S$4,0)),"")) -> 55.984052 | S11: =IF($B11="","",IFERROR(INDEX('Pillar-2'!$A$5:$S$216,MATCH($B11,'Pillar-2'!$B$5:$B$216,0),MATCH(S$1,'Pillar-2'!$A$4:$S$4,0)),"")) -> 28.131275 | T11: =IF($B11="","",IFERROR(INDEX('Pillar-2'!$A$5:$S$216,MATCH($B11,'Pillar-2'!$B$5:$B$216,0),MATCH(T$1,'Pillar-2'!$A$4:$S$4,0)),"")) -> 53.449699 | U11: =IF($B11="","",IFERROR(INDEX('Pillar-2'!$A$5:$S$216,MATCH($B11,'Pillar-2'!$B$5:$B$216,0),MATCH(U$1,'Pillar-2'!$A$4:$S$4,0)),"")) -> 100 | V11: =IF($B11="","",IFERROR(INDEX('Pillar-2'!$A$5:$S$216,MATCH($B11,'Pillar-2'!$B$5:$B$216,0),MATCH(V$1,'Pillar-2'!$A$4:$S$4,0)),"")) -> 75 | W11: =IF($B11="","",IFERROR(INDEX('Pillar-3'!$A$5:$M$217,MATCH($B11,'Pillar-3'!$B$5:$B$217,0),MATCH(W$1,'Pillar-3'!$A$4:$M$4,0)),"")) -> 82.5 | X11: =IF($B11="","",IFERROR(INDEX('Pillar-3'!$A$5:$M$217,MATCH($B11,'Pillar-3'!$B$5:$B$217,0),MATCH(X$1,'Pillar-3'!$A$4:$M$4,0)),"")) -> 74.23 | Y11: =IF($B11="","",IFERROR(INDEX('Pillar-3'!$A$5:$M$217,MATCH($B11,'Pillar-3'!$B$5:$B$217,0),MATCH(Y$1,'Pillar-3'!$A$4:$M$4,0)),"")) -> 74.29 | Z11: =IF($B11="","",IFERROR(INDEX('Pillar-3'!$A$5:$M$217,MATCH($B11,'Pillar-3'!$B$5:$B$217,0),MATCH(Z$1,'Pillar-3'!$A$4:$M$4,0)),"")) -> 77.41 | AA11: =IF($B11="","",IFERROR(INDEX('Pillar-3'!$A$5:$M$217,MATCH($B11,'Pillar-3'!$B$5:$B$217,0),MATCH(AA$1,'Pillar-3'!$A$4:$M$4,0)),"")) -> 66.7 | AB11: =IF($B11="","",IFERROR(INDEX('Pillar-4'!$A$5:$R$217,MATCH($B11,'Pillar-4'!$B$5:$B$217,0),MATCH(AB$1,'Pillar-4'!$A$4:$R$4,0)),"")) -> 0 | AC11: =IF($B11="","",IFERROR(INDEX('Pillar-4'!$A$5:$R$217,MATCH($B11,'Pillar-4'!$B$5:$B$217,0),MATCH(AC$1,'Pillar-4'!$A$4:$R$4,0)),"")) -> 0 | AD11: =IF($B11="","",IFERROR(INDEX('Pillar-4'!$A$5:$R$217,MATCH($B11,'Pillar-4'!$B$5:$B$217,0),MATCH(AD$1,'Pillar-4'!$A$4:$R$4,0)),"")) -> 0 | AE11: =IF($B11="","",IFERROR(INDEX('Pillar-4'!$A$5:$R$217,MATCH($B11,'Pillar-4'!$B$5:$B$217,0),MATCH(AE$1,'Pillar-4'!$A$4:$R$4,0)),"")) -> 20 | AF11: =IF($B11="","",IFERROR(INDEX('Pillar-4'!$A$5:$R$217,MATCH($B11,'Pillar-4'!$B$5:$B$217,0),MATCH(AF$1,'Pillar-4'!$A$4:$R$4,0)),"")) -> 0 | AG11: =IF($B11="","",IFERROR(INDEX('Pillar-5'!$A$5:$Q$216,MATCH($B11,'Pillar-5'!$B$5:$B$216,0),MATCH(AG$1,'Pillar-5'!$A$4:$Q$4,0)),"")) -> 24.013688 | AH11: =IF($B11="","",IFERROR(INDEX('Pillar-5'!$A$5:$Q$216,MATCH($B11,'Pillar-5'!$B$5:$B$216,0),MATCH(AH$1,'Pillar-5'!$A$4:$Q$4,0)),"")) -> 100 | AI11: =IF($B11="","",IFERROR(INDEX('Pillar-5'!$A$5:$Q$216,MATCH($B11,'Pillar-5'!$B$5:$B$216,0),MATCH(AI$1,'Pillar-5'!$A$4:$Q$4,0)),"")) -> 71.139333 | AJ11: =IF($B11="","",IFERROR(INDEX('Pillar-5'!$A$5:$Q$216,MATCH($B11,'Pillar-5'!$B$5:$B$216,0),MATCH(AJ$1,'Pillar-5'!$A$4:$Q$4,0)),"")) -> 65.813597 | AK11: =IF($B11="","",IFERROR(INDEX('Pillar-6'!$A$5:$Q$216,MATCH($B11,'Pillar-6'!$B$5:$B$216,0),MATCH(AK$1,'Pillar-6'!$A$4:$Q$4,0)),"")) -> 80 | AL11: =IF($B11="","",IFERROR(INDEX('Pillar-6'!$A$5:$Q$216,MATCH($B11,'Pillar-6'!$B$5:$B$216,0),MATCH(AL$1,'Pillar-6'!$A$4:$Q$4,0)),"")) -> 83.31 | AM11: =IF($B11="","",IFERROR(INDEX('Pillar-6'!$A$5:$Q$216,MATCH($B11,'Pillar-6'!$B$5:$B$216,0),MATCH(AM$1,'Pillar-6'!$A$4:$Q$4,0)),"")) -> 100
A12: Dominican Republic | B12: DOM | C12: =IF($B12="","",IFERROR(INDEX(Screening!$A$2:$R$219,MATCH($B12,Screening!$B$2:$B$219,0),MATCH("Include in final index",Screening!$A$1:$R$1,0)),"")) -> Yes | D12: =IF($B12="","",IFERROR(INDEX('INDEX ranked'!$A$3:$J$200,MATCH($B12,'INDEX ranked'!$B$3:$B$200,0),MATCH("Rank",'INDEX ranked'!$A$2:$J$2,0)),"")) -> 27 | E12: =IF($B12="","",IFERROR(INDEX('INDEX ranked'!$A$3:$J$200,MATCH($B12,'INDEX ranked'!$B$3:$B$200,0),MATCH("Overall index score",'INDEX ranked'!$A$2:$J$2,0)),"")) -> 43.719635 | F12: =IF($B12="","",IFERROR(INDEX('INDEX ranked'!$A$3:$J$200,MATCH($B12,'INDEX ranked'!$B$3:$B$200,0),MATCH(F$1,'INDEX ranked'!$A$2:$J$2,0)),"")) -> 26.862616 | G12: =IF($B12="","",IFERROR(INDEX('INDEX ranked'!$A$3:$J$200,MATCH($B12,'INDEX ranked'!$B$3:$B$200,0),MATCH(G$1,'INDEX ranked'!$A$2:$J$2,0)),"")) -> 39.015957 | H12: =IF($B12="","",IFERROR(INDEX('INDEX ranked'!$A$3:$J$200,MATCH($B12,'INDEX ranked'!$B$3:$B$200,0),MATCH(H$1,'INDEX ranked'!$A$2:$J$2,0)),"")) -> 54.588 | I12: =IF($B12="","",IFERROR(INDEX('INDEX ranked'!$A$3:$J$200,MATCH($B12,'INDEX ranked'!$B$3:$B$200,0),MATCH(I$1,'INDEX ranked'!$A$2:$J$2,0)),"")) -> 30.75 | J12: =IF($B12="","",IFERROR(INDEX('INDEX ranked'!$A$3:$J$200,MATCH($B12,'INDEX ranked'!$B$3:$B$200,0),MATCH(J$1,'INDEX ranked'!$A$2:$J$2,0)),"")) -> 59.328467 | K12: =IF($B12="","",IFERROR(INDEX('INDEX ranked'!$A$3:$J$200,MATCH($B12,'INDEX ranked'!$B$3:$B$200,0),MATCH(K$1,'INDEX ranked'!$A$2:$J$2,0)),"")) -> 73.0645 | L12: =IF($B12="","",IFERROR(INDEX('Pillar-1'!$A$5:$M$216,MATCH($B12,'Pillar-1'!$B$5:$B$216,0),MATCH(L$1,'Pillar-1'!$A$4:$M$4,0)),"")) -> 20.639703 | M12: =IF($B12="","",IFERROR(INDEX('Pillar-1'!$A$5:$M$216,MATCH($B12,'Pillar-1'!$B$5:$B$216,0),MATCH(M$1,'Pillar-1'!$A$4:$M$4,0)),"")) -> 26.978998 | N12: =IF($B12="","",IFERROR(INDEX('Pillar-1'!$A$5:$M$216,MATCH($B12,'Pillar-1'!$B$5:$B$216,0),MATCH(N$1,'Pillar-1'!$A$4:$M$4,0)),"")) -> 32.985771 | O12: =IF($B12="","",IFERROR(INDEX('Pillar-2'!$A$5:$S$216,MATCH($B12,'Pillar-2'!$B$5:$B$216,0),MATCH(O$1,'Pillar-2'!$A$4:$S$4,0)),"")) -> 31.248677 | P12: =IF($B12="","",IFERROR(INDEX('Pillar-2'!$A$5:$S$216,MATCH($B12,'Pillar-2'!$B$5:$B$216,0),MATCH(P$1,'Pillar-2'!$A$4:$S$4,0)),"")) -> 100 | Q12: =IF($B12="","",IFERROR(INDEX('Pillar-2'!$A$5:$S$216,MATCH($B12,'Pillar-2'!$B$5:$B$216,0),MATCH(Q$1,'Pillar-2'!$A$4:$S$4,0)),"")) -> 100 | R12: =IF($B12="","",IFERROR(INDEX('Pillar-2'!$A$5:$S$216,MATCH($B12,'Pillar-2'!$B$5:$B$216,0),MATCH(R$1,'Pillar-2'!$A$4:$S$4,0)),"")) -> 4.7793665 | S12: =IF($B12="","",IFERROR(INDEX('Pillar-2'!$A$5:$S$216,MATCH($B12,'Pillar-2'!$B$5:$B$216,0),MATCH(S$1,'Pillar-2'!$A$4:$S$4,0)),"")) -> 31.166154 | T12: =IF($B12="","",IFERROR(INDEX('Pillar-2'!$A$5:$S$216,MATCH($B12,'Pillar-2'!$B$5:$B$216,0),MATCH(T$1,'Pillar-2'!$A$4:$S$4,0)),"")) -> 16.908171 | U12: =IF($B12="","",IFERROR(INDEX('Pillar-2'!$A$5:$S$216,MATCH($B12,'Pillar-2'!$B$5:$B$216,0),MATCH(U$1,'Pillar-2'!$A$4:$S$4,0)),"")) -> 20 | V12: =IF($B12="","",IFERROR(INDEX('Pillar-2'!$A$5:$S$216,MATCH($B12,'Pillar-2'!$B$5:$B$216,0),MATCH(V$1,'Pillar-2'!$A$4:$S$4,0)),"")) -> 0 | W12: =IF($B12="","",IFERROR(INDEX('Pillar-3'!$A$5:$M$217,MATCH($B12,'Pillar-3'!$B$5:$B$217,0),MATCH(W$1,'Pillar-3'!$A$4:$M$4,0)),"")) -> 75.96 | X12: =IF($B12="","",IFERROR(INDEX('Pillar-3'!$A$5:$M$217,MATCH($B12,'Pillar-3'!$B$5:$B$217,0),MATCH(X$1,'Pillar-3'!$A$4:$M$4,0)),"")) -> 52.79 | Y12: =IF($B12="","",IFERROR(INDEX('Pillar-3'!$A$5:$M$217,MATCH($B12,'Pillar-3'!$B$5:$B$217,0),MATCH(Y$1,'Pillar-3'!$A$4:$M$4,0)),"")) -> 58.13 | Z12: =IF($B12="","",IFERROR(INDEX('Pillar-3'!$A$5:$M$217,MATCH($B12,'Pillar-3'!$B$5:$B$217,0),MATCH(Z$1,'Pillar-3'!$A$4:$M$4,0)),"")) -> 53.83 | AA12: =IF($B12="","",IFERROR(INDEX('Pillar-3'!$A$5:$M$217,MATCH($B12,'Pillar-3'!$B$5:$B$217,0),MATCH(AA$1,'Pillar-3'!$A$4:$M$4,0)),"")) -> 42.48 | AB12: =IF($B12="","",IFERROR(INDEX('Pillar-4'!$A$5:$R$217,MATCH($B12,'Pillar-4'!$B$5:$B$217,0),MATCH(AB$1,'Pillar-4'!$A$4:$R$4,0)),"")) -> 0 | AC12: =IF($B12="","",IFERROR(INDEX('Pillar-4'!$A$5:$R$217,MATCH($B12,'Pillar-4'!$B$5:$B$217,0),MATCH(AC$1,'Pillar-4'!$A$4:$R$4,0)),"")) -> 0 | AD12: =IF($B12="","",IFERROR(INDEX('Pillar-4'!$A$5:$R$217,MATCH($B12,'Pillar-4'!$B$5:$B$217,0),MATCH(AD$1,'Pillar-4'!$A$4:$R$4,0)),"")) -> 0 | AE12: =IF($B12="","",IFERROR(INDEX('Pillar-4'!$A$5:$R$217,MATCH($B12,'Pillar-4'!$B$5:$B$217,0),MATCH(AE$1,'Pillar-4'!$A$4:$R$4,0)),"")) -> 60 | AF12: =IF($B12="","",IFERROR(INDEX('Pillar-4'!$A$5:$R$217,MATCH($B12,'Pillar-4'!$B$5:$B$217,0),MATCH(AF$1,'Pillar-4'!$A$4:$R$4,0)),"")) -> 75 | AG12: =IF($B12="","",IFERROR(INDEX('Pillar-5'!$A$5:$Q$216,MATCH($B12,'Pillar-5'!$B$5:$B$216,0),MATCH(AG$1,'Pillar-5'!$A$4:$Q$4,0)),"")) -> 15.961043 | AH12: =IF($B12="","",IFERROR(INDEX('Pillar-5'!$A$5:$Q$216,MATCH($B12,'Pillar-5'!$B$5:$B$216,0),MATCH(AH$1,'Pillar-5'!$A$4:$Q$4,0)),"")) -> 100 | AI12: =IF($B12="","",IFERROR(INDEX('Pillar-5'!$A$5:$Q$216,MATCH($B12,'Pillar-5'!$B$5:$B$216,0),MATCH(AI$1,'Pillar-5'!$A$4:$Q$4,0)),"")) -> 60.805333 | AJ12: =IF($B12="","",IFERROR(INDEX('Pillar-5'!$A$5:$Q$216,MATCH($B12,'Pillar-5'!$B$5:$B$216,0),MATCH(AJ$1,'Pillar-5'!$A$4:$Q$4,0)),"")) -> 69.51635 | AK12: =IF($B12="","",IFERROR(INDEX('Pillar-6'!$A$5:$Q$216,MATCH($B12,'Pillar-6'!$B$5:$B$216,0),MATCH(AK$1,'Pillar-6'!$A$4:$Q$4,0)),"")) -> 80 | AL12: =IF($B12="","",IFERROR(INDEX('Pillar-6'!$A$5:$Q$216,MATCH($B12,'Pillar-6'!$B$5:$B$216,0),MATCH(AL$1,'Pillar-6'!$A$4:$Q$4,0)),"")) -> 66.81 | AM12: =IF($B12="","",IFERROR(INDEX('Pillar-6'!$A$5:$Q$216,MATCH($B12,'Pillar-6'!$B$5:$B$216,0),MATCH(AM$1,'Pillar-6'!$A$4:$Q$4,0)),"")) -> 75
A13: Germany | B13: DEU | C13: =IF($B13="","",IFERROR(INDEX(Screening!$A$2:$R$219,MATCH($B13,Screening!$B$2:$B$219,0),MATCH("Include in final index",Screening!$A$1:$R$1,0)),"")) -> Yes | D13: =IF($B13="","",IFERROR(INDEX('INDEX ranked'!$A$3:$J$200,MATCH($B13,'INDEX ranked'!$B$3:$B$200,0),MATCH("Rank",'INDEX ranked'!$A$2:$J$2,0)),"")) -> 2 | E13: =IF($B13="","",IFERROR(INDEX('INDEX ranked'!$A$3:$J$200,MATCH($B13,'INDEX ranked'!$B$3:$B$200,0),MATCH("Overall index score",'INDEX ranked'!$A$2:$J$2,0)),"")) -> 75.33112 | F13: =IF($B13="","",IFERROR(INDEX('INDEX ranked'!$A$3:$J$200,MATCH($B13,'INDEX ranked'!$B$3:$B$200,0),MATCH(F$1,'INDEX ranked'!$A$2:$J$2,0)),"")) -> 80.528427 | G13: =IF($B13="","",IFERROR(INDEX('INDEX ranked'!$A$3:$J$200,MATCH($B13,'INDEX ranked'!$B$3:$B$200,0),MATCH(G$1,'INDEX ranked'!$A$2:$J$2,0)),"")) -> 87.144209 | H13: =IF($B13="","",IFERROR(INDEX('INDEX ranked'!$A$3:$J$200,MATCH($B13,'INDEX ranked'!$B$3:$B$200,0),MATCH(H$1,'INDEX ranked'!$A$2:$J$2,0)),"")) -> 80.517 | I13: =IF($B13="","",IFERROR(INDEX('INDEX ranked'!$A$3:$J$200,MATCH($B13,'INDEX ranked'!$B$3:$B$200,0),MATCH(I$1,'INDEX ranked'!$A$2:$J$2,0)),"")) -> 49.027601 | J13: =IF($B13="","",IFERROR(INDEX('INDEX ranked'!$A$3:$J$200,MATCH($B13,'INDEX ranked'!$B$3:$B$200,0),MATCH(J$1,'INDEX ranked'!$A$2:$J$2,0)),"")) -> 66.520655 | K13: =IF($B13="","",IFERROR(INDEX('INDEX ranked'!$A$3:$J$200,MATCH($B13,'INDEX ranked'!$B$3:$B$200,0),MATCH(K$1,'INDEX ranked'!$A$2:$J$2,0)),"")) -> 99.35425 | L13: =IF($B13="","",IFERROR(INDEX('Pillar-1'!$A$5:$M$216,MATCH($B13,'Pillar-1'!$B$5:$B$216,0),MATCH(L$1,'Pillar-1'!$A$4:$M$4,0)),"")) -> 66.751651 | M13: =IF($B13="","",IFERROR(INDEX('Pillar-1'!$A$5:$M$216,MATCH($B13,'Pillar-1'!$B$5:$B$216,0),MATCH(M$1,'Pillar-1'!$A$4:$M$4,0)),"")) -> 100 | N13: =IF($B13="","",IFERROR(INDEX('Pillar-1'!$A$5:$M$216,MATCH($B13,'Pillar-1'!$B$5:$B$216,0),MATCH(N$1,'Pillar-1'!$A$4:$M$4,0)),"")) -> 77.615282 | O13: =IF($B13="","",IFERROR(INDEX('Pillar-2'!$A$5:$S$216,MATCH($B13,'Pillar-2'!$B$5:$B$216,0),MATCH(O$1,'Pillar-2'!$A$4:$S$4,0)),"")) -> 85.941799 | P13: =IF($B13="","",IFERROR(INDEX('Pillar-2'!$A$5:$S$216,MATCH($B13,'Pillar-2'!$B$5:$B$216,0),MATCH(P$1,'Pillar-2'!$A$4:$S$4,0)),"")) -> 100 | Q13: =IF($B13="","",IFERROR(INDEX('Pillar-2'!$A$5:$S$216,MATCH($B13,'Pillar-2'!$B$5:$B$216,0),MATCH(Q$1,'Pillar-2'!$A$4:$S$4,0)),"")) -> 100 | R13: =IF($B13="","",IFERROR(INDEX('Pillar-2'!$A$5:$S$216,MATCH($B13,'Pillar-2'!$B$5:$B$216,0),MATCH(R$1,'Pillar-2'!$A$4:$S$4,0)),"")) -> 55.816701 | S13: =IF($B13="","",IFERROR(INDEX('Pillar-2'!$A$5:$S$216,MATCH($B13,'Pillar-2'!$B$5:$B$216,0),MATCH(S$1,'Pillar-2'!$A$4:$S$4,0)),"")) -> 96.483591 | T13: =IF($B13="","",IFERROR(INDEX('Pillar-2'!$A$5:$S$216,MATCH($B13,'Pillar-2'!$B$5:$B$216,0),MATCH(T$1,'Pillar-2'!$A$4:$S$4,0)),"")) -> 31.939481 | U13: =IF($B13="","",IFERROR(INDEX('Pillar-2'!$A$5:$S$216,MATCH($B13,'Pillar-2'!$B$5:$B$216,0),MATCH(U$1,'Pillar-2'!$A$4:$S$4,0)),"")) -> 100 | V13: =IF($B13="","",IFERROR(INDEX('Pillar-2'!$A$5:$S$216,MATCH($B13,'Pillar-2'!$B$5:$B$216,0),MATCH(V$1,'Pillar-2'!$A$4:$S$4,0)),"")) -> 100 | W13: =IF($B13="","",IFERROR(INDEX('Pillar-3'!$A$5:$M$217,MATCH($B13,'Pillar-3'!$B$5:$B$217,0),MATCH(W$1,'Pillar-3'!$A$4:$M$4,0)),"")) -> 68.02 | X13: =IF($B13="","",IFERROR(INDEX('Pillar-3'!$A$5:$M$217,MATCH($B13,'Pillar-3'!$B$5:$B$217,0),MATCH(X$1,'Pillar-3'!$A$4:$M$4,0)),"")) -> 81.41 | Y13: =IF($B13="","",IFERROR(INDEX('Pillar-3'!$A$5:$M$217,MATCH($B13,'Pillar-3'!$B$5:$B$217,0),MATCH(Y$1,'Pillar-3'!$A$4:$M$4,0)),"")) -> 78.49 | Z13: =IF($B13="","",IFERROR(INDEX('Pillar-3'!$A$5:$M$217,MATCH($B13,'Pillar-3'!$B$5:$B$217,0),MATCH(Z$1,'Pillar-3'!$A$4:$M$4,0)),"")) -> 84.95 | AA13: =IF($B13="","",IFERROR(INDEX('Pillar-3'!$A$5:$M$217,MATCH($B13,'Pillar-3'!$B$5:$B$217,0),MATCH(AA$1,'Pillar-3'!$A$4:$M$4,0)),"")) -> 83.75 | AB13: =IF($B13="","",IFERROR(INDEX('Pillar-4'!$A$5:$R$217,MATCH($B13,'Pillar-4'!$B$5:$B$217,0),MATCH(AB$1,'Pillar-4'!$A$4:$R$4,0)),"")) -> 52.234566 | AC13: =IF($B13="","",IFERROR(INDEX('Pillar-4'!$A$5:$R$217,MATCH($B13,'Pillar-4'!$B$5:$B$217,0),MATCH(AC$1,'Pillar-4'!$A$4:$R$4,0)),"")) -> 80.446635 | AD13: =IF($B13="","",IFERROR(INDEX('Pillar-4'!$A$5:$R$217,MATCH($B13,'Pillar-4'!$B$5:$B$217,0),MATCH(AD$1,'Pillar-4'!$A$4:$R$4,0)),"")) -> 81.60907 | AE13: =IF($B13="","",IFERROR(INDEX('Pillar-4'!$A$5:$R$217,MATCH($B13,'Pillar-4'!$B$5:$B$217,0),MATCH(AE$1,'Pillar-4'!$A$4:$R$4,0)),"")) -> 20 | AF13: =IF($B13="","",IFERROR(INDEX('Pillar-4'!$A$5:$R$217,MATCH($B13,'Pillar-4'!$B$5:$B$217,0),MATCH(AF$1,'Pillar-4'!$A$4:$R$4,0)),"")) -> 25 | AG13: =IF($B13="","",IFERROR(INDEX('Pillar-5'!$A$5:$Q$216,MATCH($B13,'Pillar-5'!$B$5:$B$216,0),MATCH(AG$1,'Pillar-5'!$A$4:$Q$4,0)),"")) -> 38.626742 | AH13: =IF($B13="","",IFERROR(INDEX('Pillar-5'!$A$5:$Q$216,MATCH($B13,'Pillar-5'!$B$5:$B$216,0),MATCH(AH$1,'Pillar-5'!$A$4:$Q$4,0)),"")) -> 100 | AI13: =IF($B13="","",IFERROR(INDEX('Pillar-5'!$A$5:$Q$216,MATCH($B13,'Pillar-5'!$B$5:$B$216,0),MATCH(AI$1,'Pillar-5'!$A$4:$Q$4,0)),"")) -> 58.515333 | AJ13: =IF($B13="","",IFERROR(INDEX('Pillar-5'!$A$5:$Q$216,MATCH($B13,'Pillar-5'!$B$5:$B$216,0),MATCH(AJ$1,'Pillar-5'!$A$4:$Q$4,0)),"")) -> 72.918261 | AK13: =IF($B13="","",IFERROR(INDEX('Pillar-6'!$A$5:$Q$216,MATCH($B13,'Pillar-6'!$B$5:$B$216,0),MATCH(AK$1,'Pillar-6'!$A$4:$Q$4,0)),"")) -> 100 | AL13: =IF($B13="","",IFERROR(INDEX('Pillar-6'!$A$5:$Q$216,MATCH($B13,'Pillar-6'!$B$5:$B$216,0),MATCH(AL$1,'Pillar-6'!$A$4:$Q$4,0)),"")) -> 98.565 | AM13: =IF($B13="","",IFERROR(INDEX('Pillar-6'!$A$5:$Q$216,MATCH($B13,'Pillar-6'!$B$5:$B$216,0),MATCH(AM$1,'Pillar-6'!$A$4:$Q$4,0)),"")) -> 100
A14: Hong Kong | B14: HKG | C14: =IF($B14="","",IFERROR(INDEX(Screening!$A$2:$R$219,MATCH($B14,Screening!$B$2:$B$219,0),MATCH("Include in final index",Screening!$A$1:$R$1,0)),"")) -> Yes | D14: =IF($B14="","",IFERROR(INDEX('INDEX ranked'!$A$3:$J$200,MATCH($B14,'INDEX ranked'!$B$3:$B$200,0),MATCH("Rank",'INDEX ranked'!$A$2:$J$2,0)),"")) -> 21 | E14: =IF($B14="","",IFERROR(INDEX('INDEX ranked'!$A$3:$J$200,MATCH($B14,'INDEX ranked'!$B$3:$B$200,0),MATCH("Overall index score",'INDEX ranked'!$A$2:$J$2,0)),"")) -> 48.284899 | F14: =IF($B14="","",IFERROR(INDEX('INDEX ranked'!$A$3:$J$200,MATCH($B14,'INDEX ranked'!$B$3:$B$200,0),MATCH(F$1,'INDEX ranked'!$A$2:$J$2,0)),"")) -> 4.5636845 | G14: =IF($B14="","",IFERROR(INDEX('INDEX ranked'!$A$3:$J$200,MATCH($B14,'INDEX ranked'!$B$3:$B$200,0),MATCH(G$1,'INDEX ranked'!$A$2:$J$2,0)),"")) -> 67.969412 | H14: =IF($B14="","",IFERROR(INDEX('INDEX ranked'!$A$3:$J$200,MATCH($B14,'INDEX ranked'!$B$3:$B$200,0),MATCH(H$1,'INDEX ranked'!$A$2:$J$2,0)),"")) -> 79.537 | I14: =IF($B14="","",IFERROR(INDEX('INDEX ranked'!$A$3:$J$200,MATCH($B14,'INDEX ranked'!$B$3:$B$200,0),MATCH(I$1,'INDEX ranked'!$A$2:$J$2,0)),"")) -> 1.8606328 | J14: =IF($B14="","",IFERROR(INDEX('INDEX ranked'!$A$3:$J$200,MATCH($B14,'INDEX ranked'!$B$3:$B$200,0),MATCH(J$1,'INDEX ranked'!$A$2:$J$2,0)),"")) -> 97.983185 | K14: =IF($B14="","",IFERROR(INDEX('INDEX ranked'!$A$3:$J$200,MATCH($B14,'INDEX ranked'!$B$3:$B$200,0),MATCH(K$1,'INDEX ranked'!$A$2:$J$2,0)),"")) -> 67.78125 | L14: =IF($B14="","",IFERROR(INDEX('Pillar-1'!$A$5:$M$216,MATCH($B14,'Pillar-1'!$B$5:$B$216,0),MATCH(L$1,'Pillar-1'!$A$4:$M$4,0)),"")) -> 0 | M14: =IF($B14="","",IFERROR(INDEX('Pillar-1'!$A$5:$M$216,MATCH($B14,'Pillar-1'!$B$5:$B$216,0),MATCH(M$1,'Pillar-1'!$A$4:$M$4,0)),"")) -> 1.0154627 | N14: =IF($B14="","",IFERROR(INDEX('Pillar-1'!$A$5:$M$216,MATCH($B14,'Pillar-1'!$B$5:$B$216,0),MATCH(N$1,'Pillar-1'!$A$4:$M$4,0)),"")) -> 12.168702 | O14: =IF($B14="","",IFERROR(INDEX('Pillar-2'!$A$5:$S$216,MATCH($B14,'Pillar-2'!$B$5:$B$216,0),MATCH(O$1,'Pillar-2'!$A$4:$S$4,0)),"")) -> 59.825397 | P14: =IF($B14="","",IFERROR(INDEX('Pillar-2'!$A$5:$S$216,MATCH($B14,'Pillar-2'!$B$5:$B$216,0),MATCH(P$1,'Pillar-2'!$A$4:$S$4,0)),"")) -> 100 | Q14: =IF($B14="","",IFERROR(INDEX('Pillar-2'!$A$5:$S$216,MATCH($B14,'Pillar-2'!$B$5:$B$216,0),MATCH(Q$1,'Pillar-2'!$A$4:$S$4,0)),"")) -> 100 | R14: =IF($B14="","",IFERROR(INDEX('Pillar-2'!$A$5:$S$216,MATCH($B14,'Pillar-2'!$B$5:$B$216,0),MATCH(R$1,'Pillar-2'!$A$4:$S$4,0)),"")) -> 100 | S14: =IF($B14="","",IFERROR(INDEX('Pillar-2'!$A$5:$S$216,MATCH($B14,'Pillar-2'!$B$5:$B$216,0),MATCH(S$1,'Pillar-2'!$A$4:$S$4,0)),"")) -> 9.0548873 | T14: =IF($B14="","",IFERROR(INDEX('Pillar-2'!$A$5:$S$216,MATCH($B14,'Pillar-2'!$B$5:$B$216,0),MATCH(T$1,'Pillar-2'!$A$4:$S$4,0)),"")) -> 58.797219 | U14: =IF($B14="","",IFERROR(INDEX('Pillar-2'!$A$5:$S$216,MATCH($B14,'Pillar-2'!$B$5:$B$216,0),MATCH(U$1,'Pillar-2'!$A$4:$S$4,0)),"")) -> 0 | V14: =IF($B14="","",IFERROR(INDEX('Pillar-2'!$A$5:$S$216,MATCH($B14,'Pillar-2'!$B$5:$B$216,0),MATCH(V$1,'Pillar-2'!$A$4:$S$4,0)),"")) -> 75 | W14: =IF($B14="","",IFERROR(INDEX('Pillar-3'!$A$5:$M$217,MATCH($B14,'Pillar-3'!$B$5:$B$217,0),MATCH(W$1,'Pillar-3'!$A$4:$M$4,0)),"")) -> 76.67 | X14: =IF($B14="","",IFERROR(INDEX('Pillar-3'!$A$5:$M$217,MATCH($B14,'Pillar-3'!$B$5:$B$217,0),MATCH(X$1,'Pillar-3'!$A$4:$M$4,0)),"")) -> 83.18 | Y14: =IF($B14="","",IFERROR(INDEX('Pillar-3'!$A$5:$M$217,MATCH($B14,'Pillar-3'!$B$5:$B$217,0),MATCH(Y$1,'Pillar-3'!$A$4:$M$4,0)),"")) -> 82.3 | Z14: =IF($B14="","",IFERROR(INDEX('Pillar-3'!$A$5:$M$217,MATCH($B14,'Pillar-3'!$B$5:$B$217,0),MATCH(Z$1,'Pillar-3'!$A$4:$M$4,0)),"")) -> 72.82 | AA14: =IF($B14="","",IFERROR(INDEX('Pillar-3'!$A$5:$M$217,MATCH($B14,'Pillar-3'!$B$5:$B$217,0),MATCH(AA$1,'Pillar-3'!$A$4:$M$4,0)),"")) -> 79.68 | AB14: =IF($B14="","",IFERROR(INDEX('Pillar-4'!$A$5:$R$217,MATCH($B14,'Pillar-4'!$B$5:$B$217,0),MATCH(AB$1,'Pillar-4'!$A$4:$R$4,0)),"")) -> 9.3031638 | AC14: =IF($B14="","",IFERROR(INDEX('Pillar-4'!$A$5:$R$217,MATCH($B14,'Pillar-4'!$B$5:$B$217,0),MATCH(AC$1,'Pillar-4'!$A$4:$R$4,0)),"")) -> 0 | AD14: =IF($B14="","",IFERROR(INDEX('Pillar-4'!$A$5:$R$217,MATCH($B14,'Pillar-4'!$B$5:$B$217,0),MATCH(AD$1,'Pillar-4'!$A$4:$R$4,0)),"")) -> 0 | AE14: =IF($B14="","",IFERROR(INDEX('Pillar-4'!$A$5:$R$217,MATCH($B14,'Pillar-4'!$B$5:$B$217,0),MATCH(AE$1,'Pillar-4'!$A$4:$R$4,0)),"")) -> 0 | AF14: =IF($B14="","",IFERROR(INDEX('Pillar-4'!$A$5:$R$217,MATCH($B14,'Pillar-4'!$B$5:$B$217,0),MATCH(AF$1,'Pillar-4'!$A$4:$R$4,0)),"")) -> 0 | AG14: =IF($B14="","",IFERROR(INDEX('Pillar-5'!$A$5:$Q$216,MATCH($B14,'Pillar-5'!$B$5:$B$216,0),MATCH(AG$1,'Pillar-5'!$A$4:$Q$4,0)),"")) -> 100 | AH14: =IF($B14="","",IFERROR(INDEX('Pillar-5'!$A$5:$Q$216,MATCH($B14,'Pillar-5'!$B$5:$B$216,0),MATCH(AH$1,'Pillar-5'!$A$4:$Q$4,0)),"")) -> 100 | AI14: =IF($B14="","",IFERROR(INDEX('Pillar-5'!$A$5:$Q$216,MATCH($B14,'Pillar-5'!$B$5:$B$216,0),MATCH(AI$1,'Pillar-5'!$A$4:$Q$4,0)),"")) -> 93.859333 | AJ14: =IF($B14="","",IFERROR(INDEX('Pillar-5'!$A$5:$Q$216,MATCH($B14,'Pillar-5'!$B$5:$B$216,0),MATCH(AJ$1,'Pillar-5'!$A$4:$Q$4,0)),"")) -> 96.845274 | AK14: =IF($B14="","",IFERROR(INDEX('Pillar-6'!$A$5:$Q$216,MATCH($B14,'Pillar-6'!$B$5:$B$216,0),MATCH(AK$1,'Pillar-6'!$A$4:$Q$4,0)),"")) -> 20 | AL14: =IF($B14="","",IFERROR(INDEX('Pillar-6'!$A$5:$Q$216,MATCH($B14,'Pillar-6'!$B$5:$B$216,0),MATCH(AL$1,'Pillar-6'!$A$4:$Q$4,0)),"")) -> 90.625 | AM14: =IF($B14="","",IFERROR(INDEX('Pillar-6'!$A$5:$Q$216,MATCH($B14,'Pillar-6'!$B$5:$B$216,0),MATCH(AM$1,'Pillar-6'!$A$4:$Q$4,0)),"")) -> 100
... A37: Vietnam | B37: VNM | C37: =IF($B37="","",IFERROR(INDEX(Screening!$A$2:$R$219,MATCH($B37,Screening!$B$2:$B$219,0),MATCH("Include in final index",Screening!$A$1:$R$1,0)),"")) -> Yes | D37: =IF($B37="","",IFERROR(INDEX('INDEX ranked'!$A$3:$J$200,MATCH($B37,'INDEX ranked'!$B$3:$B$200,0),MATCH("Rank",'INDEX ranked'!$A$2:$J$2,0)),"")) -> 8 | E37: =IF($B37="","",IFERROR(INDEX('INDEX ranked'!$A$3:$J$200,MATCH($B37,'INDEX ranked'!$B$3:$B$200,0),MATCH("Overall index score",'INDEX ranked'!$A$2:$J$2,0)),"")) -> 59.047171 | F37: =IF($B37="","",IFERROR(INDEX('INDEX ranked'!$A$3:$J$200,MATCH($B37,'INDEX ranked'!$B$3:$B$200,0),MATCH(F$1,'INDEX ranked'!$A$2:$J$2,0)),"")) -> 42.588404 | G37: =IF($B37="","",IFERROR(INDEX('INDEX ranked'!$A$3:$J$200,MATCH($B37,'INDEX ranked'!$B$3:$B$200,0),MATCH(G$1,'INDEX ranked'!$A$2:$J$2,0)),"")) -> 58.075052 | H37: =IF($B37="","",IFERROR(INDEX('INDEX ranked'!$A$3:$J$200,MATCH($B37,'INDEX ranked'!$B$3:$B$200,0),MATCH(H$1,'INDEX ranked'!$A$2:$J$2,0)),"")) -> 50.513 | I37: =IF($B37="","",IFERROR(INDEX('INDEX ranked'!$A$3:$J$200,MATCH($B37,'INDEX ranked'!$B$3:$B$200,0),MATCH(I$1,'INDEX ranked'!$A$2:$J$2,0)),"")) -> 70.649827 | J37: =IF($B37="","",IFERROR(INDEX('INDEX ranked'!$A$3:$J$200,MATCH($B37,'INDEX ranked'!$B$3:$B$200,0),MATCH(J$1,'INDEX ranked'!$A$2:$J$2,0)),"")) -> 76.538933 | K37: =IF($B37="","",IFERROR(INDEX('INDEX ranked'!$A$3:$J$200,MATCH($B37,'INDEX ranked'!$B$3:$B$200,0),MATCH(K$1,'INDEX ranked'!$A$2:$J$2,0)),"")) -> 57.26725 | L37: =IF($B37="","",IFERROR(INDEX('Pillar-1'!$A$5:$M$216,MATCH($B37,'Pillar-1'!$B$5:$B$216,0),MATCH(L$1,'Pillar-1'!$A$4:$M$4,0)),"")) -> 47.792328 | M37: =IF($B37="","",IFERROR(INDEX('Pillar-1'!$A$5:$M$216,MATCH($B37,'Pillar-1'!$B$5:$B$216,0),MATCH(M$1,'Pillar-1'!$A$4:$M$4,0)),"")) -> 28.963766 | N37: =IF($B37="","",IFERROR(INDEX('Pillar-1'!$A$5:$M$216,MATCH($B37,'Pillar-1'!$B$5:$B$216,0),MATCH(N$1,'Pillar-1'!$A$4:$M$4,0)),"")) -> 49.06274 | O37: =IF($B37="","",IFERROR(INDEX('Pillar-2'!$A$5:$S$216,MATCH($B37,'Pillar-2'!$B$5:$B$216,0),MATCH(O$1,'Pillar-2'!$A$4:$S$4,0)),"")) -> 27.62963 | P37: =IF($B37="","",IFERROR(INDEX('Pillar-2'!$A$5:$S$216,MATCH($B37,'Pillar-2'!$B$5:$B$216,0),MATCH(P$1,'Pillar-2'!$A$4:$S$4,0)),"")) -> 83.398537 | Q37: =IF($B37="","",IFERROR(INDEX('Pillar-2'!$A$5:$S$216,MATCH($B37,'Pillar-2'!$B$5:$B$216,0),MATCH(Q$1,'Pillar-2'!$A$4:$S$4,0)),"")) -> 33.228294 | R37: =IF($B37="","",IFERROR(INDEX('Pillar-2'!$A$5:$S$216,MATCH($B37,'Pillar-2'!$B$5:$B$216,0),MATCH(R$1,'Pillar-2'!$A$4:$S$4,0)),"")) -> 50.65341 | S37: =IF($B37="","",IFERROR(INDEX('Pillar-2'!$A$5:$S$216,MATCH($B37,'Pillar-2'!$B$5:$B$216,0),MATCH(S$1,'Pillar-2'!$A$4:$S$4,0)),"")) -> 70.250004 | T37: =IF($B37="","",IFERROR(INDEX('Pillar-2'!$A$5:$S$216,MATCH($B37,'Pillar-2'!$B$5:$B$216,0),MATCH(T$1,'Pillar-2'!$A$4:$S$4,0)),"")) -> 61.499069 | U37: =IF($B37="","",IFERROR(INDEX('Pillar-2'!$A$5:$S$216,MATCH($B37,'Pillar-2'!$B$5:$B$216,0),MATCH(U$1,'Pillar-2'!$A$4:$S$4,0)),"")) -> 100 | V37: =IF($B37="","",IFERROR(INDEX('Pillar-2'!$A$5:$S$216,MATCH($B37,'Pillar-2'!$B$5:$B$216,0),MATCH(V$1,'Pillar-2'!$A$4:$S$4,0)),"")) -> 50 | W37: =IF($B37="","",IFERROR(INDEX('Pillar-3'!$A$5:$M$217,MATCH($B37,'Pillar-3'!$B$5:$B$217,0),MATCH(W$1,'Pillar-3'!$A$4:$M$4,0)),"")) -> 65.99 | X37: =IF($B37="","",IFERROR(INDEX('Pillar-3'!$A$5:$M$217,MATCH($B37,'Pillar-3'!$B$5:$B$217,0),MATCH(X$1,'Pillar-3'!$A$4:$M$4,0)),"")) -> 49.55 | Y37: =IF($B37="","",IFERROR(INDEX('Pillar-3'!$A$5:$M$217,MATCH($B37,'Pillar-3'!$B$5:$B$217,0),MATCH(Y$1,'Pillar-3'!$A$4:$M$4,0)),"")) -> 50.65 | Z37: =IF($B37="","",IFERROR(INDEX('Pillar-3'!$A$5:$M$217,MATCH($B37,'Pillar-3'!$B$5:$B$217,0),MATCH(Z$1,'Pillar-3'!$A$4:$M$4,0)),"")) -> 51.56 | AA37: =IF($B37="","",IFERROR(INDEX('Pillar-3'!$A$5:$M$217,MATCH($B37,'Pillar-3'!$B$5:$B$217,0),MATCH(AA$1,'Pillar-3'!$A$4:$M$4,0)),"")) -> 42.76 | AB37: =IF($B37="","",IFERROR(INDEX('Pillar-4'!$A$5:$R$217,MATCH($B37,'Pillar-4'!$B$5:$B$217,0),MATCH(AB$1,'Pillar-4'!$A$4:$R$4,0)),"")) -> 65.433086 | AC37: =IF($B37="","",IFERROR(INDEX('Pillar-4'!$A$5:$R$217,MATCH($B37,'Pillar-4'!$B$5:$B$217,0),MATCH(AC$1,'Pillar-4'!$A$4:$R$4,0)),"")) -> 85.143509 | AD37: =IF($B37="","",IFERROR(INDEX('Pillar-4'!$A$5:$R$217,MATCH($B37,'Pillar-4'!$B$5:$B$217,0),MATCH(AD$1,'Pillar-4'!$A$4:$R$4,0)),"")) -> 80.230053 | AE37: =IF($B37="","",IFERROR(INDEX('Pillar-4'!$A$5:$R$217,MATCH($B37,'Pillar-4'!$B$5:$B$217,0),MATCH(AE$1,'Pillar-4'!$A$4:$R$4,0)),"")) -> 80 | AF37: =IF($B37="","",IFERROR(INDEX('Pillar-4'!$A$5:$R$217,MATCH($B37,'Pillar-4'!$B$5:$B$217,0),MATCH(AF$1,'Pillar-4'!$A$4:$R$4,0)),"")) -> 50 | AG37: =IF($B37="","",IFERROR(INDEX('Pillar-5'!$A$5:$Q$216,MATCH($B37,'Pillar-5'!$B$5:$B$216,0),MATCH(AG$1,'Pillar-5'!$A$4:$Q$4,0)),"")) -> 41.48955 | AH37: =IF($B37="","",IFERROR(INDEX('Pillar-5'!$A$5:$Q$216,MATCH($B37,'Pillar-5'!$B$5:$B$216,0),MATCH(AH$1,'Pillar-5'!$A$4:$Q$4,0)),"")) -> 100 | AI37: =IF($B37="","",IFERROR(INDEX('Pillar-5'!$A$5:$Q$216,MATCH($B37,'Pillar-5'!$B$5:$B$216,0),MATCH(AI$1,'Pillar-5'!$A$4:$Q$4,0)),"")) -> 79.224667 | AJ37: =IF($B37="","",IFERROR(INDEX('Pillar-5'!$A$5:$Q$216,MATCH($B37,'Pillar-5'!$B$5:$B$216,0),MATCH(AJ$1,'Pillar-5'!$A$4:$Q$4,0)),"")) -> 92.988537 | AK37: =IF($B37="","",IFERROR(INDEX('Pillar-6'!$A$5:$Q$216,MATCH($B37,'Pillar-6'!$B$5:$B$216,0),MATCH(AK$1,'Pillar-6'!$A$4:$Q$4,0)),"")) -> 40 | AL37: =IF($B37="","",IFERROR(INDEX('Pillar-6'!$A$5:$Q$216,MATCH($B37,'Pillar-6'!$B$5:$B$216,0),MATCH(AL$1,'Pillar-6'!$A$4:$Q$4,0)),"")) -> 51.705 | AM37: =IF($B37="","",IFERROR(INDEX('Pillar-6'!$A$5:$Q$216,MATCH($B37,'Pillar-6'!$B$5:$B$216,0),MATCH(AM$1,'Pillar-6'!$A$4:$Q$4,0)),"")) -> 100

Sheet Pillar-1
A1: PILLAR 1 Energy system conditions | C1: Eligibility gate | E1: Indicators | H1: Indicator weights (v3)
E2: 1 | F2: 2 | G2: 3 | H2: 0 | I2: 0 | J2: 0.35 | K2: 0.3 | L2: 0.35 | M2: =SUM(J2:L2) -> 1
C3: Operating coal capacity – proxy for opportunity scale | D3: Coal share of electricity generation | E3: Renewable electricity share | F3: Wind and solar share | G3: Grid emissions intensity | H3: Operating coal capacity – eligibility gate | I3: Coal generation share – material-opportunity screen | J3: Renewable electricity share | K3: Wind and solar share | L3: Grid emissions intensity | M3: PILLAR 1 Energy system conditions
A4: Country (Gated) | B4: Country Code (ISO3) | C4: GEM operating coal capacity (MW) | D4: Ember coal share of electricity generation (%) | E4: Ember renewable electricity share (%) | F4: Ember wind and solar share (%) | G4: Ember grid emissions intensity (gCO2e/kWh) | H4: Screening field – not included in P1 score | I4: Screening field – not included in P1 score | J4: P1_Indicator1_Score | K4: P1_Indicator2_Score | L4: P1_Indicator3_Score | M4: P1_Score
A5: {=_xlfn._xlws.FILTER(Screening!$A$2:$B$216,Screening!$L$2:$L$216="Yes","")} -> Australia | B5: AUS | C5: =_xlfn.XLOOKUP($B5,[1]pillars_WIP!$B$7:$B$301,[1]pillars_WIP!$C$7:$C$301,"Missing",0) -> 22629 | D5: =_xlfn.XLOOKUP($B5,[1]pillars_WIP!$B$7:$B$301,[1]pillars_WIP!$D$7:$D$301,"Missing",0) -> 45.21 | E5: =_xlfn.XLOOKUP($B5,[1]pillars_WIP!$B$7:$B$301,[1]pillars_WIP!$E$7:$E$301,"Missing",0) -> 35.07 | F5: =_xlfn.XLOOKUP($B5,[1]pillars_WIP!$B$7:$B$301,[1]pillars_WIP!$F$7:$F$301,"Missing",0) -> 29.45 | G5: =_xlfn.XLOOKUP($B5,[1]pillars_WIP!$B$7:$B$301,[1]pillars_WIP!$G$7:$G$301,"Missing",0) -> 553.83 | H5: =IF(ISNUMBER(C5),IF(C5>0,"Yes","No"),"") -> Yes | I5: =IF(ISNUMBER(D5),IFERROR((Params!$G$6-MAX(Params!$G$5,MIN(Params!$G$6,D5)))/(Params!$G$6-Params!$G$5)*100,""),"") -> 47.842947 | J5: =IF(ISNUMBER(E5),IFERROR((MAX(Params!$G$7,MIN(Params!$G$8,E5))-Params!$G$7)/(Params!$G$8-Params!$G$7)*100,""),"") -> 39.436783 | K5: =IF(ISNUMBER(F5),IFERROR((MAX(Params!$G$9,MIN(Params!$G$10,F5))-Params!$G$9)/(Params!$G$10-Params!$G$9)*100,""),"") -> 67.574429 | L5: =IF(ISNUMBER(G5),IFERROR((Params!$G$12-MAX(Params!$G$11,MIN(Params!$G$12,G5)))/(Params!$G$12-Params!$G$11)*100,""),"") -> 35.647252 | M5: =IF(COUNT(J5:L5)=3,SUMPRODUCT(J5:L5,$J$2:$L$2),"") -> 46.551741
A6: Bangladesh | B6: BGD | C6: =_xlfn.XLOOKUP($B6,[1]pillars_WIP!$B$7:$B$301,[1]pillars_WIP!$C$7:$C$301,"Missing",0) -> 7230 | D6: =_xlfn.XLOOKUP($B6,[1]pillars_WIP!$B$7:$B$301,[1]pillars_WIP!$D$7:$D$301,"Missing",0) -> 19.94 | E6: =_xlfn.XLOOKUP($B6,[1]pillars_WIP!$B$7:$B$301,[1]pillars_WIP!$E$7:$E$301,"Missing",0) -> 1.89 | F6: =_xlfn.XLOOKUP($B6,[1]pillars_WIP!$B$7:$B$301,[1]pillars_WIP!$F$7:$F$301,"Missing",0) -> 1.2 | G6: =_xlfn.XLOOKUP($B6,[1]pillars_WIP!$B$7:$B$301,[1]pillars_WIP!$G$7:$G$301,"Missing",0) -> 695.7 | H6: =IF(ISNUMBER(C6),IF(C6>0,"Yes","No"),"") -> Yes | I6: =IF(ISNUMBER(D6),IFERROR((Params!$G$6-MAX(Params!$G$5,MIN(Params!$G$6,D6)))/(Params!$G$6-Params!$G$5)*100,""),"") -> 78.465826 | J6: =IF(ISNUMBER(E6),IFERROR((MAX(Params!$G$7,MIN(Params!$G$8,E6))-Params!$G$7)/(Params!$G$8-Params!$G$7)*100,""),"") -> 0.98505041 | K6: =IF(ISNUMBER(F6),IFERROR((MAX(Params!$G$9,MIN(Params!$G$10,F6))-Params!$G$9)/(Params!$G$10-Params!$G$9)*100,""),"") -> 2.3771059 | L6: =IF(ISNUMBER(G6),IFERROR((Params!$G$12-MAX(Params!$G$11,MIN(Params!$G$12,G6)))/(Params!$G$12-Params!$G$11)*100,""),"") -> 8.2662253 | M6: =IF(COUNT(J6:L6)=3,SUMPRODUCT(J6:L6,$J$2:$L$2),"") -> 3.9510783
A7: Bosnia and Herzegovina | B7: BIH | C7: =_xlfn.XLOOKUP($B7,[1]pillars_WIP!$B$7:$B$301,[1]pillars_WIP!$C$7:$C$301,"Missing",0) -> 1990 | D7: =_xlfn.XLOOKUP($B7,[1]pillars_WIP!$B$7:$B$301,[1]pillars_WIP!$D$7:$D$301,"Missing",0) -> 58.68 | E7: =_xlfn.XLOOKUP($B7,[1]pillars_WIP!$B$7:$B$301,[1]pillars_WIP!$E$7:$E$301,"Missing",0) -> 40.35 | F7: =_xlfn.XLOOKUP($B7,[1]pillars_WIP!$B$7:$B$301,[1]pillars_WIP!$F$7:$F$301,"Missing",0) -> 4.91 | G7: =_xlfn.XLOOKUP($B7,[1]pillars_WIP!$B$7:$B$301,[1]pillars_WIP!$G$7:$G$301,"Missing",0) -> 601.03 | H7: =IF(ISNUMBER(C7),IF(C7>0,"Yes","No"),"No") -> Yes | I7: =IF(ISNUMBER(D7),IFERROR((Params!$G$6-MAX(Params!$G$5,MIN(Params!$G$6,D7)))/(Params!$G$6-Params!$G$5)*100,""),"") -> 31.519632 | J7: =IF(ISNUMBER(E7),IFERROR((MAX(Params!$G$7,MIN(Params!$G$8,E7))-Params!$G$7)/(Params!$G$8-Params!$G$7)*100,""),"") -> 45.555684 | K7: =IF(ISNUMBER(F7),IFERROR((MAX(Params!$G$9,MIN(Params!$G$10,F7))-Params!$G$9)/(Params!$G$10-Params!$G$9)*100,""),"") -> 10.939303 | L7: =IF(ISNUMBER(G7),IFERROR((Params!$G$12-MAX(Params!$G$11,MIN(Params!$G$12,G7)))/(Params!$G$12-Params!$G$11)*100,""),"") -> 26.537613 | M7: =IF(COUNT(J7:L7)=3,SUMPRODUCT(J7:L7,$J$2:$L$2),"") -> 28.514445
A8: Brazil | B8: BRA | C8: =_xlfn.XLOOKUP($B8,[1]pillars_WIP!$B$7:$B$301,[1]pillars_WIP!$C$7:$C$301,"Missing",0) -> 2997 | D8: =_xlfn.XLOOKUP($B8,[1]pillars_WIP!$B$7:$B$301,[1]pillars_WIP!$D$7:$D$301,"Missing",0) -> 2.17 | E8: =_xlfn.XLOOKUP($B8,[1]pillars_WIP!$B$7:$B$301,[1]pillars_WIP!$E$7:$E$301,"Missing",0) -> 87.33 | F8: =_xlfn.XLOOKUP($B8,[1]pillars_WIP!$B$7:$B$301,[1]pillars_WIP!$F$7:$F$301,"Missing",0) -> 24.11 | G8: =_xlfn.XLOOKUP($B8,[1]pillars_WIP!$B$7:$B$301,[1]pillars_WIP!$G$7:$G$301,"Missing",0) -> 106.06 | H8: =IF(ISNUMBER(C8),IF(C8>0,"Yes","No"),"No") -> Yes | I8: =IF(ISNUMBER(D8),IFERROR((Params!$G$6-MAX(Params!$G$5,MIN(Params!$G$6,D8)))/(Params!$G$6-Params!$G$5)*100,""),"") -> 100 | J8: =IF(ISNUMBER(E8),IFERROR((MAX(Params!$G$7,MIN(Params!$G$8,E8))-Params!$G$7)/(Params!$G$8-Params!$G$7)*100,""),"") -> 100 | K8: =IF(ISNUMBER(F8),IFERROR((MAX(Params!$G$9,MIN(Params!$G$10,F8))-Params!$G$9)/(Params!$G$10-Params!$G$9)*100,""),"") -> 55.250404 | L8: =IF(ISNUMBER(G8),IFERROR((Params!$G$12-MAX(Params!$G$11,MIN(Params!$G$12,G8)))/(Params!$G$12-Params!$G$11)*100,""),"") -> 100 | M8: =IF(COUNT(J8:L8)=3,SUMPRODUCT(J8:L8,$J$2:$L$2),"") -> 86.575121
A9: Bulgaria | B9: BGR | C9: =_xlfn.XLOOKUP($B9,[1]pillars_WIP!$B$7:$B$301,[1]pillars_WIP!$C$7:$C$301,"Missing",0) -> 4115 | D9: =_xlfn.XLOOKUP($B9,[1]pillars_WIP!$B$7:$B$301,[1]pillars_WIP!$D$7:$D$301,"Missing",0) -> 22.87 | E9: =_xlfn.XLOOKUP($B9,[1]pillars_WIP!$B$7:$B$301,[1]pillars_WIP!$E$7:$E$301,"Missing",0) -> 29.91 | F9: =_xlfn.XLOOKUP($B9,[1]pillars_WIP!$B$7:$B$301,[1]pillars_WIP!$F$7:$F$301,"Missing",0) -> 18.14 | G9: =_xlfn.XLOOKUP($B9,[1]pillars_WIP!$B$7:$B$301,[1]pillars_WIP!$G$7:$G$301,"Missing",0) -> 278.85 | H9: =IF(ISNUMBER(C9),IF(C9>0,"Yes","No"),"No") -> Yes | I9: =IF(ISNUMBER(D9),IFERROR((Params!$G$6-MAX(Params!$G$5,MIN(Params!$G$6,D9)))/(Params!$G$6-Params!$G$5)*100,""),"") -> 74.915172 | J9: =IF(ISNUMBER(E9),IFERROR((MAX(Params!$G$7,MIN(Params!$G$8,E9))-Params!$G$7)/(Params!$G$8-Params!$G$7)*100,""),"") -> 33.456948 | K9: =IF(ISNUMBER(F9),IFERROR((MAX(Params!$G$9,MIN(Params!$G$10,F9))-Params!$G$9)/(Params!$G$10-Params!$G$9)*100,""),"") -> 41.472421 | L9: =IF(ISNUMBER(G9),IFERROR((Params!$G$12-MAX(Params!$G$11,MIN(Params!$G$12,G9)))/(Params!$G$12-Params!$G$11)*100,""),"") -> 88.718619 | M9: =IF(COUNT(J9:L9)=3,SUMPRODUCT(J9:L9,$J$2:$L$2),"") -> 55.203175
A10: Cambodia | B10: KHM | C10: =_xlfn.XLOOKUP($B10,[1]pillars_WIP!$B$7:$B$301,[1]pillars_WIP!$C$7:$C$301,"Missing",0) -> 1455 | D10: =_xlfn.XLOOKUP($B10,[1]pillars_WIP!$B$7:$B$301,[1]pillars_WIP!$D$7:$D$301,"Missing",0) -> 60.92 | E10: =_xlfn.XLOOKUP($B10,[1]pillars_WIP!$B$7:$B$301,[1]pillars_WIP!$E$7:$E$301,"Missing",0) -> 35.66 | F10: =_xlfn.XLOOKUP($B10,[1]pillars_WIP!$B$7:$B$301,[1]pillars_WIP!$F$7:$F$301,"Missing",0) -> 6.91 | G10: =_xlfn.XLOOKUP($B10,[1]pillars_WIP!$B$7:$B$301,[1]pillars_WIP!$G$7:$G$301,"Missing",0) -> 538.76 | H10: =IF(ISNUMBER(C10),IF(C10>0,"Yes","No"),"No") -> Yes | I10: =IF(ISNUMBER(D10),IFERROR((Params!$G$6-MAX(Params!$G$5,MIN(Params!$G$6,D10)))/(Params!$G$6-Params!$G$5)*100,""),"") -> 28.805138 | J10: =IF(ISNUMBER(E10),IFERROR((MAX(Params!$G$7,MIN(Params!$G$8,E10))-Params!$G$7)/(Params!$G$8-Params!$G$7)*100,""),"") -> 40.120524 | K10: =IF(ISNUMBER(F10),IFERROR((MAX(Params!$G$9,MIN(Params!$G$10,F10))-Params!$G$9)/(Params!$G$10-Params!$G$9)*100,""),"") -> 15.555043 | L10: =IF(ISNUMBER(G10),IFERROR((Params!$G$12-MAX(Params!$G$11,MIN(Params!$G$12,G10)))/(Params!$G$12-Params!$G$11)*100,""),"") -> 38.555775 | M10: =IF(COUNT(J10:L10)=3,SUMPRODUCT(J10:L10,$J$2:$L$2),"") -> 32.203217
A11: Canada | B11: CAN | C11: =_xlfn.XLOOKUP($B11,[1]pillars_WIP!$B$7:$B$301,[1]pillars_WIP!$C$7:$C$301,"Missing",0) -> 3080.8 | D11: =_xlfn.XLOOKUP($B11,[1]pillars_WIP!$B$7:$B$301,[1]pillars_WIP!$D$7:$D$301,"Missing",0) -> 3.95 | E11: =_xlfn.XLOOKUP($B11,[1]pillars_WIP!$B$7:$B$301,[1]pillars_WIP!$E$7:$E$301,"Missing",0) -> 64.27 | F11: =_xlfn.XLOOKUP($B11,[1]pillars_WIP!$B$7:$B$301,[1]pillars_WIP!$F$7:$F$301,"Missing",0) -> 8.83 | G11: =_xlfn.XLOOKUP($B11,[1]pillars_WIP!$B$7:$B$301,[1]pillars_WIP!$G$7:$G$301,"Missing",0) -> 185.35 | H11: =IF(ISNUMBER(C11),IF(C11>0,"Yes","No"),"No") -> Yes | I11: =IF(ISNUMBER(D11),IFERROR((Params!$G$6-MAX(Params!$G$5,MIN(Params!$G$6,D11)))/(Params!$G$6-Params!$G$5)*100,""),"") -> 97.842947 | J11: =IF(ISNUMBER(E11),IFERROR((MAX(Params!$G$7,MIN(Params!$G$8,E11))-Params!$G$7)/(Params!$G$8-Params!$G$7)*100,""),"") -> 73.276162 | K11: =IF(ISNUMBER(F11),IFERROR((MAX(Params!$G$9,MIN(Params!$G$10,F11))-Params!$G$9)/(Params!$G$10-Params!$G$9)*100,""),"") -> 19.986153 | L11: =IF(ISNUMBER(G11),IFERROR((Params!$G$12-MAX(Params!$G$11,MIN(Params!$G$12,G11)))/(Params!$G$12-Params!$G$11)*100,""),"") -> 100 | M11: =IF(COUNT(J11:L11)=3,SUMPRODUCT(J11:L11,$J$2:$L$2),"") -> 66.642502
A12: Chile | B12: CHL | C12: =_xlfn.XLOOKUP($B12,[1]pillars_WIP!$B$7:$B$301,[1]pillars_WIP!$C$7:$C$301,"Missing",0) -> 3117 | D12: =_xlfn.XLOOKUP($B12,[1]pillars_WIP!$B$7:$B$301,[1]pillars_WIP!$D$7:$D$301,"Missing",0) -> 15.3 | E12: =_xlfn.XLOOKUP($B12,[1]pillars_WIP!$B$7:$B$301,[1]pillars_WIP!$E$7:$E$301,"Missing",0) -> 70.04 | F12: =_xlfn.XLOOKUP($B12,[1]pillars_WIP!$B$7:$B$301,[1]pillars_WIP!$F$7:$F$301,"Missing",0) -> 34.55 | G12: =_xlfn.XLOOKUP($B12,[1]pillars_WIP!$B$7:$B$301,[1]pillars_WIP!$G$7:$G$301,"Missing",0) -> 259.87 | H12: =IF(ISNUMBER(C12),IF(C12>0,"Yes","No"),"No") -> Yes | I12: =IF(ISNUMBER(D12),IFERROR((Params!$G$6-MAX(Params!$G$5,MIN(Params!$G$6,D12)))/(Params!$G$6-Params!$G$5)*100,""),"") -> 84.088706 | J12: =IF(ISNUMBER(E12),IFERROR((MAX(Params!$G$7,MIN(Params!$G$8,E12))-Params!$G$7)/(Params!$G$8-Params!$G$7)*100,""),"") -> 79.962916 | K12: =IF(ISNUMBER(F12),IFERROR((MAX(Params!$G$9,MIN(Params!$G$10,F12))-Params!$G$9)/(Params!$G$10-Params!$G$9)*100,""),"") -> 79.344565 | L12: =IF(ISNUMBER(G12),IFERROR((Params!$G$12-MAX(Params!$G$11,MIN(Params!$G$12,G12)))/(Params!$G$12-Params!$G$11)*100,""),"") -> 92.381775 | M12: =IF(COUNT(J12:L12)=3,SUMPRODUCT(J12:L12,$J$2:$L$2),"") -> 84.124011
A13: China | B13: CHN | C13: =_xlfn.XLOOKUP($B13,[1]pillars_WIP!$B$7:$B$301,[1]pillars_WIP!$C$7:$C$301,"Missing",0) -> 1239021.8 | D13: =_xlfn.XLOOKUP($B13,[1]pillars_WIP!$B$7:$B$301,[1]pillars_WIP!$D$7:$D$301,"Missing",0) -> 57.77 | E13: =_xlfn.XLOOKUP($B13,[1]pillars_WIP!$B$7:$B$301,[1]pillars_WIP!$E$7:$E$301,"Missing",0) -> 33.7 | F13: =_xlfn.XLOOKUP($B13,[1]pillars_WIP!$B$7:$B$301,[1]pillars_WIP!$F$7:$F$301,"Missing",0) -> 18.2 | G13: =_xlfn.XLOOKUP($B13,[1]pillars_WIP!$B$7:$B$301,[1]pillars_WIP!$G$7:$G$301,"Missing",0) -> 555.4 | H13: =IF(ISNUMBER(C13),IF(C13>0,"Yes","No"),"No") -> Yes | I13: =IF(ISNUMBER(D13),IFERROR((Params!$G$6-MAX(Params!$G$5,MIN(Params!$G$6,D13)))/(Params!$G$6-Params!$G$5)*100,""),"") -> 32.622395 | J13: =IF(ISNUMBER(E13),IFERROR((MAX(Params!$G$7,MIN(Params!$G$8,E13))-Params!$G$7)/(Params!$G$8-Params!$G$7)*100,""),"") -> 37.849113 | K13: =IF(ISNUMBER(F13),IFERROR((MAX(Params!$G$9,MIN(Params!$G$10,F13))-Params!$G$9)/(Params!$G$10-Params!$G$9)*100,""),"") -> 41.610893 | L13: =IF(ISNUMBER(G13),IFERROR((Params!$G$12-MAX(Params!$G$11,MIN(Params!$G$12,G13)))/(Params!$G$12-Params!$G$11)*100,""),"") -> 35.344241 | M13: =IF(COUNT(J13:L13)=3,SUMPRODUCT(J13:L13,$J$2:$L$2),"") -> 38.100942
A14: Czech Republic | B14: CZE | C14: =_xlfn.XLOOKUP($B14,[1]pillars_WIP!$B$7:$B$301,[1]pillars_WIP!$C$7:$C$301,"Missing",0) -> 6803.6 | D14: =_xlfn.XLOOKUP($B14,[1]pillars_WIP!$B$7:$B$301,[1]pillars_WIP!$D$7:$D$301,"Missing",0) -> 36.42 | E14: =_xlfn.XLOOKUP($B14,[1]pillars_WIP!$B$7:$B$301,[1]pillars_WIP!$E$7:$E$301,"Missing",0) -> 16.89 | F14: =_xlfn.XLOOKUP($B14,[1]pillars_WIP!$B$7:$B$301,[1]pillars_WIP!$F$7:$F$301,"Missing",0) -> 5.85 | G14: =_xlfn.XLOOKUP($B14,[1]pillars_WIP!$B$7:$B$301,[1]pillars_WIP!$G$7:$G$301,"Missing",0) -> 414.23 | H14: =IF(ISNUMBER(C14),IF(C14>0,"Yes","No"),"No") -> Yes | I14: =IF(ISNUMBER(D14),IFERROR((Params!$G$6-MAX(Params!$G$5,MIN(Params!$G$6,D14)))/(Params!$G$6-Params!$G$5)*100,""),"") -> 58.49491 | J14: =IF(ISNUMBER(E14),IFERROR((MAX(Params!$G$7,MIN(Params!$G$8,E14))-Params!$G$7)/(Params!$G$8-Params!$G$7)*100,""),"") -> 18.368293 | K14: =IF(ISNUMBER(F14),IFERROR((MAX(Params!$G$9,MIN(Params!$G$10,F14))-Params!$G$9)/(Params!$G$10-Params!$G$9)*100,""),"") -> 13.108701 | L14: =IF(ISNUMBER(G14),IFERROR((Params!$G$12-MAX(Params!$G$11,MIN(Params!$G$12,G14)))/(Params!$G$12-Params!$G$11)*100,""),"") -> 62.590168 | M14: =IF(COUNT(J14:L14)=3,SUMPRODUCT(J14:L14,$J$2:$L$2),"") -> 32.268071
